Workbook

Sheet RESUMEN
A1: HISTORIAL DE PRECIOS DE PROVEEDORES — CONSOLIDADO
A2: Dic 2024 → Jul 2026 · fuente: 12 tablas mensuales de órdenes + historial previo · generado 12/08/2026
A4: TIPO DE CAMBIO (MXN por USD): | B4: 20 | C4: ← editable; las columnas MXN de todas las hojas usan esta celda
A6: PROVEEDOR | B6: HOJA | C6: ÓRDENES | D6: PRIMERA ORDEN | E6: ÚLTIMA ORDEN | F6: SKUs DISTINTOS | G6: LÍNEAS | H6: PIEZAS
A7: HAIFENG | B7: HAIFENG | C7: 13 | D7: 2025-09-01 | E7: 2026-06-16 | F7: 1015 | G7: 2601 | H7: 8885
A8: ZOEY | B8: ZOEY | C8: 11 | D8: 2025-09-01 | E8: 2026-06-08 | F8: 468 | G8: 1020 | H8: 2589
A9: CYNTHIA | B9: CYNTHIA CAO | C9: 8 | D9: 2025-09-05 | E9: 2026-07-07 | F9: 361 | G9: 905 | H9: 2759
A10: NANCY | B10: NANCY VIP | C10: 7 | D10: 2025-09-06 | E10: 2026-07-09 | F10: 305 | G10: 582 | H10: 2230
A11: DINA DU | B11: DINA DU | C11: 5 | D11: 2024-12-01 | E11: 2026-04-27 | F11: 85 | G11: 106 | H11: 377
A12: COCOMA | B12: COCOMA | C12: 2 | D12: 2025-05-01 | E12: 2026-01-20 | F12: 51 | G12: 73 | H12: 368
A13: MOLLY | B13: MOLLY | C13: 1 | D13: 2025-10-10 | E13: 2025-10-10 | F13: 19 | G13: 19 | H13: 38
A14: COCO ZHANG | B14: COCO ZHANG | C14: 1 | D14: 2026-02-16 | E14: 2026-02-16 | F14: 13 | G14: 13 | H14: 20
A15: TOTAL | C15: =SUM(C7:C14) | F15: =SUM(F7:F14) | G15: =SUM(G7:G14) | H15: =SUM(H7:H14)
A17: CÓMO LEER LAS HOJAS DE PROVEEDOR:
A18: • Una fila por SKU. Cada columna de orden muestra el COSTO UNITARIO (USD) pagado en esa orden; celda vacía = no se ordenó.
A19: • MEJOR (US) = mínimo histórico · ÚLTIMA (US) = costo de la orden más reciente · MXN = MEJOR × tipo de cambio (celda B4).
A20: • Columnas marcadas con * vienen del historial previo (órdenes que no están en las tablas mensuales: CYNTHIA 07/07/26, ZOEY dic 25, DINA DU orden 1046 dic 24/ene 25).
A21: • CYNTHIA: desde abril 2026 cambió el método (precio de lista + descuento sobre el total). La columna "MEJOR DESDE ABR ★" es la referencia real.
A22: • NANCY 09/07/2026: se usaron los costos de la tabla mensual de julio (con descuento), no los del historial viejo.
A23: • La hoja TODAS LAS ORDENES tiene el detalle línea por línea (cantidad, costos con envío/comisiones, ROAS y precio de venta al momento de la orden).
A24: • De los dos archivos de FEBRERO 2026 se usó la versión "(1)", que incluye la orden COCO ZHANG 16/02/2026 que falta en el otro.

Sheet ALERTA ROAS
A1: ALERTA ROAS — PRODUCTOS VENDIÉNDOSE POR DEBAJO DE 3.5× SU COSTO
A2: 40 CRÍTICOS (precio < 2.5× costo) y 194 en PELIGRO (2.5×–3.5×) de 2,191 SKUs cruzados con Shopify el 12/08/2026. Costo = COSTO UNIT TOTAL (MXN) de la última orden (incluye envío, comisión Alibaba y Shop&Cross).
A3: MÚLTIPLO = precio Shopify ÷ costo. Con múltiplo < 2.5 la publicidad casi seguro pierde dinero; entre 2.5 y 3.5 el margen es frágil.
A5: ESTADO | B5: SKU | C5: PRODUCTO (Shopify) | D5: VARIANTE | E5: PROVEEDOR | F5: ÚLT. ORDEN | G5: COSTO UNIT TOTAL (MXN) | H5: PRECIO SHOPIFY (MXN) | I5: MÚLTIPLO | J5: PRECIO MÍN ROAS 2.5 | K5: PRECIO ROAS 3.5 | L5: PRECIO ROAS 4 | M5: STATUS | N5: INVENTARIO
A6: CRÍTICO (<2.5) | B6: 94530225617804 | C6: ARETES TRIBALES CD | D6: Default Title | E6: CYNTHIA | F6: 2025-09-05 | G6: 221.58 | H6: 250 | I6: =IF(G6=0,"",H6/G6) | J6: =ROUND(G6*2.5,0) | K6: =ROUND(G6*3.5,0) | L6: =ROUND(G6*4,0) | M6: DRAFT | N6: 2
A7: CRÍTICO (<2.5) | B7: 11915825763755 | C7: TRAJE DE BAÑO C | D7: L | E7: CYNTHIA | F7: 2026-04-27 | G7: 830.4 | H7: 1099 | I7: =IF(G7=0,"",H7/G7) | J7: =ROUND(G7*2.5,0) | K7: =ROUND(G7*3.5,0) | L7: =ROUND(G7*4,0) | M7: ACTIVE | N7: 0
A8: CRÍTICO (<2.5) | B8: 68802901471244 | C8: BOLSO LV MESSENGER | D8: 30cm de largo x 20cm de alto x 10 cm de ancho | E8: ZOEY | F8: 2026-03-02 | G8: 1261.29 | H8: 1900 | I8: =IF(G8=0,"",H8/G8) | J8: =ROUND(G8*2.5,0) | K8: =ROUND(G8*3.5,0) | L8: =ROUND(G8*4,0) | M8: ACTIVE | N8: 3
A9: CRÍTICO (<2.5) | B9: 85887252483277 | C9: CHAMARRA BLACK JW | D9: L | E9: MOLLY | F9: 2025-10-10 | G9: 594.3 | H9: 899 | I9: =IF(G9=0,"",H9/G9) | J9: =ROUND(G9*2.5,0) | K9: =ROUND(G9*3.5,0) | L9: =ROUND(G9*4,0) | M9: ACTIVE | N9: 0
A10: CRÍTICO (<2.5) | B10: 43728085695276 | C10: BOLSO F FENDIGRAPHY BLACK | D10: 14cm de largo x 11cm de alto x 4cm de ancho | E10: ZOEY | F10: 2025-09-01 | G10: 1255.89 | H10: 2050 | I10: =IF(G10=0,"",H10/G10) | J10: =ROUND(G10*2.5,0) | K10: =ROUND(G10*3.5,0) | L10: =ROUND(G10*4,0) | M10: ACTIVE | N10: 0
A11: CRÍTICO (<2.5) | B11: 41889241004845 | C11: CHOKER KNOT ZIRCONIAS GOLD | D11: Default Title | E11: CYNTHIA | F11: 2025-10-25 | G11: 518.8 | H11: 866 | I11: =IF(G11=0,"",H11/G11) | J11: =ROUND(G11*2.5,0) | K11: =ROUND(G11*3.5,0) | L11: =ROUND(G11*4,0) | M11: ACTIVE | N11: 1
A12: CRÍTICO (<2.5) | B12: 85887251827853 | C12: CAMISETA BLUE JW | D12: L | E12: MOLLY | F12: 2025-10-10 | G12: 405.73 | H12: 676 | I12: =IF(G12=0,"",H12/G12) | J12: =ROUND(G12*2.5,0) | K12: =ROUND(G12*3.5,0) | L12: =ROUND(G12*4,0) | M12: ACTIVE | N12: 1
A13: CRÍTICO (<2.5) | B13: 14679511089581 | C13: PULSERA H SILVER | D13: Default Title | E13: HAIFENG | F13: 2026-04-16 | G13: 273.2 | H13: 460 | I13: =IF(G13=0,"",H13/G13) | J13: =ROUND(G13*2.5,0) | K13: =ROUND(G13*3.5,0) | L13: =ROUND(G13*4,0) | M13: ACTIVE | N13: 2
A14: CRÍTICO (<2.5) | B14: 95383471436684 | C14: HOODIE C BLACK | D14: L | E14: DINA DU | F14: 2025-10-21 | G14: 756.93 | H14: 1285 | I14: =IF(G14=0,"",H14/G14) | J14: =ROUND(G14*2.5,0) | K14: =ROUND(G14*3.5,0) | L14: =ROUND(G14*4,0) | M14: ACTIVE | N14: 1
A15: CRÍTICO (<2.5) | B15: 37309581067981 | C15: HOODIE ALLS BLACK | D15: M | E15: ZOEY | F15: 2025-10-02 | G15: 826.84 | H15: 1449 | I15: =IF(G15=0,"",H15/G15) | J15: =ROUND(G15*2.5,0) | K15: =ROUND(G15*3.5,0) | L15: =ROUND(G15*4,0) | M15: ACTIVE | N15: 1
A16: CRÍTICO (<2.5) | B16: 85887251331053 | C16: SUDADERA ZIPPER BEIGE JW | D16: M | E16: MOLLY | F16: 2025-10-10 | G16: 540.02 | H16: 950 | I16: =IF(G16=0,"",H16/G16) | J16: =ROUND(G16*2.5,0) | K16: =ROUND(G16*3.5,0) | L16: =ROUND(G16*4,0) | M16: ACTIVE | N16: 0
A17: CRÍTICO (<2.5) | B17: 42981601575052 | C17: ANILLO ESSENTIAL V PERLE | D17: Default Title | E17: NANCY | F17: 2026-07-09 | G17: 136.2 | H17: 250 | I17: =IF(G17=0,"",H17/G17) | J17: =ROUND(G17*2.5,0) | K17: =ROUND(G17*3.5,0) | L17: =ROUND(G17*4,0) | M17: ACTIVE | N17: 0
... A47: PELIGRO (<3.5) | B47: 12314361636973 | C47: ANILLO F SILVER ZIRCONIAS | D47: 9 | E47: HAIFENG | F47: 2025-10-22 | G47: 147.9 | H47: 374 | I47: =IF(G47=0,"",H47/G47) | J47: =ROUND(G47*2.5,0) | K47: =ROUND(G47*3.5,0) | L47: =ROUND(G47*4,0) | M47: ACTIVE | N47: 2
A48: PELIGRO (<3.5) | B48: 89790741803853 | C48: COLLAR BV SILVER GRABADO CON ZIRCONIA | E48: HAIFENG | F48: 2025-09-25 | G48: 147.68 | H48: 375 | I48: =IF(G48=0,"",H48/G48) | J48: =ROUND(G48*2.5,0) | K48: =ROUND(G48*3.5,0) | L48: =ROUND(G48*4,0) | M48: ACTIVE | N48: 1
A49: PELIGRO (<3.5) | B49: 89790741914029 | C49: COLLAR BV ROSEGOLD GRABADO CON ZIRCONIA | D49: Default Title | E49: HAIFENG | F49: 2025-09-25 | G49: 147.68 | H49: 375 | I49: =IF(G49=0,"",H49/G49) | J49: =ROUND(G49*2.5,0) | K49: =ROUND(G49*3.5,0) | L49: =ROUND(G49*4,0) | M49: ACTIVE | N49: 3
A50: PELIGRO (<3.5) | B50: 16117871480237 | C50: PULSERA KNOT ONE ROSEGOLD CON ZIRCONIA | D50: Default Title | E50: HAIFENG | F50: 2025-09-25 | G50: 210.97 | H50: 535 | I50: =IF(G50=0,"",H50/G50) | J50: =ROUND(G50*2.5,0) | K50: =ROUND(G50*3.5,0) | L50: =ROUND(G50*4,0) | M50: ACTIVE | N50: 2
A51: PELIGRO (<3.5) | B51: 30410821083277 | C51: PULSERA KNOT ONE GOLD CON ZIRCONIA | D51: Default Title | E51: HAIFENG | F51: 2025-09-25 | G51: 210.97 | H51: 535 | I51: =IF(G51=0,"",H51/G51) | J51: =ROUND(G51*2.5,0) | K51: =ROUND(G51*3.5,0) | L51: =ROUND(G51*4,0) | M51: ACTIVE | N51: 1
A52: PELIGRO (<3.5) | B52: 17964141887725 | C52: LENTES CD LINK A1U | D52: Default Title | E52: HAIFENG | F52: 2026-05-06 | G52: 742.65 | H52: 1884 | I52: =IF(G52=0,"",H52/G52) | J52: =ROUND(G52*2.5,0) | K52: =ROUND(G52*3.5,0) | L52: =ROUND(G52*4,0) | M52: ACTIVE | N52: 2
A53: PELIGRO (<3.5) | B53: 34361211039213 | C53: PULSERA DIVAS DREAM SILVER | D53: Default Title | E53: HAIFENG | F53: 2026-04-16 | G53: 157.74 | H53: 403 | I53: =IF(G53=0,"",H53/G53) | J53: =ROUND(G53*2.5,0) | K53: =ROUND(G53*3.5,0) | L53: =ROUND(G53*4,0) | M53: ACTIVE | N53: 3
A54: PELIGRO (<3.5) | B54: 35432871939597 | C54: ARETES H MINI MAILLON ROSE GOLD-WHITE | D54: Default Title | E54: HAIFENG | F54: 2026-02-05 | G54: 190.05 | H54: 487 | I54: =IF(G54=0,"",H54/G54) | J54: =ROUND(G54*2.5,0) | K54: =ROUND(G54*3.5,0) | L54: =ROUND(G54*4,0) | M54: ACTIVE | N54: 3
A55: PELIGRO (<3.5) | B55: 85887252166317 | C55: SUETER GREY CASHMERE | D55: L | E55: MOLLY | F55: 2025-10-10 | G55: 500.02 | H55: 1283.24 | I55: =IF(G55=0,"",H55/G55) | J55: =ROUND(G55*2.5,0) | K55: =ROUND(G55*3.5,0) | L55: =ROUND(G55*4,0) | M55: ACTIVE | N55: 0
A56: PELIGRO (<3.5) | B56: 85887252087757 | C56: SUETER BONE JW | D56: L | E56: MOLLY | F56: 2025-10-10 | G56: 500.02 | H56: 1283.24 | I56: =IF(G56=0,"",H56/G56) | J56: =ROUND(G56*2.5,0) | K56: =ROUND(G56*3.5,0) | L56: =ROUND(G56*4,0) | M56: ACTIVE | N56: 1
A57: PELIGRO (<3.5) | B57: 42834319871628 | C57: SANDALIAS DG | D57: 27cm | E57: ZOEY | F57: 2026-06-08 | G57: 980.46 | H57: 2534 | I57: =IF(G57=0,"",H57/G57) | J57: =ROUND(G57*2.5,0) | K57: =ROUND(G57*3.5,0) | L57: =ROUND(G57*4,0) | M57: ACTIVE | N57: 1
A58: PELIGRO (<3.5) | B58: 61744051068109 | C58: PULSERA CD GOLD CON ZIRCONIA | D58: Default Title | E58: ZOEY | F58: 2026-01-20 | G58: 468.57 | H58: 1218 | I58: =IF(G58=0,"",H58/G58) | J58: =ROUND(G58*2.5,0) | K58: =ROUND(G58*3.5,0) | L58: =ROUND(G58*4,0) | M58: ACTIVE | N58: 6
A59: PELIGRO (<3.5) | B59: 48915671144269 | C59: CAMISETA CD OBLIQUE BLACK | D59: M OVERSIZE | E59: ZOEY | F59: 2026-04-20 | G59: 691.44 | H59: 1799 | I59: =IF(G59=0,"",H59/G59) | J59: =ROUND(G59*2.5,0) | K59: =ROUND(G59*3.5,0) | L59: =ROUND(G59*4,0) | M59: ACTIVE | N59: 2
A60: PELIGRO (<3.5) | B60: 48915671011501 | C60: CAMISETA CD OBLIQUE BLACK | D60: L OVERSIZE | E60: ZOEY | F60: 2026-04-20 | G60: 691.44 | H60: 1799 | I60: =IF(G60=0,"",H60/G60) | J60: =ROUND(G60*2.5,0) | K60: =ROUND(G60*3.5,0) | L60: =ROUND(G60*4,0) | M60: ACTIVE | N60: 1
A61: PELIGRO (<3.5) | B61: 15565825325196 | C61: CARTERA GC BI-FOLD | D61: 9.5cm x 10cm | E61: ZOEY | F61: 2026-03-19 | G61: 464.08 | H61: 1208 | I61: =IF(G61=0,"",H61/G61) | J61: =ROUND(G61*2.5,0) | K61: =ROUND(G61*3.5,0) | L61: =ROUND(G61*4,0) | M61: ACTIVE | N61: 4
A62: PELIGRO (<3.5) | B62: 63794531345773 | C62: LENTES CD SIGNATURE B8U | E62: ZOEY | F62: 2026-03-02 | G62: 840.86 | H62: 2187 | I62: =IF(G62=0,"",H62/G62) | J62: =ROUND(G62*2.5,0) | K62: =ROUND(G62*3.5,0) | L62: =ROUND(G62*4,0) | M62: ACTIVE | N62: 1
A63: PELIGRO (<3.5) | B63: 23025461332941 | C63: TENIS H BOUNCING WHITE | D63: 42/8MX | E63: ZOEY | F63: 2026-05-15 | G63: 1590.28 | H63: 4139 | I63: =IF(G63=0,"",H63/G63) | J63: =ROUND(G63*2.5,0) | K63: =ROUND(G63*3.5,0) | L63: =ROUND(G63*4,0) | M63: ACTIVE | N63: 1
A64: PELIGRO (<3.5) | B64: 23025461724461 | C64: MOCASINES GC HORSEBIT | D64: 42/8MX | E64: ZOEY | F64: 2026-05-15 | G64: 1537.27 | H64: 3997 | I64: =IF(G64=0,"",H64/G64) | J64: =ROUND(G64*2.5,0) | K64: =ROUND(G64*3.5,0) | L64: =ROUND(G64*4,0) | M64: ACTIVE | N64: 1
A65: PELIGRO (<3.5) | B65: 23025461857229 | C65: MOCASINES GC HORSEBIT | D65: 44/9MX | E65: ZOEY | F65: 2026-05-15 | G65: 1537.27 | H65: 3997 | I65: =IF(G65=0,"",H65/G65) | J65: =ROUND(G65*2.5,0) | K65: =ROUND(G65*3.5,0) | L65: =ROUND(G65*4,0) | M65: ACTIVE | N65: 1
A66: PELIGRO (<3.5) | B66: 69645921049005 | C66: PULSERA YSL GOLD | D66: Default Title | E66: NANCY | F66: 2026-07-09 | G66: 145.95 | H66: 380 | I66: =IF(G66=0,"",H66/G66) | J66: =ROUND(G66*2.5,0) | K66: =ROUND(G66*3.5,0) | L66: =ROUND(G66*4,0) | M66: ACTIVE | N66: 0
A67: PELIGRO (<3.5) | B67: 61050601014957 | C67: LEGGINGS LLM BLACK | D67: 2M ,1L | E67: ZOEY | F67: 2026-05-15 | G67: 662.62 | H67: 1729 | I67: =IF(G67=0,"",H67/G67) | J67: =ROUND(G67*2.5,0) | K67: =ROUND(G67*3.5,0) | L67: =ROUND(G67*4,0) | M67: ACTIVE | N67: 4
A68: PELIGRO (<3.5) | B68: 39252671462093 | C68: LENTES GC 1SN BLACK | D68: Default Title | E68: CYNTHIA | F68: 2025-10-25 | G68: 943.27 | H68: 2461 | I68: =IF(G68=0,"",H68/G68) | J68: =ROUND(G68*2.5,0) | K68: =ROUND(G68*3.5,0) | L68: =ROUND(G68*4,0) | M68: ACTIVE | N68: 2
A69: PELIGRO (<3.5) | B69: 29736662528589 | C69: ANILLO OPEN HEART SILVER | D69: 7 | E69: HAIFENG | F69: 2026-02-05 | G69: 149.27 | H69: 389 | I69: =IF(G69=0,"",H69/G69) | J69: =ROUND(G69*2.5,0) | K69: =ROUND(G69*3.5,0) | L69: =ROUND(G69*4,0) | M69: ACTIVE | N69: 1
A70: PELIGRO (<3.5) | B70: 44504631084621 | C70: BOLSO C TILLY BROWN | D70: 15cm de alto x 19.5cm de largo x 7.5cm de ancho | E70: DINA DU | F70: 2025-10-21 | G70: 1177.45 | H70: 3076.23 | I70: =IF(G70=0,"",H70/G70) | J70: =ROUND(G70*2.5,0) | K70: =ROUND(G70*3.5,0) | L70: =ROUND(G70*4,0) | M70: ACTIVE | N70: 1
A71: PELIGRO (<3.5) | B71: 64e78f941b012 | C71: BOLSO V WHITE | D71: 20.5cmx14cm | E71: DINA DU | F71: 2025-10-21 | G71: 1289.59 | H71: 3369 | I71: =IF(G71=0,"",H71/G71) | J71: =ROUND(G71*2.5,0) | K71: =ROUND(G71*3.5,0) | L71: =ROUND(G71*4,0) | M71: ACTIVE | N71: 0
A72: PELIGRO (<3.5) | B72: 648cc60ce32b1 | C72: CARTERA LV BROWN | D72: 12cmx9cm | E72: DINA DU | F72: 2026-04-27 | G72: 351.58 | H72: 916 | I72: =IF(G72=0,"",H72/G72) | J72: =ROUND(G72*2.5,0) | K72: =ROUND(G72*3.5,0) | L72: =ROUND(G72*4,0) | M72: ACTIVE | N72: 2
A73: PELIGRO (<3.5) | B73: 42265107366028 | C73: HOODIE C BLACK | D73: M | E73: DINA DU | F73: 2025-10-21 | G73: 756.93 | H73: 1977 | I73: =IF(G73=0,"",H73/G73) | J73: =ROUND(G73*2.5,0) | K73: =ROUND(G73*3.5,0) | L73: =ROUND(G73*4,0) | M73: ACTIVE | N73: 3
A74: PELIGRO (<3.5) | B74: 665bd49b4a58a | C74: TARJETERO LV BLUE | D74: 8cm x 11cm | E74: DINA DU | F74: 2025-10-21 | G74: 476.59 | H74: 1245 | I74: =IF(G74=0,"",H74/G74) | J74: =ROUND(G74*2.5,0) | K74: =ROUND(G74*3.5,0) | L74: =ROUND(G74*4,0) | M74: ACTIVE | N74: 7
... A138: PELIGRO (<3.5) | B138: 64e78e7b03ab1 | C138: ANILLO BV 3 OROS | D138: 8 | E138: HAIFENG | F138: 2025-09-25 | G138: 168.78 | H138: 520 | I138: =IF(G138=0,"",H138/G138) | J138: =ROUND(G138*2.5,0) | K138: =ROUND(G138*3.5,0) | L138: =ROUND(G138*4,0) | M138: ACTIVE | N138: 0
A139: PELIGRO (<3.5) | B139: 29953903326061 | C139: BOLSO YSL GABY VANITY | E139: ZOEY | F139: 2026-06-08 | G139: 1299.11 | H139: 3999 | I139: =IF(G139=0,"",H139/G139) | J139: =ROUND(G139*2.5,0) | K139: =ROUND(G139*3.5,0) | L139: =ROUND(G139*4,0) | M139: ACTIVE | N139: 0
A140: PELIGRO (<3.5) | B140: 24469401092557 | C140: UGG PANTUFLAS TAZZ II | D140: 24CM | E140: CYNTHIA | F140: 2025-10-25 | G140: 838.46 | H140: 2592 | I140: =IF(G140=0,"",H140/G140) | J140: =ROUND(G140*2.5,0) | K140: =ROUND(G140*3.5,0) | L140: =ROUND(G140*4,0) | M140: ACTIVE | N140: 4
A141: PELIGRO (<3.5) | B141: 43047219789964 | C141: PULSERA ONE T CON ZIRCONIA SILVER | D141: 16.58cm | E141: CYNTHIA | F141: 2025-09-05 | G141: 372.65 | H141: 1150 | I141: =IF(G141=0,"",H141/G141) | J141: =ROUND(G141*2.5,0) | K141: =ROUND(G141*3.5,0) | L141: =ROUND(G141*4,0) | M141: ACTIVE | N141: 1
A142: PELIGRO (<3.5) | B142: 665bce4734fce | C142: PULSERA PERLEÉ ROSEGOLD | D142: 16cm | E142: NANCY | F142: 2026-07-09 | G142: 277.52 | H142: 860 | I142: =IF(G142=0,"",H142/G142) | J142: =ROUND(G142*2.5,0) | K142: =ROUND(G142*3.5,0) | L142: =ROUND(G142*4,0) | M142: ACTIVE | N142: 0
A143: PELIGRO (<3.5) | B143: 85563421017997 | C143: COLLAR LV INSIGNIAS BLOSSOM GOLD BLACK | D143: Default Title | E143: ZOEY | F143: 2025-10-02 | G143: 259.86 | H143: 807 | I143: =IF(G143=0,"",H143/G143) | J143: =ROUND(G143*2.5,0) | K143: =ROUND(G143*3.5,0) | L143: =ROUND(G143*4,0) | M143: ACTIVE | N143: 1
A144: PELIGRO (<3.5) | B144: 24469411303885 | C144: BOLSO CC CLASIC NUDE | D144: Default Title | E144: CYNTHIA | F144: 2025-10-25 | G144: 1414.9 | H144: 4449 | I144: =IF(G144=0,"",H144/G144) | J144: =ROUND(G144*2.5,0) | K144: =ROUND(G144*3.5,0) | L144: =ROUND(G144*4,0) | M144: ACTIVE | N144: 0
A145: PELIGRO (<3.5) | B145: 42981877514380 | C145: COLLAR LOCK CON ZIRCONIAS SILVER | D145: Default Title | E145: NANCY | F145: 2026-05-31 | G145: 208.46 | H145: 655 | I145: =IF(G145=0,"",H145/G145) | J145: =ROUND(G145*2.5,0) | K145: =ROUND(G145*3.5,0) | L145: =ROUND(G145*4,0) | M145: ACTIVE | N145: 5
A146: PELIGRO (<3.5) | B146: 24072851105773 | C146: BOLSO CC MINI KELLY BLACK | D146: Default Title | E146: CYNTHIA | F146: 2026-04-27 | G146: 1375.35 | H146: 4350 | I146: =IF(G146=0,"",H146/G146) | J146: =ROUND(G146*2.5,0) | K146: =ROUND(G146*3.5,0) | L146: =ROUND(G146*4,0) | M146: ACTIVE | N146: 0
A147: PELIGRO (<3.5) | B147: 83844901025261 | C147: PULSERA DE TELA F GOLD BLACK | D147: Default Title | E147: ZOEY | F147: 2025-10-02 | G147: 188.99 | H147: 599 | I147: =IF(G147=0,"",H147/G147) | J147: =ROUND(G147*2.5,0) | K147: =ROUND(G147*3.5,0) | L147: =ROUND(G147*4,0) | M147: ACTIVE | N147: 0
A148: PELIGRO (<3.5) | B148: 15711172277517 | C148: ARETES CD SADDLE GOLD | D148: 3 cm | E148: CYNTHIA | F148: 2025-10-25 | G148: 183.41 | H148: 582.47 | I148: =IF(G148=0,"",H148/G148) | J148: =ROUND(G148*2.5,0) | K148: =ROUND(G148*3.5,0) | L148: =ROUND(G148*4,0) | M148: ACTIVE | N148: 3
A149: PELIGRO (<3.5) | B149: 41889241640397 | C149: ANILLO CD ZIRCONIAS GOLD-BLACK | D149: 8 | E149: CYNTHIA | F149: 2025-10-25 | G149: 248.92 | H149: 790.5 | I149: =IF(G149=0,"",H149/G149) | J149: =ROUND(G149*2.5,0) | K149: =ROUND(G149*3.5,0) | L149: =ROUND(G149*4,0) | M149: ACTIVE | N149: 0
A150: PELIGRO (<3.5) | B150: 39252671591341 | C150: GORRA LULU WHITE | D150: Default Title | E150: CYNTHIA | F150: 2025-10-25 | G150: 282.98 | H150: 898.67 | I150: =IF(G150=0,"",H150/G150) | J150: =ROUND(G150*2.5,0) | K150: =ROUND(G150*3.5,0) | L150: =ROUND(G150*4,0) | M150: ACTIVE | N150: 1
A151: PELIGRO (<3.5) | B151: 42981955928204 | C151: ANILLO TB SILVER | D151: 8 | E151: NANCY | F151: 2026-05-08 | G151: 70.74 | H151: 225 | I151: =IF(G151=0,"",H151/G151) | J151: =ROUND(G151*2.5,0) | K151: =ROUND(G151*3.5,0) | L151: =ROUND(G151*4,0) | M151: ACTIVE | N151: 4
... A225: PELIGRO (<3.5) | B225: 43728084530892 | C225: SUÉTER PR MILANO WHITE | D225: M | E225: ZOEY | F225: 2026-06-08 | G225: 931.43 | H225: 3260 | I225: =IF(G225=0,"",H225/G225) | J225: =ROUND(G225*2.5,0) | K225: =ROUND(G225*3.5,0) | L225: =ROUND(G225*4,0) | M225: ACTIVE | N225: 0
A226: PELIGRO (<3.5) | B226: 24780441331117 | C226: BOLSO LV NANO DIANE MONOGRAM | E226: ZOEY | F226: 2026-06-08 | G226: 931.43 | H226: 3260 | I226: =IF(G226=0,"",H226/G226) | J226: =ROUND(G226*2.5,0) | K226: =ROUND(G226*3.5,0) | L226: =ROUND(G226*4,0) | M226: ACTIVE | N226: 0
A227: PELIGRO (<3.5) | B227: 62809482933772 | C227: BOLSO CD MESSENGER SADDLE BLUE | D227: 20cm de largo x 14cm de alto x 5cm de ancho | E227: CYNTHIA | F227: 2026-03-19 | G227: 1342.87 | H227: 4700 | I227: =IF(G227=0,"",H227/G227) | J227: =ROUND(G227*2.5,0) | K227: =ROUND(G227*3.5,0) | L227: =ROUND(G227*4,0) | M227: ACTIVE | N227: 2
A228: PELIGRO (<3.5) | B228: 43728082064620 | C228: BOLSO LW CHERRY | D228: 28cmx20cm | E228: CYNTHIA | F228: 2026-02-18 | G228: 2001.21 | H228: 6999 | I228: =IF(G228=0,"",H228/G228) | J228: =ROUND(G228*2.5,0) | K228: =ROUND(G228*3.5,0) | L228: =ROUND(G228*4,0) | M228: ACTIVE | N228: 4
A229: PELIGRO (<3.5) | B229: 43728071990540 | C229: BOLSO LW BLACK | D229: 28cm x 20cm | E229: CYNTHIA | F229: 2026-02-18 | G229: 2001.21 | H229: 6999 | I229: =IF(G229=0,"",H229/G229) | J229: =ROUND(G229*2.5,0) | K229: =ROUND(G229*3.5,0) | L229: =ROUND(G229*4,0) | M229: ACTIVE | N229: 4
A230: PELIGRO (<3.5) | B230: 64e78f9336406 | C230: BOLSO V BLACK | D230: 20.5cmx14cm | E230: DINA DU | F230: 2026-02-06 | G230: 1229.18 | H230: 4302.14 | I230: =IF(G230=0,"",H230/G230) | J230: =ROUND(G230*2.5,0) | K230: =ROUND(G230*3.5,0) | L230: =ROUND(G230*4,0) | M230: ACTIVE | N230: 2
A231: PELIGRO (<3.5) | B231: 67572cbd4a7ca | C231: BOLSO YSL CON CADENA BLACK | D231: 19cm de alto x 24cm de largo x 7cm de ancho | E231: DINA DU | F231: 2026-02-06 | G231: 1229.18 | H231: 4302.14 | I231: =IF(G231=0,"",H231/G231) | J231: =ROUND(G231*2.5,0) | K231: =ROUND(G231*3.5,0) | L231: =ROUND(G231*4,0) | M231: ACTIVE | N231: 1
A232: PELIGRO (<3.5) | B232: 85367152182925 | C232: BOLSO CC SHINY STAR BLACK | D232: BLACK/GOLD | E232: DINA DU | F232: 2026-02-06 | G232: 1496.4 | H232: 5237.39 | I232: =IF(G232=0,"",H232/G232) | J232: =ROUND(G232*2.5,0) | K232: =ROUND(G232*3.5,0) | L232: =ROUND(G232*4,0) | M232: ACTIVE | N232: 2
A233: PELIGRO (<3.5) | B233: 85367151372749 | C233: BOLSO CD MESSENGER SOLAPA | D233: BLACK | E233: DINA DU | F233: 2026-02-06 | G233: 1149.02 | H233: 4021.57 | I233: =IF(G233=0,"",H233/G233) | J233: =ROUND(G233*2.5,0) | K233: =ROUND(G233*3.5,0) | L233: =ROUND(G233*4,0) | M233: ACTIVE | N233: 0
A234: PELIGRO (<3.5) | B234: 19693770314380 | C234: BOLSO DE VIAJE BROWN LV | D234: HIGH QUALITY | E234: DINA DU | F234: 2026-04-27 | G234: 1703.79 | H234: 5963.27 | I234: =IF(G234=0,"",H234/G234) | J234: =ROUND(G234*2.5,0) | K234: =ROUND(G234*3.5,0) | L234: =ROUND(G234*4,0) | M234: ACTIVE | N234: 1
A235: PELIGRO (<3.5) | B235: 43409491041677 | C235: BOLSO YSL CON CADENA NUDE | D235: REGULAR | E235: DINA DU | F235: 2026-04-27 | G235: 1244.04 | H235: 4354.13 | I235: =IF(G235=0,"",H235/G235) | J235: =ROUND(G235*2.5,0) | K235: =ROUND(G235*3.5,0) | L235: =ROUND(G235*4,0) | M235: ACTIVE | N235: 2
A236: PELIGRO (<3.5) | B236: 67572cbe60534 | C236: BOLSO YSL CON CADENA OFF WHITE | D236: Middle Quality | E236: DINA DU | F236: 2026-04-27 | G236: 1244.04 | H236: 4354.13 | I236: =IF(G236=0,"",H236/G236) | J236: =ROUND(G236*2.5,0) | K236: =ROUND(G236*3.5,0) | L236: =ROUND(G236*4,0) | M236: ACTIVE | N236: 0
A237: PELIGRO (<3.5) | B237: 58071991054829 | C237: BOLSO YSL CON CADENA BURDEOS | D237: 24cm de largo x 18cm de alto x 8cm de ancho. | E237: DINA DU | F237: 2026-04-27 | G237: 1244.04 | H237: 4354.13 | I237: =IF(G237=0,"",H237/G237) | J237: =ROUND(G237*2.5,0) | K237: =ROUND(G237*3.5,0) | L237: =ROUND(G237*4,0) | M237: ACTIVE | N237: 0
A238: PELIGRO (<3.5) | B238: 10132411318605 | C238: BOLSO CD BOW BLACK | D238: Default Title | E238: DINA DU | F238: 2026-04-27 | G238: 1920.15 | H238: 6720.51 | I238: =IF(G238=0,"",H238/G238) | J238: =ROUND(G238*2.5,0) | K238: =ROUND(G238*3.5,0) | L238: =ROUND(G238*4,0) | M238: ACTIVE | N238: 0
A239: PELIGRO (<3.5) | B239: 10132411251373 | C239: BOLSO CD BOW BURGUNDY | D239: Default Title | E239: DINA DU | F239: 2026-04-27 | G239: 1920.15 | H239: 6720.51 | I239: =IF(G239=0,"",H239/G239) | J239: =ROUND(G239*2.5,0) | K239: =ROUND(G239*3.5,0) | L239: =ROUND(G239*4,0) | M239: ACTIVE | N239: 1

Sheet HAIFENG
A1: HISTORIAL DE PRECIOS — HAIFENG
A2: 13 orden(es) · costo unitario en USD · MXN = MEJOR × RESUMEN!B4 · * = dato del historial previo
A4: SKU | B4: PRODUCTO | C4: VARIANTE | D4: MATERIAL | E4: Sep 2025 01/09 | F4: Sep 2025 25/09 | G4: Oct 2025 22/10 | H4: Nov 2025 11/11 | I4: Dic 2025 03/12 | J4: Ene 2026 20/01 | K4: Feb 2026 05/02 | L4: Feb 2026 10/02 | M4: Mar 2026 11/03 | N4: Abr 2026 16/04 | O4: May 2026 06/05 | P4: May 2026 26/05 | Q4: Jun 2026 16/06 | R4: MEJOR (US) | S4: ÚLTIMA (US) | T4: MXN (mejor×TC) | U4: # ÓRD.
A5: 64085742311277 | B5: ANILLO ALLIANCE CON ZIRCONIA C | C5: 5 | F5: 2 | R5: =IF(COUNT(E5:Q5)=0,"",MIN(E5:Q5)) | S5: =IF(COUNT(E5:Q5)=0,"",LOOKUP(2,1/(E5:Q5<>""),E5:Q5)) | T5: =IF(R5="","",ROUND(R5*RESUMEN!$B$4,0)) | U5: =COUNT(E5:Q5)
A6: 64085742444045 | B6: ANILLO ALLIANCE CON ZIRCONIA C | C6: 6 | F6: 2 | R6: =IF(COUNT(E6:Q6)=0,"",MIN(E6:Q6)) | S6: =IF(COUNT(E6:Q6)=0,"",LOOKUP(2,1/(E6:Q6<>""),E6:Q6)) | T6: =IF(R6="","",ROUND(R6*RESUMEN!$B$4,0)) | U6: =COUNT(E6:Q6)
A7: 64085742576813 | B7: ANILLO ALLIANCE CON ZIRCONIA ROSE GOLD C | C7: 7 | D7: Stainless Stee | H7: 2 | I7: 2 | P7: 2 | R7: =IF(COUNT(E7:Q7)=0,"",MIN(E7:Q7)) | S7: =IF(COUNT(E7:Q7)=0,"",LOOKUP(2,1/(E7:Q7<>""),E7:Q7)) | T7: =IF(R7="","",ROUND(R7*RESUMEN!$B$4,0)) | U7: =COUNT(E7:Q7)
A8: 64085742794061 | B8: ANILLO ALLIANCE ROSE GOLD C | C8: 6 | F8: 2 | R8: =IF(COUNT(E8:Q8)=0,"",MIN(E8:Q8)) | S8: =IF(COUNT(E8:Q8)=0,"",LOOKUP(2,1/(E8:Q8<>""),E8:Q8)) | T8: =IF(R8="","",ROUND(R8*RESUMEN!$B$4,0)) | U8: =COUNT(E8:Q8)
A9: 64085742826829 | B9: ANILLO ALLIANCE ROSE GOLD C | C9: 7 | D9: Stainless Stee | P9: 2 | R9: =IF(COUNT(E9:Q9)=0,"",MIN(E9:Q9)) | S9: =IF(COUNT(E9:Q9)=0,"",LOOKUP(2,1/(E9:Q9<>""),E9:Q9)) | T9: =IF(R9="","",ROUND(R9*RESUMEN!$B$4,0)) | U9: =COUNT(E9:Q9)
A10: 66075791007693 | B10: ANILLO ALLIANCE SILVER C | C10: 7 | D10: Stainless Stee | H10: 2 | O10: 2 | R10: =IF(COUNT(E10:Q10)=0,"",MIN(E10:Q10)) | S10: =IF(COUNT(E10:Q10)=0,"",LOOKUP(2,1/(E10:Q10<>""),E10:Q10)) | T10: =IF(R10="","",ROUND(R10*RESUMEN!$B$4,0)) | U10: =COUNT(E10:Q10)
A11: 66075801140461 | B11: ANILLO ALLIANCE SILVER C | C11: 8 | H11: 2 | R11: =IF(COUNT(E11:Q11)=0,"",MIN(E11:Q11)) | S11: =IF(COUNT(E11:Q11)=0,"",LOOKUP(2,1/(E11:Q11<>""),E11:Q11)) | T11: =IF(R11="","",ROUND(R11*RESUMEN!$B$4,0)) | U11: =COUNT(E11:Q11)
A12: 66075801273229 | B12: ANILLO ALLIANCE SILVER C | C12: 9 | D12: Stainless stee | H12: 2 | I12: 2 | J12: 2 | N12: 2 | R12: =IF(COUNT(E12:Q12)=0,"",MIN(E12:Q12)) | S12: =IF(COUNT(E12:Q12)=0,"",LOOKUP(2,1/(E12:Q12<>""),E12:Q12)) | T12: =IF(R12="","",ROUND(R12*RESUMEN!$B$4,0)) | U12: =COUNT(E12:Q12)
A13: 67201533404653 | B13: ANILLO ANCHO TRUE T GOLD | C13: 6 | D13: Copper Alloy | Q13: 7 | R13: =IF(COUNT(E13:Q13)=0,"",MIN(E13:Q13)) | S13: =IF(COUNT(E13:Q13)=0,"",LOOKUP(2,1/(E13:Q13<>""),E13:Q13)) | T13: =IF(R13="","",ROUND(R13*RESUMEN!$B$4,0)) | U13: =COUNT(E13:Q13)
A14: 67201533537421 | B14: ANILLO ANCHO TRUE T GOLD | C14: 7 | E14: 7 | H14: 7 | I14: 7 | R14: =IF(COUNT(E14:Q14)=0,"",MIN(E14:Q14)) | S14: =IF(COUNT(E14:Q14)=0,"",LOOKUP(2,1/(E14:Q14<>""),E14:Q14)) | T14: =IF(R14="","",ROUND(R14*RESUMEN!$B$4,0)) | U14: =COUNT(E14:Q14)
A15: 67201533670189 | B15: ANILLO ANCHO TRUE T GOLD | C15: 8 | D15: Copper alloy | E15: 7 | I15: 7 | N15: 7 | R15: =IF(COUNT(E15:Q15)=0,"",MIN(E15:Q15)) | S15: =IF(COUNT(E15:Q15)=0,"",LOOKUP(2,1/(E15:Q15<>""),E15:Q15)) | T15: =IF(R15="","",ROUND(R15*RESUMEN!$B$4,0)) | U15: =COUNT(E15:Q15)
A16: 21605761269037 | B16: ANILLO BACK SOON T ROSE GOLD | C16: 5 | D16: Stainless stee | F16: 3 | N16: 3 | R16: =IF(COUNT(E16:Q16)=0,"",MIN(E16:Q16)) | S16: =IF(COUNT(E16:Q16)=0,"",LOOKUP(2,1/(E16:Q16<>""),E16:Q16)) | T16: =IF(R16="","",ROUND(R16*RESUMEN!$B$4,0)) | U16: =COUNT(E16:Q16)
A17: 21605771301805 | B17: ANILLO BACK SOON T ROSE GOLD | C17: 6 | D17: Stainless Stee | F17: 3 | M17: 3 | Q17: 3 | R17: =IF(COUNT(E17:Q17)=0,"",MIN(E17:Q17)) | S17: =IF(COUNT(E17:Q17)=0,"",LOOKUP(2,1/(E17:Q17<>""),E17:Q17)) | T17: =IF(R17="","",ROUND(R17*RESUMEN!$B$4,0)) | U17: =COUNT(E17:Q17)
A18: 21605771334573 | B18: ANILLO BACK SOON T ROSE GOLD | C18: 7 | H18: 3 | I18: 3 | R18: =IF(COUNT(E18:Q18)=0,"",MIN(E18:Q18)) | S18: =IF(COUNT(E18:Q18)=0,"",LOOKUP(2,1/(E18:Q18<>""),E18:Q18)) | T18: =IF(R18="","",ROUND(R18*RESUMEN!$B$4,0)) | U18: =COUNT(E18:Q18)
A19: ANDREA | B19: ANILLO BACK SOON T SILVER | D19: Stainless stee | Q19: 1.8 | R19: =IF(COUNT(E19:Q19)=0,"",MIN(E19:Q19)) | S19: =IF(COUNT(E19:Q19)=0,"",LOOKUP(2,1/(E19:Q19<>""),E19:Q19)) | T19: =IF(R19="","",ROUND(R19*RESUMEN!$B$4,0)) | U19: =COUNT(E19:Q19)
A20: 21605774283693 | B20: ANILLO BACK SOON T SILVER | C20: 6 | D20: Stainless Stee | F20: 3 | I20: 3 | J20: 3 | O20: 3 | P20: 3 | R20: =IF(COUNT(E20:Q20)=0,"",MIN(E20:Q20)) | S20: =IF(COUNT(E20:Q20)=0,"",LOOKUP(2,1/(E20:Q20<>""),E20:Q20)) | T20: =IF(R20="","",ROUND(R20*RESUMEN!$B$4,0)) | U20: =COUNT(E20:Q20)
A21: 21605774316461 | B21: ANILLO BACK SOON T SILVER | C21: 7 | D21: Stainless stee | H21: 3 | I21: 3 | J21: 3 | L21: 3 | N21: 3 | R21: =IF(COUNT(E21:Q21)=0,"",MIN(E21:Q21)) | S21: =IF(COUNT(E21:Q21)=0,"",LOOKUP(2,1/(E21:Q21<>""),E21:Q21)) | T21: =IF(R21="","",ROUND(R21*RESUMEN!$B$4,0)) | U21: =COUNT(E21:Q21)
A22: 21605774349229 | B22: ANILLO BACK SOON T SILVER | C22: 8 | D22: Stainless stee | F22: 3 | H22: 3 | I22: 3 | N22: 3 | R22: =IF(COUNT(E22:Q22)=0,"",MIN(E22:Q22)) | S22: =IF(COUNT(E22:Q22)=0,"",LOOKUP(2,1/(E22:Q22<>""),E22:Q22)) | T22: =IF(R22="","",ROUND(R22*RESUMEN!$B$4,0)) | U22: =COUNT(E22:Q22)
A23: 67201533776845 | B23: ANILLO BEAN CON ZIRCONIA GOLD | C23: 6 | D23: Copper alloy | H23: 5 | I23: 5 | J23: 5 | N23: 5 | R23: =IF(COUNT(E23:Q23)=0,"",MIN(E23:Q23)) | S23: =IF(COUNT(E23:Q23)=0,"",LOOKUP(2,1/(E23:Q23<>""),E23:Q23)) | T23: =IF(R23="","",ROUND(R23*RESUMEN!$B$4,0)) | U23: =COUNT(E23:Q23)
A24: 67201533809613 | B24: ANILLO BEAN CON ZIRCONIA GOLD | C24: 7 | D24: Copper alloy | F24: 5 | J24: 5 | L24: 5 | R24: =IF(COUNT(E24:Q24)=0,"",MIN(E24:Q24)) | S24: =IF(COUNT(E24:Q24)=0,"",LOOKUP(2,1/(E24:Q24<>""),E24:Q24)) | T24: =IF(R24="","",ROUND(R24*RESUMEN!$B$4,0)) | U24: =COUNT(E24:Q24)
A25: 67201533942381 | B25: ANILLO BEAN CON ZIRCONIA GOLD | C25: 8 | I25: 5 | R25: =IF(COUNT(E25:Q25)=0,"",MIN(E25:Q25)) | S25: =IF(COUNT(E25:Q25)=0,"",LOOKUP(2,1/(E25:Q25<>""),E25:Q25)) | T25: =IF(R25="","",ROUND(R25*RESUMEN!$B$4,0)) | U25: =COUNT(E25:Q25)
A26: 67201534287725 | B26: ANILLO BEAN T SILVER MINI | C26: 6 | D26: Copper alloy | I26: 5 | J26: 5 | L26: 5 | R26: =IF(COUNT(E26:Q26)=0,"",MIN(E26:Q26)) | S26: =IF(COUNT(E26:Q26)=0,"",LOOKUP(2,1/(E26:Q26<>""),E26:Q26)) | T26: =IF(R26="","",ROUND(R26*RESUMEN!$B$4,0)) | U26: =COUNT(E26:Q26)
A27: 654bd7ac2dee3 | B27: ANILLO BV 3 OROS-5 | C27: 5 | F27: 8 | R27: =IF(COUNT(E27:Q27)=0,"",MIN(E27:Q27)) | S27: =IF(COUNT(E27:Q27)=0,"",LOOKUP(2,1/(E27:Q27<>""),E27:Q27)) | T27: =IF(R27="","",ROUND(R27*RESUMEN!$B$4,0)) | U27: =COUNT(E27:Q27)
A28: 64e78e7b03ab1 | B28: ANILLO BV 3 OROS-8 | C28: 8 | F28: 8 | R28: =IF(COUNT(E28:Q28)=0,"",MIN(E28:Q28)) | S28: =IF(COUNT(E28:Q28)=0,"",LOOKUP(2,1/(E28:Q28<>""),E28:Q28)) | T28: =IF(R28="","",ROUND(R28*RESUMEN!$B$4,0)) | U28: =COUNT(E28:Q28)
A29: 64e78e7bb52a6 | B29: ANILLO BV 3 OROS-9 | C29: 9 | F29: 8 | R29: =IF(COUNT(E29:Q29)=0,"",MIN(E29:Q29)) | S29: =IF(COUNT(E29:Q29)=0,"",LOOKUP(2,1/(E29:Q29<>""),E29:Q29)) | T29: =IF(R29="","",ROUND(R29*RESUMEN!$B$4,0)) | U29: =COUNT(E29:Q29)
A30: 17964142179245 | B30: ANILLO BV ANISH KAPOOR | C30: 7 | O30: 8 | R30: =IF(COUNT(E30:Q30)=0,"",MIN(E30:Q30)) | S30: =IF(COUNT(E30:Q30)=0,"",LOOKUP(2,1/(E30:Q30<>""),E30:Q30)) | T30: =IF(R30="","",ROUND(R30*RESUMEN!$B$4,0)) | U30: =COUNT(E30:Q30)
A31: 40154173040301 | B31: ANILLO BV B.ZERO1 DELGADO SILVER | C31: 6 | K31: 7 | R31: =IF(COUNT(E31:Q31)=0,"",MIN(E31:Q31)) | S31: =IF(COUNT(E31:Q31)=0,"",LOOKUP(2,1/(E31:Q31<>""),E31:Q31)) | T31: =IF(R31="","",ROUND(R31*RESUMEN!$B$4,0)) | U31: =COUNT(E31:Q31)
A32: 40154173173069 | B32: ANILLO BV B.ZERO1 DELGADO SILVER | C32: 7 | K32: 7 | R32: =IF(COUNT(E32:Q32)=0,"",MIN(E32:Q32)) | S32: =IF(COUNT(E32:Q32)=0,"",LOOKUP(2,1/(E32:Q32<>""),E32:Q32)) | T32: =IF(R32="","",ROUND(R32*RESUMEN!$B$4,0)) | U32: =COUNT(E32:Q32)
A33: 66009451058221 | B33: ANILLO BV BROWN | C33: 6 | D33: Stainless stee | L33: 7 | R33: =IF(COUNT(E33:Q33)=0,"",MIN(E33:Q33)) | S33: =IF(COUNT(E33:Q33)=0,"",LOOKUP(2,1/(E33:Q33<>""),E33:Q33)) | T33: =IF(R33="","",ROUND(R33*RESUMEN!$B$4,0)) | U33: =COUNT(E33:Q33)
A34: 66009451058222 | B34: ANILLO BV BROWN | C34: 7 | D34: Stainless Stee | J34: 7 | L34: 7 | O34: 7 | R34: =IF(COUNT(E34:Q34)=0,"",MIN(E34:Q34)) | S34: =IF(COUNT(E34:Q34)=0,"",LOOKUP(2,1/(E34:Q34<>""),E34:Q34)) | T34: =IF(R34="","",ROUND(R34*RESUMEN!$B$4,0)) | U34: =COUNT(E34:Q34)
A35: 66009451058223 | B35: ANILLO BV BROWN | C35: 8 | D35: Stainless Stee | J35: 7 | L35: 7 | Q35: 7 | R35: =IF(COUNT(E35:Q35)=0,"",MIN(E35:Q35)) | S35: =IF(COUNT(E35:Q35)=0,"",LOOKUP(2,1/(E35:Q35<>""),E35:Q35)) | T35: =IF(R35="","",ROUND(R35*RESUMEN!$B$4,0)) | U35: =COUNT(E35:Q35)
A36: 6 | B36: ANILLO BV BROWN-6 | F36: 7 | R36: =IF(COUNT(E36:Q36)=0,"",MIN(E36:Q36)) | S36: =IF(COUNT(E36:Q36)=0,"",LOOKUP(2,1/(E36:Q36<>""),E36:Q36)) | T36: =IF(R36="","",ROUND(R36*RESUMEN!$B$4,0)) | U36: =COUNT(E36:Q36)
A37: 7 | B37: ANILLO BV BROWN-7 | F37: 7 | R37: =IF(COUNT(E37:Q37)=0,"",MIN(E37:Q37)) | S37: =IF(COUNT(E37:Q37)=0,"",LOOKUP(2,1/(E37:Q37<>""),E37:Q37)) | T37: =IF(R37="","",ROUND(R37*RESUMEN!$B$4,0)) | U37: =COUNT(E37:Q37)
A38: 8 | B38: ANILLO BV BROWN-8 | F38: 7 | R38: =IF(COUNT(E38:Q38)=0,"",MIN(E38:Q38)) | S38: =IF(COUNT(E38:Q38)=0,"",LOOKUP(2,1/(E38:Q38<>""),E38:Q38)) | T38: =IF(R38="","",ROUND(R38*RESUMEN!$B$4,0)) | U38: =COUNT(E38:Q38)
A39: 10956321024557 | B39: ANILLO BV BUMPS GOLD ZIRCONIAS | C39: 6 | D39: nan | F39: 10 | M39: 11 | R39: =IF(COUNT(E39:Q39)=0,"",MIN(E39:Q39)) | S39: =IF(COUNT(E39:Q39)=0,"",LOOKUP(2,1/(E39:Q39<>""),E39:Q39)) | T39: =IF(R39="","",ROUND(R39*RESUMEN!$B$4,0)) | U39: =COUNT(E39:Q39)
A40: 10956321157325 | B40: ANILLO BV BUMPS GOLD ZIRCONIAS | C40: 7 | D40: Stainless Stee | F40: 10 | L40: 11 | O40: 12 | R40: =IF(COUNT(E40:Q40)=0,"",MIN(E40:Q40)) | S40: =IF(COUNT(E40:Q40)=0,"",LOOKUP(2,1/(E40:Q40<>""),E40:Q40)) | T40: =IF(R40="","",ROUND(R40*RESUMEN!$B$4,0)) | U40: =COUNT(E40:Q40)
A41: 13667531088813 | B41: ANILLO BV BUMPS GOLD-BLACK | C41: 8 | D41: Stainless stee | F41: 9 | L41: 9 | R41: =IF(COUNT(E41:Q41)=0,"",MIN(E41:Q41)) | S41: =IF(COUNT(E41:Q41)=0,"",LOOKUP(2,1/(E41:Q41<>""),E41:Q41)) | T41: =IF(R41="","",ROUND(R41*RESUMEN!$B$4,0)) | U41: =COUNT(E41:Q41)
A42: 10956321324077 | B42: ANILLO BV BUMPS SILVER ZIRCONIAS | C42: 7 | D42: Stainless stee | F42: 10 | N42: 10 | R42: =IF(COUNT(E42:Q42)=0,"",MIN(E42:Q42)) | S42: =IF(COUNT(E42:Q42)=0,"",LOOKUP(2,1/(E42:Q42<>""),E42:Q42)) | T42: =IF(R42="","",ROUND(R42*RESUMEN!$B$4,0)) | U42: =COUNT(E42:Q42)
A43: 10956321291309 | B43: ANILLO BV BUMPS SILVER ZIRCONIAS-6 | C43: 6 | F43: 10 | R43: =IF(COUNT(E43:Q43)=0,"",MIN(E43:Q43)) | S43: =IF(COUNT(E43:Q43)=0,"",LOOKUP(2,1/(E43:Q43<>""),E43:Q43)) | T43: =IF(R43="","",ROUND(R43*RESUMEN!$B$4,0)) | U43: =COUNT(E43:Q43)
A44: 22064322680525 | B44: ANILLO BV ROSE GOLD PEARL | C44: 6 | K44: 8 | R44: =IF(COUNT(E44:Q44)=0,"",MIN(E44:Q44)) | S44: =IF(COUNT(E44:Q44)=0,"",LOOKUP(2,1/(E44:Q44<>""),E44:Q44)) | T44: =IF(R44="","",ROUND(R44*RESUMEN!$B$4,0)) | U44: =COUNT(E44:Q44)
A45: 22064322713293 | B45: ANILLO BV ROSE GOLD PEARL | C45: 7 | D45: Copper alloy | K45: 8 | P45: 8 | R45: =IF(COUNT(E45:Q45)=0,"",MIN(E45:Q45)) | S45: =IF(COUNT(E45:Q45)=0,"",LOOKUP(2,1/(E45:Q45<>""),E45:Q45)) | T45: =IF(R45="","",ROUND(R45*RESUMEN!$B$4,0)) | U45: =COUNT(E45:Q45)
A46: 17964142243085 | B46: ANILLO BV SORTIJA SILVER | C46: 7 | O46: 7 | R46: =IF(COUNT(E46:Q46)=0,"",MIN(E46:Q46)) | S46: =IF(COUNT(E46:Q46)=0,"",LOOKUP(2,1/(E46:Q46<>""),E46:Q46)) | T46: =IF(R46="","",ROUND(R46*RESUMEN!$B$4,0)) | U46: =COUNT(E46:Q46)
A47: 16117871577997 | B47: ANILLO BV ZERO 1 BLACK-ROSEGOLD | C47: 7 | D47: Stainless stee | F47: 9 | L47: 7 | N47: 7 | R47: =IF(COUNT(E47:Q47)=0,"",MIN(E47:Q47)) | S47: =IF(COUNT(E47:Q47)=0,"",LOOKUP(2,1/(E47:Q47<>""),E47:Q47)) | T47: =IF(R47="","",ROUND(R47*RESUMEN!$B$4,0)) | U47: =COUNT(E47:Q47)
A48: 16117871610765 | B48: ANILLO BV ZERO 1 BLACK-ROSEGOLD | C48: 8 | D48: Stainless Stee | F48: 9 | L48: 7 | Q48: 9 | R48: =IF(COUNT(E48:Q48)=0,"",MIN(E48:Q48)) | S48: =IF(COUNT(E48:Q48)=0,"",LOOKUP(2,1/(E48:Q48<>""),E48:Q48)) | T48: =IF(R48="","",ROUND(R48*RESUMEN!$B$4,0)) | U48: =COUNT(E48:Q48)
A49: 94122711058029 | B49: ANILLO BV ZERO 1 SILVER | C49: 7 | D49: nan | F49: 7 | M49: 6 | R49: =IF(COUNT(E49:Q49)=0,"",MIN(E49:Q49)) | S49: =IF(COUNT(E49:Q49)=0,"",LOOKUP(2,1/(E49:Q49<>""),E49:Q49)) | T49: =IF(R49="","",ROUND(R49*RESUMEN!$B$4,0)) | U49: =COUNT(E49:Q49)
A50: 94122711058030 | B50: ANILLO BV ZERO 1 SILVER | C50: 8 | D50: nan | F50: 6 | M50: 6 | R50: =IF(COUNT(E50:Q50)=0,"",MIN(E50:Q50)) | S50: =IF(COUNT(E50:Q50)=0,"",LOOKUP(2,1/(E50:Q50<>""),E50:Q50)) | T50: =IF(R50="","",ROUND(R50*RESUMEN!$B$4,0)) | U50: =COUNT(E50:Q50)
A51: 94122711058031 | B51: ANILLO BV ZERO 1 SILVER | C51: 9 | D51: Stainless stee | F51: 6 | L51: 6 | N51: 6 | Q51: 6 | R51: =IF(COUNT(E51:Q51)=0,"",MIN(E51:Q51)) | S51: =IF(COUNT(E51:Q51)=0,"",LOOKUP(2,1/(E51:Q51<>""),E51:Q51)) | T51: =IF(R51="","",ROUND(R51*RESUMEN!$B$4,0)) | U51: =COUNT(E51:Q51)
A52: 35432871289805 | B52: ANILLO CC COCO CRUSH ROSE GOLD | C52: 6 | K52: 10 | R52: =IF(COUNT(E52:Q52)=0,"",MIN(E52:Q52)) | S52: =IF(COUNT(E52:Q52)=0,"",LOOKUP(2,1/(E52:Q52<>""),E52:Q52)) | T52: =IF(R52="","",ROUND(R52*RESUMEN!$B$4,0)) | U52: =COUNT(E52:Q52)
A53: 35432871322573 | B53: ANILLO CC COCO CRUSH ROSE GOLD | C53: 7 | K53: 10 | R53: =IF(COUNT(E53:Q53)=0,"",MIN(E53:Q53)) | S53: =IF(COUNT(E53:Q53)=0,"",LOOKUP(2,1/(E53:Q53<>""),E53:Q53)) | T53: =IF(R53="","",ROUND(R53*RESUMEN!$B$4,0)) | U53: =COUNT(E53:Q53)
A54: 35432871441773 | B54: ANILLO CC COCO CRUSH ROSE GOLD-SILVER | C54: 6 | D54: Stainless Stee | K54: 10 | P54: 10 | R54: =IF(COUNT(E54:Q54)=0,"",MIN(E54:Q54)) | S54: =IF(COUNT(E54:Q54)=0,"",LOOKUP(2,1/(E54:Q54<>""),E54:Q54)) | T54: =IF(R54="","",ROUND(R54*RESUMEN!$B$4,0)) | U54: =COUNT(E54:Q54)
A55: 35432871574541 | B55: ANILLO CC COCO CRUSH ROSE GOLD-SILVER | C55: 7 | D55: Stainless Stee | K55: 10 | P55: 10 | R55: =IF(COUNT(E55:Q55)=0,"",MIN(E55:Q55)) | S55: =IF(COUNT(E55:Q55)=0,"",LOOKUP(2,1/(E55:Q55<>""),E55:Q55)) | T55: =IF(R55="","",ROUND(R55*RESUMEN!$B$4,0)) | U55: =COUNT(E55:Q55)
A56: 86347032550093 | B56: ANILLO CD DIAMOND ZIRCONIAS | C56: 7 | D56: Copper alloy | G56: 6 | L56: 4.9 | N56: 4.9 | P56: 4.9 | R56: =IF(COUNT(E56:Q56)=0,"",MIN(E56:Q56)) | S56: =IF(COUNT(E56:Q56)=0,"",LOOKUP(2,1/(E56:Q56<>""),E56:Q56)) | T56: =IF(R56="","",ROUND(R56*RESUMEN!$B$4,0)) | U56: =COUNT(E56:Q56)
A57: 61222821052141 | B57: ANILLO CD GRABADO GOLD BLACK ZIRCONIAS | C57: 6 | D57: Stainless stee | F57: 6.9 | L57: 6.9 | R57: =IF(COUNT(E57:Q57)=0,"",MIN(E57:Q57)) | S57: =IF(COUNT(E57:Q57)=0,"",LOOKUP(2,1/(E57:Q57<>""),E57:Q57)) | T57: =IF(R57="","",ROUND(R57*RESUMEN!$B$4,0)) | U57: =COUNT(E57:Q57)
A58: 61222821166797 | B58: ANILLO CD GRABADO GOLD BLACK ZIRCONIAS | C58: 8 | D58: Stainless Stee | F58: 6.9 | L58: 6.9 | P58: 7.9 | R58: =IF(COUNT(E58:Q58)=0,"",MIN(E58:Q58)) | S58: =IF(COUNT(E58:Q58)=0,"",LOOKUP(2,1/(E58:Q58<>""),E58:Q58)) | T58: =IF(R58="","",ROUND(R58*RESUMEN!$B$4,0)) | U58: =COUNT(E58:Q58)
A59: 85549091025933 | B59: ANILLO CD LOGO GOLD CON ZIRCONIAS | C59: Default Title | I59: 6 | R59: =IF(COUNT(E59:Q59)=0,"",MIN(E59:Q59)) | S59: =IF(COUNT(E59:Q59)=0,"",LOOKUP(2,1/(E59:Q59<>""),E59:Q59)) | T59: =IF(R59="","",ROUND(R59*RESUMEN!$B$4,0)) | U59: =COUNT(E59:Q59)
A60: 29736662234765 | B60: ANILLO CD TRIBALES GOLD | C60: 7 | D60: Copper alloy | K60: 6.99 | P60: 6.99 | R60: =IF(COUNT(E60:Q60)=0,"",MIN(E60:Q60)) | S60: =IF(COUNT(E60:Q60)=0,"",LOOKUP(2,1/(E60:Q60<>""),E60:Q60)) | T60: =IF(R60="","",ROUND(R60*RESUMEN!$B$4,0)) | U60: =COUNT(E60:Q60)
A61: 10717801055213 | B61: ANILLO CD ZIRCONIAS GOLD-BLACK | C61: 7 | D61: Copper alloy | J61: 9.5 | L61: 9.5 | R61: =IF(COUNT(E61:Q61)=0,"",MIN(E61:Q61)) | S61: =IF(COUNT(E61:Q61)=0,"",LOOKUP(2,1/(E61:Q61<>""),E61:Q61)) | T61: =IF(R61="","",ROUND(R61*RESUMEN!$B$4,0)) | U61: =COUNT(E61:Q61)
A62: 22064322048301 | B62: ANILLO CLASH DOBLE ROSE GOLD | C62: 6 | K62: 10 | R62: =IF(COUNT(E62:Q62)=0,"",MIN(E62:Q62)) | S62: =IF(COUNT(E62:Q62)=0,"",LOOKUP(2,1/(E62:Q62<>""),E62:Q62)) | T62: =IF(R62="","",ROUND(R62*RESUMEN!$B$4,0)) | U62: =COUNT(E62:Q62)
A63: 22064322181069 | B63: ANILLO CLASH DOBLE ROSE GOLD | C63: 7 | K63: 10 | R63: =IF(COUNT(E63:Q63)=0,"",MIN(E63:Q63)) | S63: =IF(COUNT(E63:Q63)=0,"",LOOKUP(2,1/(E63:Q63<>""),E63:Q63)) | T63: =IF(R63="","",ROUND(R63*RESUMEN!$B$4,0)) | U63: =COUNT(E63:Q63)
A64: 66176e62063fb | B64: ANILLO CLASH GOLD | C64: 10 | D64: Copper alloy | H64: 10 | I64: 10 | L64: 10 | R64: =IF(COUNT(E64:Q64)=0,"",MIN(E64:Q64)) | S64: =IF(COUNT(E64:Q64)=0,"",LOOKUP(2,1/(E64:Q64<>""),E64:Q64)) | T64: =IF(R64="","",ROUND(R64*RESUMEN!$B$4,0)) | U64: =COUNT(E64:Q64)
A65: 66176e628d423 | B65: ANILLO CLASH GOLD | C65: 11 | H65: 10 | I65: 10 | R65: =IF(COUNT(E65:Q65)=0,"",MIN(E65:Q65)) | S65: =IF(COUNT(E65:Q65)=0,"",LOOKUP(2,1/(E65:Q65<>""),E65:Q65)) | T65: =IF(R65="","",ROUND(R65*RESUMEN!$B$4,0)) | U65: =COUNT(E65:Q65)
A66: 66176e5ecde32 | B66: ANILLO CLASH GOLD | C66: 5 | D66: Copper Alloy | Q66: 10 | R66: =IF(COUNT(E66:Q66)=0,"",MIN(E66:Q66)) | S66: =IF(COUNT(E66:Q66)=0,"",LOOKUP(2,1/(E66:Q66<>""),E66:Q66)) | T66: =IF(R66="","",ROUND(R66*RESUMEN!$B$4,0)) | U66: =COUNT(E66:Q66)
A67: 66176e5f7392c | B67: ANILLO CLASH GOLD | C67: 6 | D67: Copper Alloy | E67: 10 | J67: 10 | N67: 10 | Q67: 10 | R67: =IF(COUNT(E67:Q67)=0,"",MIN(E67:Q67)) | S67: =IF(COUNT(E67:Q67)=0,"",LOOKUP(2,1/(E67:Q67<>""),E67:Q67)) | T67: =IF(R67="","",ROUND(R67*RESUMEN!$B$4,0)) | U67: =COUNT(E67:Q67)
A68: 66176e6009ab0 | B68: ANILLO CLASH GOLD | C68: 7 | D68: Copper alloy | E68: 10 | J68: 10 | M68: 10 | Q68: 10 | R68: =IF(COUNT(E68:Q68)=0,"",MIN(E68:Q68)) | S68: =IF(COUNT(E68:Q68)=0,"",LOOKUP(2,1/(E68:Q68<>""),E68:Q68)) | T68: =IF(R68="","",ROUND(R68*RESUMEN!$B$4,0)) | U68: =COUNT(E68:Q68)
A69: 66176e609b95a | B69: ANILLO CLASH GOLD | C69: 8 | D69: Copper Alloy | F69: 10 | M69: 10 | O69: 10 | R69: =IF(COUNT(E69:Q69)=0,"",MIN(E69:Q69)) | S69: =IF(COUNT(E69:Q69)=0,"",LOOKUP(2,1/(E69:Q69<>""),E69:Q69)) | T69: =IF(R69="","",ROUND(R69*RESUMEN!$B$4,0)) | U69: =COUNT(E69:Q69)
A70: 66176e6140134 | B70: ANILLO CLASH GOLD | C70: 9 | D70: Copper Alloy | E70: 10 | I70: 10 | N70: 10 | Q70: 10 | R70: =IF(COUNT(E70:Q70)=0,"",MIN(E70:Q70)) | S70: =IF(COUNT(E70:Q70)=0,"",LOOKUP(2,1/(E70:Q70<>""),E70:Q70)) | T70: =IF(R70="","",ROUND(R70*RESUMEN!$B$4,0)) | U70: =COUNT(E70:Q70)
A71: 66176e62285d1 | B71: ANILLO CLASH ROSEGOLD | C71: 10 | E71: 10 | J71: 10 | R71: =IF(COUNT(E71:Q71)=0,"",MIN(E71:Q71)) | S71: =IF(COUNT(E71:Q71)=0,"",LOOKUP(2,1/(E71:Q71<>""),E71:Q71)) | T71: =IF(R71="","",ROUND(R71*RESUMEN!$B$4,0)) | U71: =COUNT(E71:Q71)
A72: 66176e5ee773d | B72: ANILLO CLASH ROSEGOLD | C72: 5 | D72: Copper alloy | H72: 10 | L72: 10 | N72: 10 | R72: =IF(COUNT(E72:Q72)=0,"",MIN(E72:Q72)) | S72: =IF(COUNT(E72:Q72)=0,"",LOOKUP(2,1/(E72:Q72<>""),E72:Q72)) | T72: =IF(R72="","",ROUND(R72*RESUMEN!$B$4,0)) | U72: =COUNT(E72:Q72)
A73: 66176e5f8fac7 | B73: ANILLO CLASH ROSEGOLD | C73: 6 | D73: Copper | E73: 10 | H73: 10 | L73: 10 | Q73: 10 | R73: =IF(COUNT(E73:Q73)=0,"",MIN(E73:Q73)) | S73: =IF(COUNT(E73:Q73)=0,"",LOOKUP(2,1/(E73:Q73<>""),E73:Q73)) | T73: =IF(R73="","",ROUND(R73*RESUMEN!$B$4,0)) | U73: =COUNT(E73:Q73)
A74: 66176e602b0bf | B74: ANILLO CLASH ROSEGOLD | C74: 7 | D74: Copper Alloy | F74: 10 | I74: 10 | J74: 10 | N74: 10 | O74: 10 | R74: =IF(COUNT(E74:Q74)=0,"",MIN(E74:Q74)) | S74: =IF(COUNT(E74:Q74)=0,"",LOOKUP(2,1/(E74:Q74<>""),E74:Q74)) | T74: =IF(R74="","",ROUND(R74*RESUMEN!$B$4,0)) | U74: =COUNT(E74:Q74)
A75: 66176e60bbec9 | B75: ANILLO CLASH ROSEGOLD | C75: 8 | D75: Copper Alloy | H75: 10 | J75: 10 | L75: 10 | Q75: 10 | R75: =IF(COUNT(E75:Q75)=0,"",MIN(E75:Q75)) | S75: =IF(COUNT(E75:Q75)=0,"",LOOKUP(2,1/(E75:Q75<>""),E75:Q75)) | T75: =IF(R75="","",ROUND(R75*RESUMEN!$B$4,0)) | U75: =COUNT(E75:Q75)
A76: 66176e616caf6 | B76: ANILLO CLASH ROSEGOLD | C76: 9 | D76: Copper alloy | F76: 10 | I76: 10 | L76: 10 | R76: =IF(COUNT(E76:Q76)=0,"",MIN(E76:Q76)) | S76: =IF(COUNT(E76:Q76)=0,"",LOOKUP(2,1/(E76:Q76<>""),E76:Q76)) | T76: =IF(R76="","",ROUND(R76*RESUMEN!$B$4,0)) | U76: =COUNT(E76:Q76)
A77: 63ebd3f635fb6 | B77: ANILLO CLASH SILVER | C77: 10 | D77: Copper Alloy | F77: 10 | Q77: 10 | R77: =IF(COUNT(E77:Q77)=0,"",MIN(E77:Q77)) | S77: =IF(COUNT(E77:Q77)=0,"",LOOKUP(2,1/(E77:Q77<>""),E77:Q77)) | T77: =IF(R77="","",ROUND(R77*RESUMEN!$B$4,0)) | U77: =COUNT(E77:Q77)
A78: 63ebd3f721f2e | B78: ANILLO CLASH SILVER | C78: 11 | D78: copper alloy | I78: 10 | M78: 10 | Q78: 10 | R78: =IF(COUNT(E78:Q78)=0,"",MIN(E78:Q78)) | S78: =IF(COUNT(E78:Q78)=0,"",LOOKUP(2,1/(E78:Q78<>""),E78:Q78)) | T78: =IF(R78="","",ROUND(R78*RESUMEN!$B$4,0)) | U78: =COUNT(E78:Q78)
A79: 63ebd3f136b3c | B79: ANILLO CLASH SILVER | C79: 5 | E79: 10 | R79: =IF(COUNT(E79:Q79)=0,"",MIN(E79:Q79)) | S79: =IF(COUNT(E79:Q79)=0,"",LOOKUP(2,1/(E79:Q79<>""),E79:Q79)) | T79: =IF(R79="","",ROUND(R79*RESUMEN!$B$4,0)) | U79: =COUNT(E79:Q79)
A80: 63ebd3f2335dc | B80: ANILLO CLASH SILVER | C80: 6 | D80: copper alloy | I80: 10 | P80: 10 | R80: =IF(COUNT(E80:Q80)=0,"",MIN(E80:Q80)) | S80: =IF(COUNT(E80:Q80)=0,"",LOOKUP(2,1/(E80:Q80<>""),E80:Q80)) | T80: =IF(R80="","",ROUND(R80*RESUMEN!$B$4,0)) | U80: =COUNT(E80:Q80)
A81: 63ebd3f32bfc9 | B81: ANILLO CLASH SILVER | C81: 7 | D81: Copper alloy | E81: 10 | N81: 10 | R81: =IF(COUNT(E81:Q81)=0,"",MIN(E81:Q81)) | S81: =IF(COUNT(E81:Q81)=0,"",LOOKUP(2,1/(E81:Q81<>""),E81:Q81)) | T81: =IF(R81="","",ROUND(R81*RESUMEN!$B$4,0)) | U81: =COUNT(E81:Q81)
A82: 63ebd3f42d4db | B82: ANILLO CLASH SILVER | C82: 8 | D82: Copper alloy | E82: 10 | I82: 10 | J82: 10 | L82: 10 | N82: 10 | R82: =IF(COUNT(E82:Q82)=0,"",MIN(E82:Q82)) | S82: =IF(COUNT(E82:Q82)=0,"",LOOKUP(2,1/(E82:Q82<>""),E82:Q82)) | T82: =IF(R82="","",ROUND(R82*RESUMEN!$B$4,0)) | U82: =COUNT(E82:Q82)
A83: 63ebd3f53c553 | B83: ANILLO CLASH SILVER | C83: 9 | H83: 10 | I83: 10 | R83: =IF(COUNT(E83:Q83)=0,"",MIN(E83:Q83)) | S83: =IF(COUNT(E83:Q83)=0,"",LOOKUP(2,1/(E83:Q83<>""),E83:Q83)) | T83: =IF(R83="","",ROUND(R83*RESUMEN!$B$4,0)) | U83: =COUNT(E83:Q83)
A84: 40154173560109 | B84: ANILLO CLAVO DOBLE GOLD ZIRCONIAS | C84: 6 | K84: 5 | R84: =IF(COUNT(E84:Q84)=0,"",MIN(E84:Q84)) | S84: =IF(COUNT(E84:Q84)=0,"",LOOKUP(2,1/(E84:Q84<>""),E84:Q84)) | T84: =IF(R84="","",ROUND(R84*RESUMEN!$B$4,0)) | U84: =COUNT(E84:Q84)
A85: 40154173692877 | B85: ANILLO CLAVO DOBLE GOLD ZIRCONIAS | C85: 7 | D85: Copper alloy | K85: 5 | P85: 5 | R85: =IF(COUNT(E85:Q85)=0,"",MIN(E85:Q85)) | S85: =IF(COUNT(E85:Q85)=0,"",LOOKUP(2,1/(E85:Q85<>""),E85:Q85)) | T85: =IF(R85="","",ROUND(R85*RESUMEN!$B$4,0)) | U85: =COUNT(E85:Q85)
A86: 40154173365741 | B86: ANILLO CLAVO DOBLE SILVER ZIRCONIAS | C86: 6 | K86: 5 | R86: =IF(COUNT(E86:Q86)=0,"",MIN(E86:Q86)) | S86: =IF(COUNT(E86:Q86)=0,"",LOOKUP(2,1/(E86:Q86<>""),E86:Q86)) | T86: =IF(R86="","",ROUND(R86*RESUMEN!$B$4,0)) | U86: =COUNT(E86:Q86)
A87: 40154173498509 | B87: ANILLO CLAVO DOBLE SILVER ZIRCONIAS | C87: 7 | K87: 5 | R87: =IF(COUNT(E87:Q87)=0,"",MIN(E87:Q87)) | S87: =IF(COUNT(E87:Q87)=0,"",LOOKUP(2,1/(E87:Q87<>""),E87:Q87)) | T87: =IF(R87="","",ROUND(R87*RESUMEN!$B$4,0)) | U87: =COUNT(E87:Q87)
A88: GISEL | B88: ANILLO CLAVO GOLD | D88: Stainless stee | Q88: 2.5 | R88: =IF(COUNT(E88:Q88)=0,"",MIN(E88:Q88)) | S88: =IF(COUNT(E88:Q88)=0,"",LOOKUP(2,1/(E88:Q88<>""),E88:Q88)) | T88: =IF(R88="","",ROUND(R88*RESUMEN!$B$4,0)) | U88: =COUNT(E88:Q88)
A89: 66176cde28afb | B89: ANILLO CLAVO GOLD | C89: 10 | D89: Stainless stee | L89: 2.5 | N89: 2.5 | Q89: 2.5 | R89: =IF(COUNT(E89:Q89)=0,"",MIN(E89:Q89)) | S89: =IF(COUNT(E89:Q89)=0,"",LOOKUP(2,1/(E89:Q89<>""),E89:Q89)) | T89: =IF(R89="","",ROUND(R89*RESUMEN!$B$4,0)) | U89: =COUNT(E89:Q89)
A90: 66176cdeab849 | B90: ANILLO CLAVO GOLD | C90: 11 | D90: Stainless stee | H90: 2.5 | R90: =IF(COUNT(E90:Q90)=0,"",MIN(E90:Q90)) | S90: =IF(COUNT(E90:Q90)=0,"",LOOKUP(2,1/(E90:Q90<>""),E90:Q90)) | T90: =IF(R90="","",ROUND(R90*RESUMEN!$B$4,0)) | U90: =COUNT(E90:Q90)
A91: 66176cdae92c1 | B91: ANILLO CLAVO GOLD | C91: 5 HIGH QUALITY | D91: stainless stee | I91: 2.5 | J91: 2.5 | L91: 2.5 | N91: 2.5 | Q91: 2.5 | R91: =IF(COUNT(E91:Q91)=0,"",MIN(E91:Q91)) | S91: =IF(COUNT(E91:Q91)=0,"",LOOKUP(2,1/(E91:Q91<>""),E91:Q91)) | T91: =IF(R91="","",ROUND(R91*RESUMEN!$B$4,0)) | U91: =COUNT(E91:Q91)
A92: 66176cdb9f129 | B92: ANILLO CLAVO GOLD | C92: 6 HIGH QUALITY | D92: Stainless Stee | E92: 2.5 | F92: 2.5 | H92: 2.5 | I92: 2.5 | L92: 2.5 | M92: 2.5 | P92: 2.5 | R92: =IF(COUNT(E92:Q92)=0,"",MIN(E92:Q92)) | S92: =IF(COUNT(E92:Q92)=0,"",LOOKUP(2,1/(E92:Q92<>""),E92:Q92)) | T92: =IF(R92="","",ROUND(R92*RESUMEN!$B$4,0)) | U92: =COUNT(E92:Q92)
A93: 66176cdce18ea | B93: ANILLO CLAVO GOLD | C93: 8 HIGH QUALITY | D93: Stainless Stee | E93: 2.5 | H93: 2.5 | I93: 2.5 | M93: 2.5 | Q93: 2.5 | R93: =IF(COUNT(E93:Q93)=0,"",MIN(E93:Q93)) | S93: =IF(COUNT(E93:Q93)=0,"",LOOKUP(2,1/(E93:Q93<>""),E93:Q93)) | T93: =IF(R93="","",ROUND(R93*RESUMEN!$B$4,0)) | U93: =COUNT(E93:Q93)
A94: 66176cdd7cc61 | B94: ANILLO CLAVO GOLD | C94: 9 HIGH QUALITY | D94: Stainless Stee | E94: 2.5 | H94: 2.5 | I94: 2.5 | L94: 2.5 | Q94: 2.5 | R94: =IF(COUNT(E94:Q94)=0,"",MIN(E94:Q94)) | S94: =IF(COUNT(E94:Q94)=0,"",LOOKUP(2,1/(E94:Q94<>""),E94:Q94)) | T94: =IF(R94="","",ROUND(R94*RESUMEN!$B$4,0)) | U94: =COUNT(E94:Q94)
A95: 66176cdc59c57 | B95: ANILLO CLAVO GOLD (WITHOUT ZIRCONIAS) | C95: 7 HIGH QUALITY | D95: Stainless stee | E95: 2.5 | F95: 2.5 | H95: 2.5 | I95: 2.5 | J95: 2.5 | N95: 2.5 | R95: =IF(COUNT(E95:Q95)=0,"",MIN(E95:Q95)) | S95: =IF(COUNT(E95:Q95)=0,"",LOOKUP(2,1/(E95:Q95<>""),E95:Q95)) | T95: =IF(R95="","",ROUND(R95*RESUMEN!$B$4,0)) | U95: =COUNT(E95:Q95)
A96: 66176ce38fa21 | B96: ANILLO CLAVO ROSE GOLD | C96: 10 HIGH QUALITY | F96: 2.5 | R96: =IF(COUNT(E96:Q96)=0,"",MIN(E96:Q96)) | S96: =IF(COUNT(E96:Q96)=0,"",LOOKUP(2,1/(E96:Q96<>""),E96:Q96)) | T96: =IF(R96="","",ROUND(R96*RESUMEN!$B$4,0)) | U96: =COUNT(E96:Q96)
A97: 66176ce0abf98 | B97: ANILLO CLAVO ROSE GOLD | C97: 5 HIGH QUALITY | D97: Stainless Stee | E97: 2.5 | N97: 2.5 | Q97: 2.5 | R97: =IF(COUNT(E97:Q97)=0,"",MIN(E97:Q97)) | S97: =IF(COUNT(E97:Q97)=0,"",LOOKUP(2,1/(E97:Q97<>""),E97:Q97)) | T97: =IF(R97="","",ROUND(R97*RESUMEN!$B$4,0)) | U97: =COUNT(E97:Q97)
A98: 66176ce151d29 | B98: ANILLO CLAVO ROSE GOLD | C98: 6 HIGH QUALITY | D98: Stainless Stee | E98: 2.5 | H98: 2.5 | I98: 2.5 | N98: 2.5 | Q98: 2.5 | R98: =IF(COUNT(E98:Q98)=0,"",MIN(E98:Q98)) | S98: =IF(COUNT(E98:Q98)=0,"",LOOKUP(2,1/(E98:Q98<>""),E98:Q98)) | T98: =IF(R98="","",ROUND(R98*RESUMEN!$B$4,0)) | U98: =COUNT(E98:Q98)
A99: 66176ce1d817d | B99: ANILLO CLAVO ROSE GOLD | C99: 7 HIGH QUALITY | D99: Stainless Stee | E99: 2.5 | F99: 2.5 | P99: 2.5 | Q99: 2.5 | R99: =IF(COUNT(E99:Q99)=0,"",MIN(E99:Q99)) | S99: =IF(COUNT(E99:Q99)=0,"",LOOKUP(2,1/(E99:Q99<>""),E99:Q99)) | T99: =IF(R99="","",ROUND(R99*RESUMEN!$B$4,0)) | U99: =COUNT(E99:Q99)
A100: 66176ce26bdb9 | B100: ANILLO CLAVO ROSE GOLD | C100: 8 HIGH QUALITY | D100: SIN MATERIAL | I100: 2.5 | M100: 2.5 | Q100: 2.5 | R100: =IF(COUNT(E100:Q100)=0,"",MIN(E100:Q100)) | S100: =IF(COUNT(E100:Q100)=0,"",LOOKUP(2,1/(E100:Q100<>""),E100:Q100)) | T100: =IF(R100="","",ROUND(R100*RESUMEN!$B$4,0)) | U100: =COUNT(E100:Q100)
A101: 66176ce3090a4 | B101: ANILLO CLAVO ROSE GOLD | C101: 9 HIGH QUALITY | D101: nan | I101: 2.5 | M101: 2.5 | R101: =IF(COUNT(E101:Q101)=0,"",MIN(E101:Q101)) | S101: =IF(COUNT(E101:Q101)=0,"",LOOKUP(2,1/(E101:Q101<>""),E101:Q101)) | T101: =IF(R101="","",ROUND(R101*RESUMEN!$B$4,0)) | U101: =COUNT(E101:Q101)
...

Sheet ZOEY
A1: HISTORIAL DE PRECIOS — ZOEY
A2: 11 orden(es) · costo unitario en USD · MXN = MEJOR × RESUMEN!B4 · * = dato del historial previo
A4: SKU | B4: PRODUCTO | C4: VARIANTE | D4: MATERIAL | E4: Sep 2025 01/09 | F4: Oct 2025 02/10 | G4: Oct 2025 25/10 | H4: Dic 2025 historial* | I4: Ene 2026 20/01 | J4: Feb 2026 16/02 | K4: Mar 2026 02/03 | L4: Mar 2026 19/03 | M4: Abr 2026 20/04 | N4: May 2026 15/05 | O4: Jun 2026 08/06 | P4: MEJOR (US) | Q4: ÚLTIMA (US) | R4: MXN (mejor×TC) | S4: # ÓRD.
A5: 67308101075309 | B5: ANILLO CD GOLD BLACK CON ZIRCONIA ANCHO | C5: 7 | D5: Brass + Zirconia | F5: 9 | P5: =IF(COUNT(E5:O5)=0,"",MIN(E5:O5)) | Q5: =IF(COUNT(E5:O5)=0,"",LOOKUP(2,1/(E5:O5<>""),E5:O5)) | R5: =IF(P5="","",ROUND(P5*RESUMEN!$B$4,0)) | S5: =COUNT(E5:O5)
A6: 72142921022125 | B6: ANILLO CD GOLD WHITE CON ZIRCONIA | C6: 6 | D6: Brass + Zirconia | F6: 9 | L6: 9 | N6: 9 | P6: =IF(COUNT(E6:O6)=0,"",MIN(E6:O6)) | Q6: =IF(COUNT(E6:O6)=0,"",LOOKUP(2,1/(E6:O6<>""),E6:O6)) | R6: =IF(P6="","",ROUND(P6*RESUMEN!$B$4,0)) | S6: =COUNT(E6:O6)
A7: 79684371047437 | B7: ANILLO GC BLONDIE ANCHO CON ZIRCONIA | C7: 8 | D7: Brass + Zirconia | F7: 9 | J7: 9 | K7: 9 | P7: =IF(COUNT(E7:O7)=0,"",MIN(E7:O7)) | Q7: =IF(COUNT(E7:O7)=0,"",LOOKUP(2,1/(E7:O7<>""),E7:O7)) | R7: =IF(P7="","",ROUND(P7*RESUMEN!$B$4,0)) | S7: =COUNT(E7:O7)
A8: 29502191036205 | B8: ANILLO LV LES GASTONS SILVER | C8: 8 | D8: Brass | F8: 9 | P8: =IF(COUNT(E8:O8)=0,"",MIN(E8:O8)) | Q8: =IF(COUNT(E8:O8)=0,"",LOOKUP(2,1/(E8:O8<>""),E8:O8)) | R8: =IF(P8="","",ROUND(P8*RESUMEN!$B$4,0)) | S8: =COUNT(E8:O8)
A9: 88201821024717 | B9: ANILLO LV SILVER MICROZIRCONIAS | C9: 8 | D9: Brass + Zirconia | F9: 9 | P9: =IF(COUNT(E9:O9)=0,"",MIN(E9:O9)) | Q9: =IF(COUNT(E9:O9)=0,"",LOOKUP(2,1/(E9:O9<>""),E9:O9)) | R9: =IF(P9="","",ROUND(P9*RESUMEN!$B$4,0)) | S9: =COUNT(E9:O9)
A10: 66593be00cc70 | B10: ANILLO PERLEE ROSEGOLD | C10: 7 | N10: 7 | P10: =IF(COUNT(E10:O10)=0,"",MIN(E10:O10)) | Q10: =IF(COUNT(E10:O10)=0,"",LOOKUP(2,1/(E10:O10<>""),E10:O10)) | R10: =IF(P10="","",ROUND(P10*RESUMEN!$B$4,0)) | S10: =COUNT(E10:O10)
A11: 15857685585804 | B11: ANILLO TRES AROS | C11: 6 | N11: 6 | P11: =IF(COUNT(E11:O11)=0,"",MIN(E11:O11)) | Q11: =IF(COUNT(E11:O11)=0,"",LOOKUP(2,1/(E11:O11<>""),E11:O11)) | R11: =IF(P11="","",ROUND(P11*RESUMEN!$B$4,0)) | S11: =COUNT(E11:O11)
A12: 56481488554124 | B12: ANILLO TRES AROS CON ZIRCONIA | C12: 6 | N12: 13 | P12: =IF(COUNT(E12:O12)=0,"",MIN(E12:O12)) | Q12: =IF(COUNT(E12:O12)=0,"",LOOKUP(2,1/(E12:O12<>""),E12:O12)) | R12: =IF(P12="","",ROUND(P12*RESUMEN!$B$4,0)) | S12: =COUNT(E12:O12)
A13: 56481485030668 | B13: ANILLO TRES AROS SILVER/BLACK | C13: 8 | N13: 6 | P13: =IF(COUNT(E13:O13)=0,"",MIN(E13:O13)) | Q13: =IF(COUNT(E13:O13)=0,"",LOOKUP(2,1/(E13:O13<>""),E13:O13)) | R13: =IF(P13="","",ROUND(P13*RESUMEN!$B$4,0)) | S13: =COUNT(E13:O13)
A14: 75249151006253 | B14: ARETES BV ZERO 1 GOLD CON ZIRCONIA | C14: Default Title | D14: Brass + Zirconia | F14: 9 | P14: =IF(COUNT(E14:O14)=0,"",MIN(E14:O14)) | Q14: =IF(COUNT(E14:O14)=0,"",LOOKUP(2,1/(E14:O14<>""),E14:O14)) | R14: =IF(P14="","",ROUND(P14*RESUMEN!$B$4,0)) | S14: =COUNT(E14:O14)
A15: 66148671022797 | B15: ARETES CD GOLD BLACK CON ZIRCONIA | C15: Default Title | D15: Brass + Zirconia | F15: 9 | J15: 9 | K15: 9 | M15: 9 | P15: =IF(COUNT(E15:O15)=0,"",MIN(E15:O15)) | Q15: =IF(COUNT(E15:O15)=0,"",LOOKUP(2,1/(E15:O15<>""),E15:O15)) | R15: =IF(P15="","",ROUND(P15*RESUMEN!$B$4,0)) | S15: =COUNT(E15:O15)
A16: 69612281066221 | B16: ARETES CD GOLD WHITE CON ZIRCONIA | C16: Default Title | D16: Brass + Zirconia | F16: 9 | J16: 9 | K16: 9 | N16: 9 | P16: =IF(COUNT(E16:O16)=0,"",MIN(E16:O16)) | Q16: =IF(COUNT(E16:O16)=0,"",LOOKUP(2,1/(E16:O16<>""),E16:O16)) | R16: =IF(P16="","",ROUND(P16*RESUMEN!$B$4,0)) | S16: =COUNT(E16:O16)
A17: 85409401017325 | B17: ARETES F OVAL GOLD CON ZIRCONIA | C17: Default Title | D17: Brass + Zirconia | F17: 8 | I17: 8 | J17: 8 | K17: 8 | M17: 8 | N17: 8 | P17: =IF(COUNT(E17:O17)=0,"",MIN(E17:O17)) | Q17: =IF(COUNT(E17:O17)=0,"",LOOKUP(2,1/(E17:O17<>""),E17:O17)) | R17: =IF(P17="","",ROUND(P17*RESUMEN!$B$4,0)) | S17: =COUNT(E17:O17)
A18: 83445961082989 | B18: ARETES GC MARMONT GOLD CON PERLA | C18: Default Title | D18: Brass + Zirconia | F18: 9 | O18: 8 | P18: =IF(COUNT(E18:O18)=0,"",MIN(E18:O18)) | Q18: =IF(COUNT(E18:O18)=0,"",LOOKUP(2,1/(E18:O18<>""),E18:O18)) | R18: =IF(P18="","",ROUND(P18*RESUMEN!$B$4,0)) | S18: =COUNT(E18:O18)
A19: 77275241042893 | B19: ARETES MM HEART GOLD WHITE | C19: 2cm | D19: Brass | F19: 8 | I19: 8 | L19: 8 | N19: 8 | O19: 8 | P19: =IF(COUNT(E19:O19)=0,"",MIN(E19:O19)) | Q19: =IF(COUNT(E19:O19)=0,"",LOOKUP(2,1/(E19:O19<>""),E19:O19)) | R19: =IF(P19="","",ROUND(P19*RESUMEN!$B$4,0)) | S19: =COUNT(E19:O19)
A20: 82310551082381 | B20: ARRACADAS F LOGO GOLD | C20: Default Title | D20: Brass | F20: 9 | O20: 9 | P20: =IF(COUNT(E20:O20)=0,"",MIN(E20:O20)) | Q20: =IF(COUNT(E20:O20)=0,"",LOOKUP(2,1/(E20:O20<>""),E20:O20)) | R20: =IF(P20="","",ROUND(P20*RESUMEN!$B$4,0)) | S20: =COUNT(E20:O20)
A21: 76327071018669 | B21: ARRACADAS SERPENTI VIPPER GOLD CON ZIRCONIA | C21: Default Title | D21: Brass + Zirconia | F21: 9 | J21: 9 | K21: 9 | L21: 9 | O21: 9 | P21: =IF(COUNT(E21:O21)=0,"",MIN(E21:O21)) | Q21: =IF(COUNT(E21:O21)=0,"",LOOKUP(2,1/(E21:O21<>""),E21:O21)) | R21: =IF(P21="","",ROUND(P21*RESUMEN!$B$4,0)) | S21: =COUNT(E21:O21)
A22: 93378831084685 | B22: BALLERINAS CC BEIGE BLACK | C22: 23cm | D22: Genuine leather | G22: 55 | I22: 55 | N22: 55 | P22: =IF(COUNT(E22:O22)=0,"",MIN(E22:O22)) | Q22: =IF(COUNT(E22:O22)=0,"",LOOKUP(2,1/(E22:O22<>""),E22:O22)) | R22: =IF(P22="","",ROUND(P22*RESUMEN!$B$4,0)) | S22: =COUNT(E22:O22)
A23: 93378841117453 | B23: BALLERINAS CC BEIGE BLACK | C23: 24-cm | D23: Genuine leather | G23: 55 | I23: 55 | M23: 55 | P23: =IF(COUNT(E23:O23)=0,"",MIN(E23:O23)) | Q23: =IF(COUNT(E23:O23)=0,"",LOOKUP(2,1/(E23:O23<>""),E23:O23)) | R23: =IF(P23="","",ROUND(P23*RESUMEN!$B$4,0)) | S23: =COUNT(E23:O23)
A24: 24780443041101 | B24: BALLERINAS CC COCO MARK | C24: 35/254MX | O24: 60 | P24: =IF(COUNT(E24:O24)=0,"",MIN(E24:O24)) | Q24: =IF(COUNT(E24:O24)=0,"",LOOKUP(2,1/(E24:O24<>""),E24:O24)) | R24: =IF(P24="","",ROUND(P24*RESUMEN!$B$4,0)) | S24: =COUNT(E24:O24)
A25: 24780442908333 | B25: BALLERINAS CC COCO MARK | C25: 38/25MX | O25: 60 | P25: =IF(COUNT(E25:O25)=0,"",MIN(E25:O25)) | Q25: =IF(COUNT(E25:O25)=0,"",LOOKUP(2,1/(E25:O25<>""),E25:O25)) | R25: =IF(P25="","",ROUND(P25*RESUMEN!$B$4,0)) | S25: =COUNT(E25:O25)
A26: 3378841221933 | B26: BALLERINAS LV BROWN CON INSIGNIAS | C26: 24CM | G26: 68 | P26: =IF(COUNT(E26:O26)=0,"",MIN(E26:O26)) | Q26: =IF(COUNT(E26:O26)=0,"",LOOKUP(2,1/(E26:O26<>""),E26:O26)) | R26: =IF(P26="","",ROUND(P26*RESUMEN!$B$4,0)) | S26: =COUNT(E26:O26)
A27: 93378841221933 | B27: BALLERINAS LV BROWN CON INSIGNIAS | C27: 24cm | D27: Genuine leather | I27: 68 | O27: 68 | P27: =IF(COUNT(E27:O27)=0,"",MIN(E27:O27)) | Q27: =IF(COUNT(E27:O27)=0,"",LOOKUP(2,1/(E27:O27<>""),E27:O27)) | R27: =IF(P27="","",ROUND(P27*RESUMEN!$B$4,0)) | S27: =COUNT(E27:O27)
A28: 93378841354701 | B28: BALLERINAS LV BROWN CON INSIGNIAS | C28: 25cm | D28: Genuine leather | G28: 68 | I28: 68 | O28: 68 | P28: =IF(COUNT(E28:O28)=0,"",MIN(E28:O28)) | Q28: =IF(COUNT(E28:O28)=0,"",LOOKUP(2,1/(E28:O28<>""),E28:O28)) | R28: =IF(P28="","",ROUND(P28*RESUMEN!$B$4,0)) | S28: =COUNT(E28:O28)
A29: 93378841495885 | B29: BALLERINAS MM BLACK CON ZIRCONIAS | C29: 24CM | G29: 72 | P29: =IF(COUNT(E29:O29)=0,"",MIN(E29:O29)) | Q29: =IF(COUNT(E29:O29)=0,"",LOOKUP(2,1/(E29:O29<>""),E29:O29)) | R29: =IF(P29="","",ROUND(P29*RESUMEN!$B$4,0)) | S29: =COUNT(E29:O29)
A30: 93378841508909 | B30: BALLERINAS PR BLACK CON LOGO | C30: 24cm | D30: Genuine leather | G30: 58 | I30: 58 | P30: =IF(COUNT(E30:O30)=0,"",MIN(E30:O30)) | Q30: =IF(COUNT(E30:O30)=0,"",LOOKUP(2,1/(E30:O30<>""),E30:O30)) | R30: =IF(P30="","",ROUND(P30*RESUMEN!$B$4,0)) | S30: =COUNT(E30:O30)
A31: 93378841641677 | B31: BALLERINAS PR BLACK CON LOGO | C31: 25-cm | D31: Genuine leather | G31: 58 | I31: 58 | M31: 58 | P31: =IF(COUNT(E31:O31)=0,"",MIN(E31:O31)) | Q31: =IF(COUNT(E31:O31)=0,"",LOOKUP(2,1/(E31:O31<>""),E31:O31)) | R31: =IF(P31="","",ROUND(P31*RESUMEN!$B$4,0)) | S31: =COUNT(E31:O31)
A32: 46740671064493 | B32: BOLSA DE DEPORTE BLACK | C32: Default Title | D32: Material: Spande | F32: 15 | I32: 40 | P32: =IF(COUNT(E32:O32)=0,"",MIN(E32:O32)) | Q32: =IF(COUNT(E32:O32)=0,"",LOOKUP(2,1/(E32:O32<>""),E32:O32)) | R32: =IF(P32="","",ROUND(P32*RESUMEN!$B$4,0)) | S32: =COUNT(E32:O32)
A33: 73626631067117 | B33: BOLSA DE MANO G GREEN | C33: Default Title | D33: Genuine leather | F33: 46 | I33: 35 | L33: 35 | O33: 35 | P33: =IF(COUNT(E33:O33)=0,"",MIN(E33:O33)) | Q33: =IF(COUNT(E33:O33)=0,"",LOOKUP(2,1/(E33:O33<>""),E33:O33)) | R33: =IF(P33="","",ROUND(P33*RESUMEN!$B$4,0)) | S33: =COUNT(E33:O33)
A34: 58450831080173 | B34: BOLSA DE RAQUETA LLM CREAM | C34: Default Title | D34: Bag Material: Ny | F34: 8 | I34: 30 | M34: 30 | P34: =IF(COUNT(E34:O34)=0,"",MIN(E34:O34)) | Q34: =IF(COUNT(E34:O34)=0,"",LOOKUP(2,1/(E34:O34<>""),E34:O34)) | R34: =IF(P34="","",ROUND(P34*RESUMEN!$B$4,0)) | S34: =COUNT(E34:O34)
A35: DANAHE | B35: BOLSA GC WHITE | O35: 21 | P35: =IF(COUNT(E35:O35)=0,"",MIN(E35:O35)) | Q35: =IF(COUNT(E35:O35)=0,"",LOOKUP(2,1/(E35:O35<>""),E35:O35)) | R35: =IF(P35="","",ROUND(P35*RESUMEN!$B$4,0)) | S35: =COUNT(E35:O35)
A36: 64e78f8c69235 | B36: BOLSA GC WHITE | C36: 22.5.cmx15cm | D36: Genuine leather | G36: 56 | M36: 56 | P36: =IF(COUNT(E36:O36)=0,"",MIN(E36:O36)) | Q36: =IF(COUNT(E36:O36)=0,"",LOOKUP(2,1/(E36:O36<>""),E36:O36)) | R36: =IF(P36="","",ROUND(P36*RESUMEN!$B$4,0)) | S36: =COUNT(E36:O36)
A37: 27168511089165 | B37: BOLSA GG SMALL BROWN | C37: Default Title | D37: Stainless steel | F37: 28 | I37: 46 | J37: 46 | K37: 46 | P37: =IF(COUNT(E37:O37)=0,"",MIN(E37:O37)) | Q37: =IF(COUNT(E37:O37)=0,"",LOOKUP(2,1/(E37:O37<>""),E37:O37)) | R37: =IF(P37="","",ROUND(P37*RESUMEN!$B$4,0)) | S37: =COUNT(E37:O37)
A38: 62571331097101 | B38: BOLSA LLM BLACK | C38: Default Title | D38: Genuine leather | F38: 35 | I38: 8 | M38: 8 | O38: 8 | P38: =IF(COUNT(E38:O38)=0,"",MIN(E38:O38)) | Q38: =IF(COUNT(E38:O38)=0,"",LOOKUP(2,1/(E38:O38<>""),E38:O38)) | R38: =IF(P38="","",ROUND(P38*RESUMEN!$B$4,0)) | S38: =COUNT(E38:O38)
A39: 52394691046605 | B39: BOLSA NANO NOÉ LV BROWN | C39: 13 cm de largo x 16 cm de alto x 10cm de ancho | I39: 20 | M39: 20 | P39: =IF(COUNT(E39:O39)=0,"",MIN(E39:O39)) | Q39: =IF(COUNT(E39:O39)=0,"",LOOKUP(2,1/(E39:O39<>""),E39:O39)) | R39: =IF(P39="","",ROUND(P39*RESUMEN!$B$4,0)) | S39: =COUNT(E39:O39)
A40: 64e78f2fafa3d | B40: BOLSA YSL WHITE | C40: 24cm x 15cm | D40: Genuine leather | H40: 52 | P40: =IF(COUNT(E40:O40)=0,"",MIN(E40:O40)) | Q40: =IF(COUNT(E40:O40)=0,"",LOOKUP(2,1/(E40:O40<>""),E40:O40)) | R40: =IF(P40="","",ROUND(P40*RESUMEN!$B$4,0)) | S40: =COUNT(E40:O40)
A41: 46281181071009 | B41: BOLSA YSL WHITE | C41: NUDE 24cm x 15cm | M41: 52 | P41: =IF(COUNT(E41:O41)=0,"",MIN(E41:O41)) | Q41: =IF(COUNT(E41:O41)=0,"",LOOKUP(2,1/(E41:O41<>""),E41:O41)) | R41: =IF(P41="","",ROUND(P41*RESUMEN!$B$4,0)) | S41: =COUNT(E41:O41)
A42: 94350549840780 | B42: BOLSO A TIEDIE | C42: 31cm de alto x 45.5cm de largo x 18cm de ancho | D42: Canvas | E42: 0 | G42: 10 | H42: 10 | J42: 10 | K42: 10 | M42: 10 | N42: 10 | P42: =IF(COUNT(E42:O42)=0,"",MIN(E42:O42)) | Q42: =IF(COUNT(E42:O42)=0,"",LOOKUP(2,1/(E42:O42<>""),E42:O42)) | R42: =IF(P42="","",ROUND(P42*RESUMEN!$B$4,0)) | S42: =COUNT(E42:O42)
A43: 66581df1de94d | B43: BOLSO B BLACK | C43: 17cm de largo x 11cm de alto x 8.3cm de ancho | D43: Genuine leather | E43: 45 | J43: 45 | K43: 45 | M43: 45 | P43: =IF(COUNT(E43:O43)=0,"",MIN(E43:O43)) | Q43: =IF(COUNT(E43:O43)=0,"",LOOKUP(2,1/(E43:O43<>""),E43:O43)) | R43: =IF(P43="","",ROUND(P43*RESUMEN!$B$4,0)) | S43: =COUNT(E43:O43)
A44: 66ec817c20ce6 | B44: BOLSO B BLACK | C44: HIGH QUALITY 23cm de largo x 14.5cm de alto x 10cm de ancho | D44: Genuine leather | G44: 45 | P44: =IF(COUNT(E44:O44)=0,"",MIN(E44:O44)) | Q44: =IF(COUNT(E44:O44)=0,"",LOOKUP(2,1/(E44:O44<>""),E44:O44)) | R44: =IF(P44="","",ROUND(P44*RESUMEN!$B$4,0)) | S44: =COUNT(E44:O44)
A45: 654bdbcfddee8 | B45: BOLSO B BLACK LISA | C45: 17cm de largo x 11cm de alto x 8.3cm de ancho | M45: 45 | P45: =IF(COUNT(E45:O45)=0,"",MIN(E45:O45)) | Q45: =IF(COUNT(E45:O45)=0,"",LOOKUP(2,1/(E45:O45<>""),E45:O45)) | R45: =IF(P45="","",ROUND(P45*RESUMEN!$B$4,0)) | S45: =COUNT(E45:O45)
A46: 66ec817ce19fe | B46: BOLSO B BLACK LISO | C46: HIGH QUALITY 23cm de largo x 14.5cm de alto x 10cm de ancho | D46: Genuine leather | E46: 45 | J46: 45 | K46: 45 | L46: 45 | P46: =IF(COUNT(E46:O46)=0,"",MIN(E46:O46)) | Q46: =IF(COUNT(E46:O46)=0,"",LOOKUP(2,1/(E46:O46<>""),E46:O46)) | R46: =IF(P46="","",ROUND(P46*RESUMEN!$B$4,0)) | S46: =COUNT(E46:O46)
A47: 654bdbd00f373 | B47: BOLSO B WHITE | C47: 17cm de largo x 11cm de alto x 8.3cm de ancho | E47: 45 | I47: 45 | P47: =IF(COUNT(E47:O47)=0,"",MIN(E47:O47)) | Q47: =IF(COUNT(E47:O47)=0,"",LOOKUP(2,1/(E47:O47<>""),E47:O47)) | R47: =IF(P47="","",ROUND(P47*RESUMEN!$B$4,0)) | S47: =COUNT(E47:O47)
A48: 43728086470604 | B48: BOLSO BT ANDIAMO CLUTCH BROWN | C48: 30.5cm de larg | H48: 60 | P48: =IF(COUNT(E48:O48)=0,"",MIN(E48:O48)) | Q48: =IF(COUNT(E48:O48)=0,"",LOOKUP(2,1/(E48:O48<>""),E48:O48)) | R48: =IF(P48="","",ROUND(P48*RESUMEN!$B$4,0)) | S48: =COUNT(E48:O48)
A49: 68374516907020 | B49: BOLSO C CLAUDE BLACK | C49: 21.5cm de largo x 11.5cm de alto x 4.5cm de ancho | E49: 52 | P49: =IF(COUNT(E49:O49)=0,"",MIN(E49:O49)) | Q49: =IF(COUNT(E49:O49)=0,"",LOOKUP(2,1/(E49:O49<>""),E49:O49)) | R49: =IF(P49="","",ROUND(P49*RESUMEN!$B$4,0)) | S49: =COUNT(E49:O49)
A50: 24780442420877 | B50: BOLSO C N°25 DENIM | O50: 65 | P50: =IF(COUNT(E50:O50)=0,"",MIN(E50:O50)) | Q50: =IF(COUNT(E50:O50)=0,"",LOOKUP(2,1/(E50:O50<>""),E50:O50)) | R50: =IF(P50="","",ROUND(P50*RESUMEN!$B$4,0)) | S50: =COUNT(E50:O50)
A51: 24780442584717 | B51: BOLSO C N°25 GOLD | O51: 65 | P51: =IF(COUNT(E51:O51)=0,"",MIN(E51:O51)) | Q51: =IF(COUNT(E51:O51)=0,"",LOOKUP(2,1/(E51:O51<>""),E51:O51)) | R51: =IF(P51="","",ROUND(P51*RESUMEN!$B$4,0)) | S51: =COUNT(E51:O51)
A52: 99781782573645 | B52: BOLSO C TANK TOP | C52: Default Title | D52: Genuine leather | J52: 55 | K52: 55 | N52: 55 | P52: =IF(COUNT(E52:O52)=0,"",MIN(E52:O52)) | Q52: =IF(COUNT(E52:O52)=0,"",LOOKUP(2,1/(E52:O52<>""),E52:O52)) | R52: =IF(P52="","",ROUND(P52*RESUMEN!$B$4,0)) | S52: =COUNT(E52:O52)
A53: 63666799441676 | B53: BOLSO C TOTE | C53: 20cm de largo x 21 cm de alto x 11cm de ancho | D53: Genuine leather | E53: 72 | H53: 72 | J53: 72 | K53: 72 | P53: =IF(COUNT(E53:O53)=0,"",MIN(E53:O53)) | Q53: =IF(COUNT(E53:O53)=0,"",LOOKUP(2,1/(E53:O53<>""),E53:O53)) | R53: =IF(P53="","",ROUND(P53*RESUMEN!$B$4,0)) | S53: =COUNT(E53:O53)
A54: 43728083210732 | B54: BOLSO CC 22 | C54: 19cm de alto x 23.5cm de ancho | D54: Genuine leather | E54: 50 | H54: 50 | I54: 50 | L54: 50 | P54: =IF(COUNT(E54:O54)=0,"",MIN(E54:O54)) | Q54: =IF(COUNT(E54:O54)=0,"",LOOKUP(2,1/(E54:O54<>""),E54:O54)) | R54: =IF(P54="","",ROUND(P54*RESUMEN!$B$4,0)) | S54: =COUNT(E54:O54)
A55: 17760786033676 | B55: BOLSO CC 22 SILVER | C55: 19cm de alto x 23.5cm de ancho | D55: Genuine leather | G55: 50 | H55: 50 | I55: 50 | L55: 50 | P55: =IF(COUNT(E55:O55)=0,"",MIN(E55:O55)) | Q55: =IF(COUNT(E55:O55)=0,"",LOOKUP(2,1/(E55:O55<>""),E55:O55)) | R55: =IF(P55="","",ROUND(P55*RESUMEN!$B$4,0)) | S55: =COUNT(E55:O55)
A56: 64571791072897 | B56: BOLSO CC BLACK | C56: 25cm de largo x 17cm de alto x 6cm de ancho | D56: Genuine leather | E56: 48 | H56: 48 | I56: 48 | J56: 48 | K56: 48 | L56: 48 | N56: 48 | O56: 48 | P56: =IF(COUNT(E56:O56)=0,"",MIN(E56:O56)) | Q56: =IF(COUNT(E56:O56)=0,"",LOOKUP(2,1/(E56:O56<>""),E56:O56)) | R56: =IF(P56="","",ROUND(P56*RESUMEN!$B$4,0)) | S56: =COUNT(E56:O56)
A57: 24780442777933 | B57: BOLSO CC CLUTCH WHITE PEARL | O57: 58 | P57: =IF(COUNT(E57:O57)=0,"",MIN(E57:O57)) | Q57: =IF(COUNT(E57:O57)=0,"",LOOKUP(2,1/(E57:O57<>""),E57:O57)) | R57: =IF(P57="","",ROUND(P57*RESUMEN!$B$4,0)) | S57: =COUNT(E57:O57)
A58: 24780442388109 | B58: BOLSO CC LARGE TOTE | O58: 69 | P58: =IF(COUNT(E58:O58)=0,"",MIN(E58:O58)) | Q58: =IF(COUNT(E58:O58)=0,"",LOOKUP(2,1/(E58:O58<>""),E58:O58)) | R58: =IF(P58="","",ROUND(P58*RESUMEN!$B$4,0)) | S58: =COUNT(E58:O58)
A59: 24780442224269 | B59: BOLSO CC MARY JANES | O59: 58 | P59: =IF(COUNT(E59:O59)=0,"",MIN(E59:O59)) | Q59: =IF(COUNT(E59:O59)=0,"",LOOKUP(2,1/(E59:O59<>""),E59:O59)) | R59: =IF(P59="","",ROUND(P59*RESUMEN!$B$4,0)) | S59: =COUNT(E59:O59)
A60: 24780442614093 | B60: BOLSO CC MINITASKE | O60: 65 | P60: =IF(COUNT(E60:O60)=0,"",MIN(E60:O60)) | Q60: =IF(COUNT(E60:O60)=0,"",LOOKUP(2,1/(E60:O60<>""),E60:O60)) | R60: =IF(P60="","",ROUND(P60*RESUMEN!$B$4,0)) | S60: =COUNT(E60:O60)
A61: 24780442101677 | B61: BOLSO CC N°25 WHITE BROWN | O61: 69 | P61: =IF(COUNT(E61:O61)=0,"",MIN(E61:O61)) | Q61: =IF(COUNT(E61:O61)=0,"",LOOKUP(2,1/(E61:O61<>""),E61:O61)) | R61: =IF(P61="","",ROUND(P61*RESUMEN!$B$4,0)) | S61: =COUNT(E61:O61)
A62: 24780442041229 | B62: BOLSO CC SHOPPING TOTE | O62: 55 | P62: =IF(COUNT(E62:O62)=0,"",MIN(E62:O62)) | Q62: =IF(COUNT(E62:O62)=0,"",LOOKUP(2,1/(E62:O62<>""),E62:O62)) | R62: =IF(P62="","",ROUND(P62*RESUMEN!$B$4,0)) | S62: =COUNT(E62:O62)
A63: 43728083564972 | B63: BOLSO CD 30 MONTAIGNE | C63: 22.5cm de larg | D63: Genuine leather | H63: 52 | P63: =IF(COUNT(E63:O63)=0,"",MIN(E63:O63)) | Q63: =IF(COUNT(E63:O63)=0,"",LOOKUP(2,1/(E63:O63<>""),E63:O63)) | R63: =IF(P63="","",ROUND(P63*RESUMEN!$B$4,0)) | S63: =COUNT(E63:O63)
A64: 43728087914796 | B64: BOLSO CD 30 MONTAIGNE BLACK | C64: 12cm de alto x 20cm de largo x 4cm de ancho | E64: 52 | N64: 52 | P64: =IF(COUNT(E64:O64)=0,"",MIN(E64:O64)) | Q64: =IF(COUNT(E64:O64)=0,"",LOOKUP(2,1/(E64:O64<>""),E64:O64)) | R64: =IF(P64="","",ROUND(P64*RESUMEN!$B$4,0)) | S64: =COUNT(E64:O64)
A65: 29953901383309 | B65: BOLSO CD BOOK TOTE BANDOLERA | O65: 88 | P65: =IF(COUNT(E65:O65)=0,"",MIN(E65:O65)) | Q65: =IF(COUNT(E65:O65)=0,"",LOOKUP(2,1/(E65:O65<>""),E65:O65)) | R65: =IF(P65="","",ROUND(P65*RESUMEN!$B$4,0)) | S65: =COUNT(E65:O65)
A66: 69521938776076 | B66: BOLSO CD CARO | C66: 18.5cm x 12cm x 6cm | D66: Genuine leather | H66: 58 | J66: 58 | K66: 58 | L66: 58 | P66: =IF(COUNT(E66:O66)=0,"",MIN(E66:O66)) | Q66: =IF(COUNT(E66:O66)=0,"",LOOKUP(2,1/(E66:O66<>""),E66:O66)) | R66: =IF(P66="","",ROUND(P66*RESUMEN!$B$4,0)) | S66: =COUNT(E66:O66)
A67: 29953901152237 | B67: BOLSO CD CRUNCHY MILLY | O67: 65 | P67: =IF(COUNT(E67:O67)=0,"",MIN(E67:O67)) | Q67: =IF(COUNT(E67:O67)=0,"",LOOKUP(2,1/(E67:O67<>""),E67:O67)) | R67: =IF(P67="","",ROUND(P67*RESUMEN!$B$4,0)) | S67: =COUNT(E67:O67)
A68: 43728083428428 | B68: BOLSO CD GROOVE 20 | C68: 25.5cm de largo x 21cm de alto x 15.5cm de ancho | D68: Canvas | E68: 55 | I68: 55 | J68: 55 | K68: 55 | P68: =IF(COUNT(E68:O68)=0,"",MIN(E68:O68)) | Q68: =IF(COUNT(E68:O68)=0,"",LOOKUP(2,1/(E68:O68<>""),E68:O68)) | R68: =IF(P68="","",ROUND(P68*RESUMEN!$B$4,0)) | S68: =COUNT(E68:O68)
A69: 29953901454477 | B69: BOLSO CD MESSENGER SADDLE ALL BLACK | O69: 64 | P69: =IF(COUNT(E69:O69)=0,"",MIN(E69:O69)) | Q69: =IF(COUNT(E69:O69)=0,"",LOOKUP(2,1/(E69:O69<>""),E69:O69)) | R69: =IF(P69="","",ROUND(P69*RESUMEN!$B$4,0)) | S69: =COUNT(E69:O69)
A70: 73794531662733 | B70: BOLSO CD MY TOP HANDLE | C70: Default Title | D70: Genuine leather | J70: 55 | K70: 55 | N70: 55 | P70: =IF(COUNT(E70:O70)=0,"",MIN(E70:O70)) | Q70: =IF(COUNT(E70:O70)=0,"",LOOKUP(2,1/(E70:O70<>""),E70:O70)) | R70: =IF(P70="","",ROUND(P70*RESUMEN!$B$4,0)) | S70: =COUNT(E70:O70)
A71: 17416232396428 | B71: BOLSO CD TOTE | C71: 36.5cm x 28cm x 10cm | D71: Canvas | E71: 45 | G71: 45 | H71: 45 | J71: 45 | K71: 45 | L71: 45 | P71: =IF(COUNT(E71:O71)=0,"",MIN(E71:O71)) | Q71: =IF(COUNT(E71:O71)=0,"",LOOKUP(2,1/(E71:O71<>""),E71:O71)) | R71: =IF(P71="","",ROUND(P71*RESUMEN!$B$4,0)) | S71: =COUNT(E71:O71)
A72: 43728083774252 | B72: BOLSO DE VIAJE LV KEEPALL 45 | C72: 44cm de largo x 25cm de alto x 20cm de ancho | D72: Genuine leather | I72: 60 | L72: 60 | P72: =IF(COUNT(E72:O72)=0,"",MIN(E72:O72)) | Q72: =IF(COUNT(E72:O72)=0,"",LOOKUP(2,1/(E72:O72<>""),E72:O72)) | R72: =IF(P72="","",ROUND(P72*RESUMEN!$B$4,0)) | S72: =COUNT(E72:O72)
A73: 14139090074764 | B73: BOLSO DE VIAJE C TRIOMPHE | C73: 50cm x 25cm x | D73: Genuine leather | H73: 65 | P73: =IF(COUNT(E73:O73)=0,"",MIN(E73:O73)) | Q73: =IF(COUNT(E73:O73)=0,"",LOOKUP(2,1/(E73:O73<>""),E73:O73)) | R73: =IF(P73="","",ROUND(P73*RESUMEN!$B$4,0)) | S73: =COUNT(E73:O73)
A74: 43728085758636 | B74: BOLSO DE VIAJE GC LOGO | C74: 42cm de largo | E74: 75 | H74: 75 | P74: =IF(COUNT(E74:O74)=0,"",MIN(E74:O74)) | Q74: =IF(COUNT(E74:O74)=0,"",LOOKUP(2,1/(E74:O74<>""),E74:O74)) | R74: =IF(P74="","",ROUND(P74*RESUMEN!$B$4,0)) | S74: =COUNT(E74:O74)
A75: 43728136587308 | B75: BOLSO DE VIAJE LV BLACK | C75: HIGH QUALITY | D75: Stainless steel | E75: 55 | H75: 55 | L75: 55 | M75: 55 | P75: =IF(COUNT(E75:O75)=0,"",MIN(E75:O75)) | Q75: =IF(COUNT(E75:O75)=0,"",LOOKUP(2,1/(E75:O75<>""),E75:O75)) | R75: =IF(P75="","",ROUND(P75*RESUMEN!$B$4,0)) | S75: =COUNT(E75:O75)
A76: 34163623006797 | B76: BOLSO F BAGUETTE TEJIDO | C76: Default Title | M76: 46 | P76: =IF(COUNT(E76:O76)=0,"",MIN(E76:O76)) | Q76: =IF(COUNT(E76:O76)=0,"",LOOKUP(2,1/(E76:O76<>""),E76:O76)) | R76: =IF(P76="","",ROUND(P76*RESUMEN!$B$4,0)) | S76: =COUNT(E76:O76)
A77: 6701d2514beab | B77: BOLSO F FENDIGRAPHY | C77: 24cm de largo x 19cm de alto x 8cm de ancho | M77: 65 | P77: =IF(COUNT(E77:O77)=0,"",MIN(E77:O77)) | Q77: =IF(COUNT(E77:O77)=0,"",LOOKUP(2,1/(E77:O77<>""),E77:O77)) | R77: =IF(P77="","",ROUND(P77*RESUMEN!$B$4,0)) | S77: =COUNT(E77:O77)
A78: 43728085695276 | B78: BOLSO F FENDIGRAPHY BLACK | C78: 14cm de largo x 11cm de alto x 4cm de ancho | E78: 50 | P78: =IF(COUNT(E78:O78)=0,"",MIN(E78:O78)) | Q78: =IF(COUNT(E78:O78)=0,"",LOOKUP(2,1/(E78:O78<>""),E78:O78)) | R78: =IF(P78="","",ROUND(P78*RESUMEN!$B$4,0)) | S78: =COUNT(E78:O78)
A79: 91345322411533 | B79: BOLSO F MON TRESOR | C79: Default Title | M79: 52 | O79: 52 | P79: =IF(COUNT(E79:O79)=0,"",MIN(E79:O79)) | Q79: =IF(COUNT(E79:O79)=0,"",LOOKUP(2,1/(E79:O79<>""),E79:O79)) | R79: =IF(P79="","",ROUND(P79*RESUMEN!$B$4,0)) | S79: =COUNT(E79:O79)
A80: 34163623137869 | B80: BOLSO F SUNSHINE BLACK | C80: Default Title | M80: 56 | P80: =IF(COUNT(E80:O80)=0,"",MIN(E80:O80)) | Q80: =IF(COUNT(E80:O80)=0,"",LOOKUP(2,1/(E80:O80<>""),E80:O80)) | R80: =IF(P80="","",ROUND(P80*RESUMEN!$B$4,0)) | S80: =COUNT(E80:O80)
A81: 64e78f8a50e61 | B81: BOLSO GC BLACK | C81: 22.5.cmx15cm | D81: Genuine leather | G81: 56 | I81: 56 | P81: =IF(COUNT(E81:O81)=0,"",MIN(E81:O81)) | Q81: =IF(COUNT(E81:O81)=0,"",LOOKUP(2,1/(E81:O81<>""),E81:O81)) | R81: =IF(P81="","",ROUND(P81*RESUMEN!$B$4,0)) | S81: =COUNT(E81:O81)
A82: 64e78f8d3897d | B82: BOLSO GC BROWN | C82: 22.5.cmx15cm | D82: Genuine leather | G82: 56 | M82: 56 | P82: =IF(COUNT(E82:O82)=0,"",MIN(E82:O82)) | Q82: =IF(COUNT(E82:O82)=0,"",LOOKUP(2,1/(E82:O82<>""),E82:O82)) | R82: =IF(P82="","",ROUND(P82*RESUMEN!$B$4,0)) | S82: =COUNT(E82:O82)
A83: 99781782406413 | B83: BOLSO GC BUCKET EMBLEM | C83: Default Title | D83: Genuine leather | J83: 58 | K83: 58 | M83: 58 | N83: 58 | O83: 58 | P83: =IF(COUNT(E83:O83)=0,"",MIN(E83:O83)) | Q83: =IF(COUNT(E83:O83)=0,"",LOOKUP(2,1/(E83:O83<>""),E83:O83)) | R83: =IF(P83="","",ROUND(P83*RESUMEN!$B$4,0)) | S83: =COUNT(E83:O83)
A84: 99781782370253 | B84: BOLSO GC BUCKET MARMONT | C84: Default Title | D84: Genuine leather | J84: 42 | K84: 42 | N84: 42 | P84: =IF(COUNT(E84:O84)=0,"",MIN(E84:O84)) | Q84: =IF(COUNT(E84:O84)=0,"",LOOKUP(2,1/(E84:O84<>""),E84:O84)) | R84: =IF(P84="","",ROUND(P84*RESUMEN!$B$4,0)) | S84: =COUNT(E84:O84)
A85: 43728086795884 | B85: BOLSO GC CHERRY | C85: 25cm de largo x 16cm de alto x 7.5cm de ancho | D85: Genuine leather | I85: 56 | L85: 56 | P85: =IF(COUNT(E85:O85)=0,"",MIN(E85:O85)) | Q85: =IF(COUNT(E85:O85)=0,"",LOOKUP(2,1/(E85:O85<>""),E85:O85)) | R85: =IF(P85="","",ROUND(P85*RESUMEN!$B$4,0)) | S85: =COUNT(E85:O85)
A86: 677c26af628d5 | B86: BOLSO GC DIONYSUS CHERRY RED | C86: 18cm de largo x 12cm de alto x 4cm de ancho | G86: 52 | P86: =IF(COUNT(E86:O86)=0,"",MIN(E86:O86)) | Q86: =IF(COUNT(E86:O86)=0,"",LOOKUP(2,1/(E86:O86<>""),E86:O86)) | R86: =IF(P86="","",ROUND(P86*RESUMEN!$B$4,0)) | S86: =COUNT(E86:O86)
A87: 6701d2474e1b0 | B87: BOLSO GC MARMONT BLACK | C87: 20cm de largo x 15cm de alto x 8cm de ancho | D87: Genuine leather | G87: 48 | H87: 48 | I87: 48 | P87: =IF(COUNT(E87:O87)=0,"",MIN(E87:O87)) | Q87: =IF(COUNT(E87:O87)=0,"",LOOKUP(2,1/(E87:O87<>""),E87:O87)) | R87: =IF(P87="","",ROUND(P87*RESUMEN!$B$4,0)) | S87: =COUNT(E87:O87)
A88: 6701d27d41def | B88: BOLSO GC NUDE | C88: 14.5cm de alto x 25.2cm de largo x 6.7cm de ancho | D88: Genuine leather | E88: 56 | H88: 56 | L88: 56 | N88: 56 | P88: =IF(COUNT(E88:O88)=0,"",MIN(E88:O88)) | Q88: =IF(COUNT(E88:O88)=0,"",LOOKUP(2,1/(E88:O88<>""),E88:O88)) | R88: =IF(P88="","",ROUND(P88*RESUMEN!$B$4,0)) | S88: =COUNT(E88:O88)
A89: 33891171250349 | B89: BOLSO H EVELYNE 29 | O89: 69 | P89: =IF(COUNT(E89:O89)=0,"",MIN(E89:O89)) | Q89: =IF(COUNT(E89:O89)=0,"",LOOKUP(2,1/(E89:O89<>""),E89:O89)) | R89: =IF(P89="","",ROUND(P89*RESUMEN!$B$4,0)) | S89: =COUNT(E89:O89)
A90: 43728099701932 | B90: BOLSO JM WHITE | C90: 16cm de alto x 19.5cm de largo x 7cm de ancho 15cm de alto de correa | D90: Genuine leather | J90: 56 | K90: 56 | P90: =IF(COUNT(E90:O90)=0,"",MIN(E90:O90)) | Q90: =IF(COUNT(E90:O90)=0,"",LOOKUP(2,1/(E90:O90<>""),E90:O90)) | R90: =IF(P90="","",ROUND(P90*RESUMEN!$B$4,0)) | S90: =COUNT(E90:O90)
A91: 654bdb24c007a | B91: BOLSO LADY D BLACK | C91: 23.5cm de largo x 20.5cm largo x 12.5cm de ancho | D91: Genuine leather | G91: 56 | P91: =IF(COUNT(E91:O91)=0,"",MIN(E91:O91)) | Q91: =IF(COUNT(E91:O91)=0,"",LOOKUP(2,1/(E91:O91<>""),E91:O91)) | R91: =IF(P91="","",ROUND(P91*RESUMEN!$B$4,0)) | S91: =COUNT(E91:O91)
A92: 66df5ec06fc76 | B92: BOLSO LADY D CHAROL BLACK | C92: 23.5cm de largo x 21cm de alto x 12cm de ancho | I92: 56 | O92: 56 | P92: =IF(COUNT(E92:O92)=0,"",MIN(E92:O92)) | Q92: =IF(COUNT(E92:O92)=0,"",LOOKUP(2,1/(E92:O92<>""),E92:O92)) | R92: =IF(P92="","",ROUND(P92*RESUMEN!$B$4,0)) | S92: =COUNT(E92:O92)
A93: 66df5ec1b9bcc | B93: BOLSO LADY D CHAROL DUSTY PINK | C93: 23.5cm de largo x 21cm de alto x 12cm de ancho | D93: Genuine leather | E93: 56 | I93: 56 | L93: 56 | N93: 56 | P93: =IF(COUNT(E93:O93)=0,"",MIN(E93:O93)) | Q93: =IF(COUNT(E93:O93)=0,"",LOOKUP(2,1/(E93:O93<>""),E93:O93)) | R93: =IF(P93="","",ROUND(P93*RESUMEN!$B$4,0)) | S93: =COUNT(E93:O93)
A94: 66280391087437 | B94: BOLSO LADY D CHAROL OFF WHITE | C94: 17cm de largo x 15cm de alto x 7cm de ancho | O94: 56 | P94: =IF(COUNT(E94:O94)=0,"",MIN(E94:O94)) | Q94: =IF(COUNT(E94:O94)=0,"",LOOKUP(2,1/(E94:O94<>""),E94:O94)) | R94: =IF(P94="","",ROUND(P94*RESUMEN!$B$4,0)) | S94: =COUNT(E94:O94)
A95: 66df5ec68a185 | B95: BOLSO LADY D CHAROL OFF WHITE | C95: 23.5cm de largo x 21cm de alto x 12cm de ancho | N95: 56 | P95: =IF(COUNT(E95:O95)=0,"",MIN(E95:O95)) | Q95: =IF(COUNT(E95:O95)=0,"",LOOKUP(2,1/(E95:O95<>""),E95:O95)) | R95: =IF(P95="","",ROUND(P95*RESUMEN!$B$4,0)) | S95: =COUNT(E95:O95)
A96: 43728088191436 | B96: BOLSO LADY D CHAROL RED | C96: 23.5cm de largo x 21cm de alto x 12cm de ancho | D96: Genuine leather | L96: 56 | P96: =IF(COUNT(E96:O96)=0,"",MIN(E96:O96)) | Q96: =IF(COUNT(E96:O96)=0,"",LOOKUP(2,1/(E96:O96<>""),E96:O96)) | R96: =IF(P96="","",ROUND(P96*RESUMEN!$B$4,0)) | S96: =COUNT(E96:O96)
A97: 66958009110540 | B97: BOLSO LADY D JOY BLACK | C97: 22cm de largo x 11.5cm dde alto x 6.8cm de ancho (REMATE) | D97: Genuine leather | J97: 56 | K97: 56 | M97: 56 | P97: =IF(COUNT(E97:O97)=0,"",MIN(E97:O97)) | Q97: =IF(COUNT(E97:O97)=0,"",LOOKUP(2,1/(E97:O97<>""),E97:O97)) | R97: =IF(P97="","",ROUND(P97*RESUMEN!$B$4,0)) | S97: =COUNT(E97:O97)
A98: 43124053803148 | B98: BOLSO LADY D JOY BLACK | C98: 25.5cm de largo x 14cm de alto x 6.8cm de ancho | D98: Genuine leather | G98: 56 | I98: 56 | M98: 56 | P98: =IF(COUNT(E98:O98)=0,"",MIN(E98:O98)) | Q98: =IF(COUNT(E98:O98)=0,"",LOOKUP(2,1/(E98:O98<>""),E98:O98)) | R98: =IF(P98="","",ROUND(P98*RESUMEN!$B$4,0)) | S98: =COUNT(E98:O98)
A99: 43124048199820 | B99: BOLSO LADY D JOY WHITE | C99: 10.5cm de alto x 16.4cm de largo x 5.5cm de ancho | D99: Genuine leather | J99: 56 | K99: 56 | P99: =IF(COUNT(E99:O99)=0,"",MIN(E99:O99)) | Q99: =IF(COUNT(E99:O99)=0,"",LOOKUP(2,1/(E99:O99<>""),E99:O99)) | R99: =IF(P99="","",ROUND(P99*RESUMEN!$B$4,0)) | S99: =COUNT(E99:O99)
A100: 37319811028493 | B100: BOLSO LADY D NUDE | C100: 15 cm alto x 17.5 cm de largo x 8 cm de ancho | M100: 56 | P100: =IF(COUNT(E100:O100)=0,"",MIN(E100:O100)) | Q100: =IF(COUNT(E100:O100)=0,"",LOOKUP(2,1/(E100:O100<>""),E100:O100)) | R100: =IF(P100="","",ROUND(P100*RESUMEN!$B$4,0)) | S100: =COUNT(E100:O100)
A101: 66581dfb2f7ce | B101: BOLSO LADY D NUDE | C101: 17cm de largo x 20cm largo x 8cm de ancho | D101: Genuine leather | G101: 56 | J101: 56 | K101: 56 | M101: 56 | N101: 56 | P101: =IF(COUNT(E101:O101)=0,"",MIN(E101:O101)) | Q101: =IF(COUNT(E101:O101)=0,"",LOOKUP(2,1/(E101:O101<>""),E101:O101)) | R101: =IF(P101="","",ROUND(P101*RESUMEN!$B$4,0)) | S101: =COUNT(E101:O101)
...

Sheet CYNTHIA CAO
A1: HISTORIAL DE PRECIOS — CYNTHIA CAO
A2: 8 orden(es) · costo unitario en USD · MXN = MEJOR × RESUMEN!B4 · * = dato del historial previo
A4: SKU | B4: PRODUCTO | C4: VARIANTE | D4: MATERIAL | E4: Sep 2025 05/09 | F4: Oct 2025 25/10 | G4: Ene 2026 07/01 | H4: Feb 2026 18/02 | I4: Mar 2026 19/03 | J4: Abr 2026 27/04 | K4: May 2026 31/05 | L4: Jul 2026 CYN070726* | M4: MEJOR (US) | N4: ÚLTIMA (US) | O4: MXN (mejor×TC) | P4: # ÓRD. | Q4: MEJOR DESDE ABR ★
A5: 43897301288173 | B5: (Sin nombre) | C5: XGH493116 26cm w | D5: Genuine leather mi | G5: 63 | J5: 65 | L5: 63 | M5: =IF(COUNT(E5:L5)=0,"",MIN(E5:L5)) | N5: =IF(COUNT(E5:L5)=0,"",LOOKUP(2,1/(E5:L5<>""),E5:L5)) | O5: =IF(M5="","",ROUND(M5*RESUMEN!$B$4,0)) | P5: =COUNT(E5:L5) | Q5: =IF(COUNT(J5:L5)=0,"",MIN(J5:L5))
A6: 41889241640397 | B6: ANILLO CD ZIRCONIAS GOLD-BLACK | C6: 8 | F6: 9.5 | M6: =IF(COUNT(E6:L6)=0,"",MIN(E6:L6)) | N6: =IF(COUNT(E6:L6)=0,"",LOOKUP(2,1/(E6:L6<>""),E6:L6)) | O6: =IF(M6="","",ROUND(M6*RESUMEN!$B$4,0)) | P6: =COUNT(E6:L6) | Q6: =IF(COUNT(J6:L6)=0,"",MIN(J6:L6))
A7: 43047206256780 | B7: ANILLO LOCK GOLD-SILVER CON ZIRCONIAS | C7: 6 | D7: copper,zircon | G7: 11.8 | I7: 12.8 | J7: 12.8 | M7: =IF(COUNT(E7:L7)=0,"",MIN(E7:L7)) | N7: =IF(COUNT(E7:L7)=0,"",LOOKUP(2,1/(E7:L7<>""),E7:L7)) | O7: =IF(M7="","",ROUND(M7*RESUMEN!$B$4,0)) | P7: =COUNT(E7:L7) | Q7: =IF(COUNT(J7:L7)=0,"",MIN(J7:L7))
A8: 43047206289548 | B8: ANILLO LOCK GOLD-SILVER CON ZIRCONIAS | C8: 7 | D8: copper,zircon | F8: 12.8 | G8: 11.8 | K8: 12.8 | M8: =IF(COUNT(E8:L8)=0,"",MIN(E8:L8)) | N8: =IF(COUNT(E8:L8)=0,"",LOOKUP(2,1/(E8:L8<>""),E8:L8)) | O8: =IF(M8="","",ROUND(M8*RESUMEN!$B$4,0)) | P8: =COUNT(E8:L8) | Q8: =IF(COUNT(J8:L8)=0,"",MIN(J8:L8))
A9: 43047206682764 | B9: ANILLO LOCK ROSEGOLD-SILVER CON ZIRCONIAS | C9: 6 | D9: copper,zircon | G9: 11.8 | M9: =IF(COUNT(E9:L9)=0,"",MIN(E9:L9)) | N9: =IF(COUNT(E9:L9)=0,"",LOOKUP(2,1/(E9:L9<>""),E9:L9)) | O9: =IF(M9="","",ROUND(M9*RESUMEN!$B$4,0)) | P9: =COUNT(E9:L9) | Q9: =IF(COUNT(J9:L9)=0,"",MIN(J9:L9))
A10: 43047206748300 | B10: ANILLO LOCK ROSEGOLD-SILVER CON ZIRCONIAS | C10: 8 | D10: copper,zircon | G10: 11.8 | J10: 12.8 | M10: =IF(COUNT(E10:L10)=0,"",MIN(E10:L10)) | N10: =IF(COUNT(E10:L10)=0,"",LOOKUP(2,1/(E10:L10<>""),E10:L10)) | O10: =IF(M10="","",ROUND(M10*RESUMEN!$B$4,0)) | P10: =COUNT(E10:L10) | Q10: =IF(COUNT(J10:L10)=0,"",MIN(J10:L10))
A11: 39252671264941 | B11: ANILLO LV LETTER GOLD | C11: 7 | D11: stainless steel | F11: 5.28 | H11: 5.28 | I11: 5.28 | M11: =IF(COUNT(E11:L11)=0,"",MIN(E11:L11)) | N11: =IF(COUNT(E11:L11)=0,"",LOOKUP(2,1/(E11:L11<>""),E11:L11)) | O11: =IF(M11="","",ROUND(M11*RESUMEN!$B$4,0)) | P11: =COUNT(E11:L11) | Q11: =IF(COUNT(J11:L11)=0,"",MIN(J11:L11))
A12: 39252671397709 | B12: ANILLO LV LETTER GOLD | C12: 8 | D12: copper | F12: 5.28 | I12: 5.28 | M12: =IF(COUNT(E12:L12)=0,"",MIN(E12:L12)) | N12: =IF(COUNT(E12:L12)=0,"",LOOKUP(2,1/(E12:L12<>""),E12:L12)) | O12: =IF(M12="","",ROUND(M12*RESUMEN!$B$4,0)) | P12: =COUNT(E12:L12) | Q12: =IF(COUNT(J12:L12)=0,"",MIN(J12:L12))
A13: 39252671092621 | B13: ANILLO LV LETTER SILVER | C13: 7 | D13: stainless steel | F13: 5.28 | H13: 5.28 | M13: =IF(COUNT(E13:L13)=0,"",MIN(E13:L13)) | N13: =IF(COUNT(E13:L13)=0,"",LOOKUP(2,1/(E13:L13<>""),E13:L13)) | O13: =IF(M13="","",ROUND(M13*RESUMEN!$B$4,0)) | P13: =COUNT(E13:L13) | Q13: =IF(COUNT(J13:L13)=0,"",MIN(J13:L13))
A14: 39252671125389 | B14: ANILLO LV LETTER SILVER | C14: 8 | F14: 5.28 | M14: =IF(COUNT(E14:L14)=0,"",MIN(E14:L14)) | N14: =IF(COUNT(E14:L14)=0,"",LOOKUP(2,1/(E14:L14<>""),E14:L14)) | O14: =IF(M14="","",ROUND(M14*RESUMEN!$B$4,0)) | P14: =COUNT(E14:L14) | Q14: =IF(COUNT(J14:L14)=0,"",MIN(J14:L14))
A15: 43047228014732 | B15: ANILLO ONE T SILVER CON ZIRCONIA | C15: 6 | D15: copper | E15: 9.8 | G15: 9.8 | K15: 9.8 | M15: =IF(COUNT(E15:L15)=0,"",MIN(E15:L15)) | N15: =IF(COUNT(E15:L15)=0,"",LOOKUP(2,1/(E15:L15<>""),E15:L15)) | O15: =IF(M15="","",ROUND(M15*RESUMEN!$B$4,0)) | P15: =COUNT(E15:L15) | Q15: =IF(COUNT(J15:L15)=0,"",MIN(J15:L15))
A16: 43047228047500 | B16: ANILLO ONE T SILVER CON ZIRCONIA | C16: 7 | E16: 9.8 | M16: =IF(COUNT(E16:L16)=0,"",MIN(E16:L16)) | N16: =IF(COUNT(E16:L16)=0,"",LOOKUP(2,1/(E16:L16<>""),E16:L16)) | O16: =IF(M16="","",ROUND(M16*RESUMEN!$B$4,0)) | P16: =COUNT(E16:L16) | Q16: =IF(COUNT(J16:L16)=0,"",MIN(J16:L16))
A17: 43728112129132 | B17: ANILLO P SHINNY FLOWER | C17: 6 | D17: copper,zircon | F17: 2.6 | I17: 2.6 | M17: =IF(COUNT(E17:L17)=0,"",MIN(E17:L17)) | N17: =IF(COUNT(E17:L17)=0,"",LOOKUP(2,1/(E17:L17<>""),E17:L17)) | O17: =IF(M17="","",ROUND(M17*RESUMEN!$B$4,0)) | P17: =COUNT(E17:L17) | Q17: =IF(COUNT(J17:L17)=0,"",MIN(J17:L17))
A18: 43078594756748 | B18: ANILLO P SHINNY FLOWER | C18: 7 | D18: copper,zircon | F18: 2.6 | G18: 2.6 | L18: 2.6 | M18: =IF(COUNT(E18:L18)=0,"",MIN(E18:L18)) | N18: =IF(COUNT(E18:L18)=0,"",LOOKUP(2,1/(E18:L18<>""),E18:L18)) | O18: =IF(M18="","",ROUND(M18*RESUMEN!$B$4,0)) | P18: =COUNT(E18:L18) | Q18: =IF(COUNT(J18:L18)=0,"",MIN(J18:L18))
A19: 43078594789516 | B19: ANILLO P SHINNY FLOWER | C19: 8 | D19: copper,zircon | H19: 2.6 | I19: 2.6 | M19: =IF(COUNT(E19:L19)=0,"",MIN(E19:L19)) | N19: =IF(COUNT(E19:L19)=0,"",LOOKUP(2,1/(E19:L19<>""),E19:L19)) | O19: =IF(M19="","",ROUND(M19*RESUMEN!$B$4,0)) | P19: =COUNT(E19:L19) | Q19: =IF(COUNT(J19:L19)=0,"",MIN(J19:L19))
A20: 43728112856684 | B20: ANILLO P STARS | C20: 6 | D20: copper | I20: 1.7 | M20: =IF(COUNT(E20:L20)=0,"",MIN(E20:L20)) | N20: =IF(COUNT(E20:L20)=0,"",LOOKUP(2,1/(E20:L20<>""),E20:L20)) | O20: =IF(M20="","",ROUND(M20*RESUMEN!$B$4,0)) | P20: =COUNT(E20:L20) | Q20: =IF(COUNT(J20:L20)=0,"",MIN(J20:L20))
A21: 43071835930764 | B21: ANILLO P STARS | C21: 7 | D21: copper | I21: 1.7 | M21: =IF(COUNT(E21:L21)=0,"",MIN(E21:L21)) | N21: =IF(COUNT(E21:L21)=0,"",LOOKUP(2,1/(E21:L21<>""),E21:L21)) | O21: =IF(M21="","",ROUND(M21*RESUMEN!$B$4,0)) | P21: =COUNT(E21:L21) | Q21: =IF(COUNT(J21:L21)=0,"",MIN(J21:L21))
A22: 43071835963532 | B22: ANILLO P STARS | C22: 8 | D22: copper | H22: 1.7 | K22: 1.7 | M22: =IF(COUNT(E22:L22)=0,"",MIN(E22:L22)) | N22: =IF(COUNT(E22:L22)=0,"",LOOKUP(2,1/(E22:L22<>""),E22:L22)) | O22: =IF(M22="","",ROUND(M22*RESUMEN!$B$4,0)) | P22: =COUNT(E22:L22) | Q22: =IF(COUNT(J22:L22)=0,"",MIN(J22:L22))
A23: 81836202265453 | B23: ANILLO P STARS | C23: 9 | D23: copper | K23: 1.7 | M23: =IF(COUNT(E23:L23)=0,"",MIN(E23:L23)) | N23: =IF(COUNT(E23:L23)=0,"",LOOKUP(2,1/(E23:L23<>""),E23:L23)) | O23: =IF(M23="","",ROUND(M23*RESUMEN!$B$4,0)) | P23: =COUNT(E23:L23) | Q23: =IF(COUNT(J23:L23)=0,"",MIN(J23:L23))
A24: 43728071296588 | B24: ANILLO SERPENTI LISO GOLD | C24: XGN gold | D24: copper | F24: 6.9 | J24: 6.8 | L24: 6.9 | M24: =IF(COUNT(E24:L24)=0,"",MIN(E24:L24)) | N24: =IF(COUNT(E24:L24)=0,"",LOOKUP(2,1/(E24:L24<>""),E24:L24)) | O24: =IF(M24="","",ROUND(M24*RESUMEN!$B$4,0)) | P24: =COUNT(E24:L24) | Q24: =IF(COUNT(J24:L24)=0,"",MIN(J24:L24))
A25: 43728071182284 | B25: ANILLO SERPENTI LISO SILVER | C25: AJUSTABLE | D25: copper | I25: 6.8 | J25: 6.8 | K25: 6.8 | M25: =IF(COUNT(E25:L25)=0,"",MIN(E25:L25)) | N25: =IF(COUNT(E25:L25)=0,"",LOOKUP(2,1/(E25:L25<>""),E25:L25)) | O25: =IF(M25="","",ROUND(M25*RESUMEN!$B$4,0)) | P25: =COUNT(E25:L25) | Q25: =IF(COUNT(J25:L25)=0,"",MIN(J25:L25))
A26: 38332091054029 | B26: ANILLO T EDGE SILVER | C26: 6 | D26: copper,zircon | G26: 10.8 | K26: 10.8 | M26: =IF(COUNT(E26:L26)=0,"",MIN(E26:L26)) | N26: =IF(COUNT(E26:L26)=0,"",LOOKUP(2,1/(E26:L26<>""),E26:L26)) | O26: =IF(M26="","",ROUND(M26*RESUMEN!$B$4,0)) | P26: =COUNT(E26:L26) | Q26: =IF(COUNT(J26:L26)=0,"",MIN(J26:L26))
A27: 38332091186797 | B27: ANILLO T EDGE SILVER | C27: XGX249-004 7# | D27: copper,zircon | F27: 10.8 | G27: 10.8 | J27: 10.8 | L27: 10.8 | M27: =IF(COUNT(E27:L27)=0,"",MIN(E27:L27)) | N27: =IF(COUNT(E27:L27)=0,"",LOOKUP(2,1/(E27:L27<>""),E27:L27)) | O27: =IF(M27="","",ROUND(M27*RESUMEN!$B$4,0)) | P27: =COUNT(E27:L27) | Q27: =IF(COUNT(J27:L27)=0,"",MIN(J27:L27))
A28: 34876761335341 | B28: ANILLO T LOVESTRUCK SILVER-ROSE GOLD | C28: 6 | D28: copper | F28: 8.8 | G28: 8.8 | I28: 8.8 | J28: 8.8 | M28: =IF(COUNT(E28:L28)=0,"",MIN(E28:L28)) | N28: =IF(COUNT(E28:L28)=0,"",LOOKUP(2,1/(E28:L28<>""),E28:L28)) | O28: =IF(M28="","",ROUND(M28*RESUMEN!$B$4,0)) | P28: =COUNT(E28:L28) | Q28: =IF(COUNT(J28:L28)=0,"",MIN(J28:L28))
A29: 34876761468109 | B29: ANILLO T LOVESTRUCK SILVER-ROSE GOLD | C29: 7 | D29: copper | G29: 8.8 | J29: 8.8 | M29: =IF(COUNT(E29:L29)=0,"",MIN(E29:L29)) | N29: =IF(COUNT(E29:L29)=0,"",LOOKUP(2,1/(E29:L29<>""),E29:L29)) | O29: =IF(M29="","",ROUND(M29*RESUMEN!$B$4,0)) | P29: =COUNT(E29:L29) | Q29: =IF(COUNT(J29:L29)=0,"",MIN(J29:L29))
A30: 41648081090125 | B30: ANILLO T LOVESTRUCK SILVER-ROSE GOLD | C30: 8 | J30: 8.8 | M30: =IF(COUNT(E30:L30)=0,"",MIN(E30:L30)) | N30: =IF(COUNT(E30:L30)=0,"",LOOKUP(2,1/(E30:L30<>""),E30:L30)) | O30: =IF(M30="","",ROUND(M30*RESUMEN!$B$4,0)) | P30: =COUNT(E30:L30) | Q30: =IF(COUNT(J30:L30)=0,"",MIN(J30:L30))
A31: 41889241279949 | B31: ANILLO T V SILVER | C31: 7 | D31: copper | F31: 9.8 | I31: 9.8 | M31: =IF(COUNT(E31:L31)=0,"",MIN(E31:L31)) | N31: =IF(COUNT(E31:L31)=0,"",LOOKUP(2,1/(E31:L31<>""),E31:L31)) | O31: =IF(M31="","",ROUND(M31*RESUMEN!$B$4,0)) | P31: =COUNT(E31:L31) | Q31: =IF(COUNT(J31:L31)=0,"",MIN(J31:L31))
A32: 41889241312717 | B32: ANILLO T V SILVER | C32: 8 | D32: copper,zircon | F32: 9.8 | I32: 9.8 | M32: =IF(COUNT(E32:L32)=0,"",MIN(E32:L32)) | N32: =IF(COUNT(E32:L32)=0,"",LOOKUP(2,1/(E32:L32<>""),E32:L32)) | O32: =IF(M32="","",ROUND(M32*RESUMEN!$B$4,0)) | P32: =COUNT(E32:L32) | Q32: =IF(COUNT(J32:L32)=0,"",MIN(J32:L32))
A33: 41889241445485 | B33: ANILLO T V SILVER | C33: 9 | D33: copper,zircon | F33: 9.8 | I33: 9.8 | M33: =IF(COUNT(E33:L33)=0,"",MIN(E33:L33)) | N33: =IF(COUNT(E33:L33)=0,"",LOOKUP(2,1/(E33:L33<>""),E33:L33)) | O33: =IF(M33="","",ROUND(M33*RESUMEN!$B$4,0)) | P33: =COUNT(E33:L33) | Q33: =IF(COUNT(J33:L33)=0,"",MIN(J33:L33))
A34: 665bb4c20b268 | B34: ANILLO V GOLD | C34: AJUSTABLE | D34: copper | K34: 6.8 | M34: =IF(COUNT(E34:L34)=0,"",MIN(E34:L34)) | N34: =IF(COUNT(E34:L34)=0,"",LOOKUP(2,1/(E34:L34<>""),E34:L34)) | O34: =IF(M34="","",ROUND(M34*RESUMEN!$B$4,0)) | P34: =COUNT(E34:L34) | Q34: =IF(COUNT(J34:L34)=0,"",MIN(J34:L34))
A35: 15711172030349 | B35: ARETES BEAN GOLD T | C35: Default Title | D35: copper | E35: 8 | F35: 8 | H35: 7.5 | I35: 8 | K35: 8.8 | M35: =IF(COUNT(E35:L35)=0,"",MIN(E35:L35)) | N35: =IF(COUNT(E35:L35)=0,"",LOOKUP(2,1/(E35:L35<>""),E35:L35)) | O35: =IF(M35="","",ROUND(M35*RESUMEN!$B$4,0)) | P35: =COUNT(E35:L35) | Q35: =IF(COUNT(J35:L35)=0,"",MIN(J35:L35))
A36: 62101481140653 | B36: ARETES BEAN SILVER T | C36: Default Title | D36: copper | E36: 8 | F36: 8 | H36: 7.5 | J36: 8 | K36: 8 | M36: =IF(COUNT(E36:L36)=0,"",MIN(E36:L36)) | N36: =IF(COUNT(E36:L36)=0,"",LOOKUP(2,1/(E36:L36<>""),E36:L36)) | O36: =IF(M36="","",ROUND(M36*RESUMEN!$B$4,0)) | P36: =COUNT(E36:L36) | Q36: =IF(COUNT(J36:L36)=0,"",MIN(J36:L36))
A37: 64e78d3bae5c1 | B37: ARETES BLOSSOM STAR GOLD | D37: copper | E37: 6.8 | G37: 6.8 | M37: =IF(COUNT(E37:L37)=0,"",MIN(E37:L37)) | N37: =IF(COUNT(E37:L37)=0,"",LOOKUP(2,1/(E37:L37<>""),E37:L37)) | O37: =IF(M37="","",ROUND(M37*RESUMEN!$B$4,0)) | P37: =COUNT(E37:L37) | Q37: =IF(COUNT(J37:L37)=0,"",MIN(J37:L37))
A38: 94792221051565 | B38: ARETES BLOSSOM STAR GOLD | C38: REGULAR | D38: copper | H38: 6.8 | K38: 6.8 | L38: 6.8 | M38: =IF(COUNT(E38:L38)=0,"",MIN(E38:L38)) | N38: =IF(COUNT(E38:L38)=0,"",LOOKUP(2,1/(E38:L38<>""),E38:L38)) | O38: =IF(M38="","",ROUND(M38*RESUMEN!$B$4,0)) | P38: =COUNT(E38:L38) | Q38: =IF(COUNT(J38:L38)=0,"",MIN(J38:L38))
A39: 64e78d3baafe7 | B39: ARETES BLOSSOM STAR ROSE GOLD | C39: white flower ros | D39: copper | E39: 6.8 | G39: 6.8 | H39: 6.8 | J39: 6.8 | L39: 6.8 | M39: =IF(COUNT(E39:L39)=0,"",MIN(E39:L39)) | N39: =IF(COUNT(E39:L39)=0,"",LOOKUP(2,1/(E39:L39<>""),E39:L39)) | O39: =IF(M39="","",ROUND(M39*RESUMEN!$B$4,0)) | P39: =COUNT(E39:L39) | Q39: =IF(COUNT(J39:L39)=0,"",MIN(J39:L39))
A40: 64e78d3c1c538 | B40: ARETES BLOSSOM STAR SILVER | C40: Default Title | D40: copper | E40: 6.8 | G40: 6.8 | I40: 6.8 | J40: 6.8 | M40: =IF(COUNT(E40:L40)=0,"",MIN(E40:L40)) | N40: =IF(COUNT(E40:L40)=0,"",LOOKUP(2,1/(E40:L40<>""),E40:L40)) | O40: =IF(M40="","",ROUND(M40*RESUMEN!$B$4,0)) | P40: =COUNT(E40:L40) | Q40: =IF(COUNT(J40:L40)=0,"",MIN(J40:L40))
A41: 665bb4e06b7c8 | B41: ARETES CC DORADO | C41: Regular | D41: stainless steel | E41: 2 | F41: 2 | H41: 2 | K41: 2 | M41: =IF(COUNT(E41:L41)=0,"",MIN(E41:L41)) | N41: =IF(COUNT(E41:L41)=0,"",LOOKUP(2,1/(E41:L41<>""),E41:L41)) | O41: =IF(M41="","",ROUND(M41*RESUMEN!$B$4,0)) | P41: =COUNT(E41:L41) | Q41: =IF(COUNT(J41:L41)=0,"",MIN(J41:L41))
A42: 63ebd72976d60 | B42: ARETES CC ROSE GOLD | C42: XGK 1.2cm rose g | D42: stainless steel | E42: 2 | G42: 2 | I42: 2 | K42: 2 | L42: 2 | M42: =IF(COUNT(E42:L42)=0,"",MIN(E42:L42)) | N42: =IF(COUNT(E42:L42)=0,"",LOOKUP(2,1/(E42:L42<>""),E42:L42)) | O42: =IF(M42="","",ROUND(M42*RESUMEN!$B$4,0)) | P42: =COUNT(E42:L42) | Q42: =IF(COUNT(J42:L42)=0,"",MIN(J42:L42))
A43: 63e0bb0816c62 | B43: ARETES CC SILVER | C43: Default Title | D43: copper | I43: 2 | K43: 2 | L43: 2 | M43: =IF(COUNT(E43:L43)=0,"",MIN(E43:L43)) | N43: =IF(COUNT(E43:L43)=0,"",LOOKUP(2,1/(E43:L43<>""),E43:L43)) | O43: =IF(M43="","",ROUND(M43*RESUMEN!$B$4,0)) | P43: =COUNT(E43:L43) | Q43: =IF(COUNT(J43:L43)=0,"",MIN(J43:L43))
A44: 8275727247244 | B44: ARETES CD COLGANTES | C44: Default Title | D44: copper,zircon | F44: 8.8 | H44: 8.8 | I44: 8.8 | K44: 8.8 | M44: =IF(COUNT(E44:L44)=0,"",MIN(E44:L44)) | N44: =IF(COUNT(E44:L44)=0,"",LOOKUP(2,1/(E44:L44<>""),E44:L44)) | O44: =IF(M44="","",ROUND(M44*RESUMEN!$B$4,0)) | P44: =COUNT(E44:L44) | Q44: =IF(COUNT(J44:L44)=0,"",MIN(J44:L44))
A45: 64e78e725d8db | B45: ARETES CD CON PERLA GOLD DR | C45: XGJSA306 gold | D45: copper | E45: 6.08 | G45: 6.08 | I45: 6.08 | K45: 6.08 | L45: 6.08 | M45: =IF(COUNT(E45:L45)=0,"",MIN(E45:L45)) | N45: =IF(COUNT(E45:L45)=0,"",LOOKUP(2,1/(E45:L45<>""),E45:L45)) | O45: =IF(M45="","",ROUND(M45*RESUMEN!$B$4,0)) | P45: =COUNT(E45:L45) | Q45: =IF(COUNT(J45:L45)=0,"",MIN(J45:L45))
A46: 665bb4e678422 | B46: ARETES CD GOLD | C46: XGYY gold | D46: copper | E46: 7 | G46: 7 | I46: 7 | K46: 7 | L46: 7 | M46: =IF(COUNT(E46:L46)=0,"",MIN(E46:L46)) | N46: =IF(COUNT(E46:L46)=0,"",LOOKUP(2,1/(E46:L46<>""),E46:L46)) | O46: =IF(M46="","",ROUND(M46*RESUMEN!$B$4,0)) | P46: =COUNT(E46:L46) | Q46: =IF(COUNT(J46:L46)=0,"",MIN(J46:L46))
A47: 665bd4aee8cb5 | B47: ARETES CD PERLAS/ ZIRCONIAS | C47: Default Title | D47: copper,Imitation p | F47: 8.8 | G47: 8.8 | K47: 8.8 | M47: =IF(COUNT(E47:L47)=0,"",MIN(E47:L47)) | N47: =IF(COUNT(E47:L47)=0,"",LOOKUP(2,1/(E47:L47<>""),E47:L47)) | O47: =IF(M47="","",ROUND(M47*RESUMEN!$B$4,0)) | P47: =COUNT(E47:L47) | Q47: =IF(COUNT(J47:L47)=0,"",MIN(J47:L47))
A48: 15711172330573 | B48: ARETES CD PETIT JOLIE GOLD | C48: Default Title | D48: copper,zircon | F48: 5.5 | G48: 6 | H48: 6 | J48: 6.8 | M48: =IF(COUNT(E48:L48)=0,"",MIN(E48:L48)) | N48: =IF(COUNT(E48:L48)=0,"",LOOKUP(2,1/(E48:L48<>""),E48:L48)) | O48: =IF(M48="","",ROUND(M48*RESUMEN!$B$4,0)) | P48: =COUNT(E48:L48) | Q48: =IF(COUNT(J48:L48)=0,"",MIN(J48:L48))
A49: 89633861063789 | B49: ARETES CD ROUND LOGO CON ZIRCONIAS | C49: HIGH QUALITY | D49: copper,zircon | F49: 7 | G49: 7 | M49: =IF(COUNT(E49:L49)=0,"",MIN(E49:L49)) | N49: =IF(COUNT(E49:L49)=0,"",LOOKUP(2,1/(E49:L49<>""),E49:L49)) | O49: =IF(M49="","",ROUND(M49*RESUMEN!$B$4,0)) | P49: =COUNT(E49:L49) | Q49: =IF(COUNT(J49:L49)=0,"",MIN(J49:L49))
A50: 15711172277517 | B50: ARETES CD SADDLE GOLD | C50: 3 cm | F50: 7 | M50: =IF(COUNT(E50:L50)=0,"",MIN(E50:L50)) | N50: =IF(COUNT(E50:L50)=0,"",LOOKUP(2,1/(E50:L50<>""),E50:L50)) | O50: =IF(M50="","",ROUND(M50*RESUMEN!$B$4,0)) | P50: =COUNT(E50:L50) | Q50: =IF(COUNT(J50:L50)=0,"",MIN(J50:L50))
A51: 677c26b6bfd93 | B51: ARETES CD SILVER | C51: silver | D51: copper | E51: 6.8 | I51: 7 | K51: 7 | L51: 6.8 | M51: =IF(COUNT(E51:L51)=0,"",MIN(E51:L51)) | N51: =IF(COUNT(E51:L51)=0,"",LOOKUP(2,1/(E51:L51<>""),E51:L51)) | O51: =IF(M51="","",ROUND(M51*RESUMEN!$B$4,0)) | P51: =COUNT(E51:L51) | Q51: =IF(COUNT(J51:L51)=0,"",MIN(J51:L51))
A52: 17235661006529 | B52: ARETES CD TRIBALES | C52: Default Title | D52: copper,Imitation p | G52: 8.8 | H52: 8.8 | K52: 8.8 | L52: 8.8 | M52: =IF(COUNT(E52:L52)=0,"",MIN(E52:L52)) | N52: =IF(COUNT(E52:L52)=0,"",LOOKUP(2,1/(E52:L52<>""),E52:L52)) | O52: =IF(M52="","",ROUND(M52*RESUMEN!$B$4,0)) | P52: =COUNT(E52:L52) | Q52: =IF(COUNT(J52:L52)=0,"",MIN(J52:L52))
A53: 66178b9555250 | B53: ARETES CLASH ROSEGOLD ZIRCONIA | C53: Default Title | E53: 5.3 | K53: 5.3 | M53: =IF(COUNT(E53:L53)=0,"",MIN(E53:L53)) | N53: =IF(COUNT(E53:L53)=0,"",LOOKUP(2,1/(E53:L53<>""),E53:L53)) | O53: =IF(M53="","",ROUND(M53*RESUMEN!$B$4,0)) | P53: =COUNT(E53:L53) | Q53: =IF(COUNT(J53:L53)=0,"",MIN(J53:L53))
A54: 43047217758348 | B54: ARETES CORAZÓN GRABADO GOLD | C54: XGX101847 gold | D54: stainless steel | E54: 5.88 | F54: 5.88 | H54: 5.4 | I54: 5.88 | J54: 5.88 | K54: 5.88 | L54: 5.4 | M54: =IF(COUNT(E54:L54)=0,"",MIN(E54:L54)) | N54: =IF(COUNT(E54:L54)=0,"",LOOKUP(2,1/(E54:L54<>""),E54:L54)) | O54: =IF(M54="","",ROUND(M54*RESUMEN!$B$4,0)) | P54: =COUNT(E54:L54) | Q54: =IF(COUNT(J54:L54)=0,"",MIN(J54:L54))
A55: 43047204716684 | B55: ARETES CORAZÓN GRABADO ROSEGOLD | C55: Default Title | D55: stainless steel | E55: 5.88 | H55: 5.4 | M55: =IF(COUNT(E55:L55)=0,"",MIN(E55:L55)) | N55: =IF(COUNT(E55:L55)=0,"",LOOKUP(2,1/(E55:L55<>""),E55:L55)) | O55: =IF(M55="","",ROUND(M55*RESUMEN!$B$4,0)) | P55: =COUNT(E55:L55) | Q55: =IF(COUNT(J55:L55)=0,"",MIN(J55:L55))
A56: 43047196360844 | B56: ARETES CORAZÓN GRABADO SILVER | C56: Default Title | D56: stainless steel | E56: 5.88 | F56: 5.88 | G56: 5.88 | H56: 5.4 | I56: 5.88 | K56: 5.88 | L56: 5.4 | M56: =IF(COUNT(E56:L56)=0,"",MIN(E56:L56)) | N56: =IF(COUNT(E56:L56)=0,"",LOOKUP(2,1/(E56:L56<>""),E56:L56)) | O56: =IF(M56="","",ROUND(M56*RESUMEN!$B$4,0)) | P56: =COUNT(E56:L56) | Q56: =IF(COUNT(J56:L56)=0,"",MIN(J56:L56))
A57: 43047211597964 | B57: ARETES CORAZÓN PLACA GRABADO GOLD | C57: Regular | D57: stainless steel | E57: 7 | K57: 7 | M57: =IF(COUNT(E57:L57)=0,"",MIN(E57:L57)) | N57: =IF(COUNT(E57:L57)=0,"",LOOKUP(2,1/(E57:L57<>""),E57:L57)) | O57: =IF(M57="","",ROUND(M57*RESUMEN!$B$4,0)) | P57: =COUNT(E57:L57) | Q57: =IF(COUNT(J57:L57)=0,"",MIN(J57:L57))
A58: 38332091970605 | B58: ARETES DG CON PERLA GOLD | C58: Default Title | D58: copper | G58: 8.8 | K58: 8.8 | M58: =IF(COUNT(E58:L58)=0,"",MIN(E58:L58)) | N58: =IF(COUNT(E58:L58)=0,"",LOOKUP(2,1/(E58:L58<>""),E58:L58)) | O58: =IF(M58="","",ROUND(M58*RESUMEN!$B$4,0)) | P58: =COUNT(E58:L58) | Q58: =IF(COUNT(J58:L58)=0,"",MIN(J58:L58))
A59: 15711172175405 | B59: ARETES DIORIVIERA GOLD CD | C59: Default Title | D59: copper,Imitation p | F59: 10 | H59: 10 | L59: 10 | M59: =IF(COUNT(E59:L59)=0,"",MIN(E59:L59)) | N59: =IF(COUNT(E59:L59)=0,"",LOOKUP(2,1/(E59:L59<>""),E59:L59)) | O59: =IF(M59="","",ROUND(M59*RESUMEN!$B$4,0)) | P59: =COUNT(E59:L59) | Q59: =IF(COUNT(J59:L59)=0,"",MIN(J59:L59))
A60: 43071800901772 | B60: ARETES F GOLD BLACK | C60: Regular | D60: copper | G60: 8.8 | K60: 8.8 | M60: =IF(COUNT(E60:L60)=0,"",MIN(E60:L60)) | N60: =IF(COUNT(E60:L60)=0,"",LOOKUP(2,1/(E60:L60<>""),E60:L60)) | O60: =IF(M60="","",ROUND(M60*RESUMEN!$B$4,0)) | P60: =COUNT(E60:L60) | Q60: =IF(COUNT(J60:L60)=0,"",MIN(J60:L60))
A61: 38332091513773 | B61: ARETES LOGO CC GOLD CON ZIRCONIAS | C61: gold | D61: copper,zircon | F61: 3.78 | G61: 3.78 | J61: 3.78 | L61: 3.78 | M61: =IF(COUNT(E61:L61)=0,"",MIN(E61:L61)) | N61: =IF(COUNT(E61:L61)=0,"",LOOKUP(2,1/(E61:L61<>""),E61:L61)) | O61: =IF(M61="","",ROUND(M61*RESUMEN!$B$4,0)) | P61: =COUNT(E61:L61) | Q61: =IF(COUNT(J61:L61)=0,"",MIN(J61:L61))
A62: 665bb51b8f87b-1 | B62: ARETES LOVE DORADOS | C62: Regular | D62: stainless steel | E62: 2.6 | G62: 2.6 | K62: 2.6 | L62: 2.6 | M62: =IF(COUNT(E62:L62)=0,"",MIN(E62:L62)) | N62: =IF(COUNT(E62:L62)=0,"",LOOKUP(2,1/(E62:L62<>""),E62:L62)) | O62: =IF(M62="","",ROUND(M62*RESUMEN!$B$4,0)) | P62: =COUNT(E62:L62) | Q62: =IF(COUNT(J62:L62)=0,"",MIN(J62:L62))
A63: 6617867e8acd0 | B63: ARETES LOVE GOLD CON ZIRCONIA | C63: Default Title | D63: stainless steel | E63: 2.6 | G63: 2.6 | J63: 2.6 | M63: =IF(COUNT(E63:L63)=0,"",MIN(E63:L63)) | N63: =IF(COUNT(E63:L63)=0,"",LOOKUP(2,1/(E63:L63<>""),E63:L63)) | O63: =IF(M63="","",ROUND(M63*RESUMEN!$B$4,0)) | P63: =COUNT(E63:L63) | Q63: =IF(COUNT(J63:L63)=0,"",MIN(J63:L63))
A64: 665bb51ee66d3 | B64: ARETES LOVE ROSE GOLD | C64: Default Title | E64: 2.6 | M64: =IF(COUNT(E64:L64)=0,"",MIN(E64:L64)) | N64: =IF(COUNT(E64:L64)=0,"",LOOKUP(2,1/(E64:L64<>""),E64:L64)) | O64: =IF(M64="","",ROUND(M64*RESUMEN!$B$4,0)) | P64: =COUNT(E64:L64) | Q64: =IF(COUNT(J64:L64)=0,"",MIN(J64:L64))
A65: 6617867767475 | B65: ARETES LOVE ROSEGOLD CON ZIRCONIA | C65: Regular | E65: 2.6 | M65: =IF(COUNT(E65:L65)=0,"",MIN(E65:L65)) | N65: =IF(COUNT(E65:L65)=0,"",LOOKUP(2,1/(E65:L65<>""),E65:L65)) | O65: =IF(M65="","",ROUND(M65*RESUMEN!$B$4,0)) | P65: =COUNT(E65:L65) | Q65: =IF(COUNT(J65:L65)=0,"",MIN(J65:L65))
A66: 661786775a1bb | B66: ARETES LOVE SILVER | C66: XGYL0002-without | D66: stainless steel | F66: 2.6 | J66: 2.6 | L66: 2.6 | M66: =IF(COUNT(E66:L66)=0,"",MIN(E66:L66)) | N66: =IF(COUNT(E66:L66)=0,"",LOOKUP(2,1/(E66:L66<>""),E66:L66)) | O66: =IF(M66="","",ROUND(M66*RESUMEN!$B$4,0)) | P66: =COUNT(E66:L66) | Q66: =IF(COUNT(J66:L66)=0,"",MIN(J66:L66))
A67: 6617867765c65 | B67: ARETES LOVE SILVER CON ZIRCONIA | C67: Default Title | D67: stainless steel,zi | F67: 2.6 | J67: 2.6 | M67: =IF(COUNT(E67:L67)=0,"",MIN(E67:L67)) | N67: =IF(COUNT(E67:L67)=0,"",LOOKUP(2,1/(E67:L67<>""),E67:L67)) | O67: =IF(M67="","",ROUND(M67*RESUMEN!$B$4,0)) | P67: =COUNT(E67:L67) | Q67: =IF(COUNT(J67:L67)=0,"",MIN(J67:L67))
A68: 43071645614220 | B68: ARETES LV CON ZIRCONIA | C68: Default Title | D68: copper | E68: 8.8 | G68: 8.8 | K68: 8.8 | M68: =IF(COUNT(E68:L68)=0,"",MIN(E68:L68)) | N68: =IF(COUNT(E68:L68)=0,"",LOOKUP(2,1/(E68:L68<>""),E68:L68)) | O68: =IF(M68="","",ROUND(M68*RESUMEN!$B$4,0)) | P68: =COUNT(E68:L68) | Q68: =IF(COUNT(J68:L68)=0,"",MIN(J68:L68))
A69: 63e0bd172995f-1 | B69: ARETES LV GOLD | C69: XGJSA767 gold | D69: stainless steel | E69: 5.18 | G69: 5.18 | H69: 5.18 | I69: 5.18 | L69: 5.18 | M69: =IF(COUNT(E69:L69)=0,"",MIN(E69:L69)) | N69: =IF(COUNT(E69:L69)=0,"",LOOKUP(2,1/(E69:L69<>""),E69:L69)) | O69: =IF(M69="","",ROUND(M69*RESUMEN!$B$4,0)) | P69: =COUNT(E69:L69) | Q69: =IF(COUNT(J69:L69)=0,"",MIN(J69:L69))
A70: 64e78e740ecaf-1 | B70: ARETES LV LOGO GOLD | C70: XGXKY gold | D70: copper | E70: 6 | F70: 6 | I70: 6.8 | J70: 6.8 | K70: 6.8 | L70: 6 | M70: =IF(COUNT(E70:L70)=0,"",MIN(E70:L70)) | N70: =IF(COUNT(E70:L70)=0,"",LOOKUP(2,1/(E70:L70<>""),E70:L70)) | O70: =IF(M70="","",ROUND(M70*RESUMEN!$B$4,0)) | P70: =COUNT(E70:L70) | Q70: =IF(COUNT(J70:L70)=0,"",MIN(J70:L70))
A71: 43728113631628 | B71: ARETES LV LOGO ROUND GOLD | C71: Regular | D71: stainless steel | I71: 3.8 | J71: 3.8 | M71: =IF(COUNT(E71:L71)=0,"",MIN(E71:L71)) | N71: =IF(COUNT(E71:L71)=0,"",LOOKUP(2,1/(E71:L71<>""),E71:L71)) | O71: =IF(M71="","",ROUND(M71*RESUMEN!$B$4,0)) | P71: =COUNT(E71:L71) | Q71: =IF(COUNT(J71:L71)=0,"",MIN(J71:L71))
A72: 654bdb81039f7 | B72: ARETES LV LOGO SILVER | C72: Stainless steel | D72: copper | E72: 6 | K72: 6.8 | M72: =IF(COUNT(E72:L72)=0,"",MIN(E72:L72)) | N72: =IF(COUNT(E72:L72)=0,"",LOOKUP(2,1/(E72:L72<>""),E72:L72)) | O72: =IF(M72="","",ROUND(M72*RESUMEN!$B$4,0)) | P72: =COUNT(E72:L72) | Q72: =IF(COUNT(J72:L72)=0,"",MIN(J72:L72))
A73: 43071661277324 | B73: ARETES LV ROUND CON ZIRCONIA | C73: Default Title | D73: copper,zircon | F73: 8.8 | J73: 8.8 | M73: =IF(COUNT(E73:L73)=0,"",MIN(E73:L73)) | N73: =IF(COUNT(E73:L73)=0,"",LOOKUP(2,1/(E73:L73<>""),E73:L73)) | O73: =IF(M73="","",ROUND(M73*RESUMEN!$B$4,0)) | P73: =COUNT(E73:L73) | Q73: =IF(COUNT(J73:L73)=0,"",MIN(J73:L73))
A74: 63e0bd1a27e4e | B74: ARETES LV SILVER | C74: Default Title | D74: stainless steel | H74: 5.18 | M74: =IF(COUNT(E74:L74)=0,"",MIN(E74:L74)) | N74: =IF(COUNT(E74:L74)=0,"",LOOKUP(2,1/(E74:L74<>""),E74:L74)) | O74: =IF(M74="","",ROUND(M74*RESUMEN!$B$4,0)) | P74: =COUNT(E74:L74) | Q74: =IF(COUNT(J74:L74)=0,"",MIN(J74:L74))
A75: 38332091841901 | B75: ARETES LW ANAGRAM GOLD | C75: XGZG1689 gold | D75: stainless steel | F75: 3.5 | G75: 3.5 | I75: 4 | K75: 4 | L75: 3.5 | M75: =IF(COUNT(E75:L75)=0,"",MIN(E75:L75)) | N75: =IF(COUNT(E75:L75)=0,"",LOOKUP(2,1/(E75:L75<>""),E75:L75)) | O75: =IF(M75="","",ROUND(M75*RESUMEN!$B$4,0)) | P75: =COUNT(E75:L75) | Q75: =IF(COUNT(J75:L75)=0,"",MIN(J75:L75))
A76: 665bd4b01f958 | B76: ARETES PR SILVER | C76: Default Title | D76: copper | I76: 6.8 | K76: 6.8 | M76: =IF(COUNT(E76:L76)=0,"",MIN(E76:L76)) | N76: =IF(COUNT(E76:L76)=0,"",LOOKUP(2,1/(E76:L76<>""),E76:L76)) | O76: =IF(M76="","",ROUND(M76*RESUMEN!$B$4,0)) | P76: =COUNT(E76:L76) | Q76: =IF(COUNT(J76:L76)=0,"",MIN(J76:L76))
A77: 43047214612620 | B77: ARETES SIXTEEN STONE | C77: Default Title | D77: copper | E77: 12.8 | G77: 12.8 | H77: 12.8 | J77: 12.8 | M77: =IF(COUNT(E77:L77)=0,"",MIN(E77:L77)) | N77: =IF(COUNT(E77:L77)=0,"",LOOKUP(2,1/(E77:L77<>""),E77:L77)) | O77: =IF(M77="","",ROUND(M77*RESUMEN!$B$4,0)) | P77: =COUNT(E77:L77) | Q77: =IF(COUNT(J77:L77)=0,"",MIN(J77:L77))
A78: 34876761251373 | B78: ARETES T SQUARE SIXTEEN STONE | C78: XGNT6-004 | D78: copper,zircon | F78: 7 | G78: 7 | H78: 7 | J78: 7 | K78: 7 | L78: 7 | M78: =IF(COUNT(E78:L78)=0,"",MIN(E78:L78)) | N78: =IF(COUNT(E78:L78)=0,"",LOOKUP(2,1/(E78:L78<>""),E78:L78)) | O78: =IF(M78="","",ROUND(M78*RESUMEN!$B$4,0)) | P78: =COUNT(E78:L78) | Q78: =IF(COUNT(J78:L78)=0,"",MIN(J78:L78))
A79: 63e0bd204f826 | B79: ARETES T-SMILE GOLD | C79: XGJSA684 gold | D79: stainless steel | G79: 3.3 | I79: 3.88 | J79: 3.88 | L79: 3.3 | M79: =IF(COUNT(E79:L79)=0,"",MIN(E79:L79)) | N79: =IF(COUNT(E79:L79)=0,"",LOOKUP(2,1/(E79:L79<>""),E79:L79)) | O79: =IF(M79="","",ROUND(M79*RESUMEN!$B$4,0)) | P79: =COUNT(E79:L79) | Q79: =IF(COUNT(J79:L79)=0,"",MIN(J79:L79))
A80: 63529311036333 | B80: ARETES T-SMILE GOLD CON ZIRCONIAS | C80: Default Title | D80: copper | G80: 6.8 | H80: 6.8 | M80: =IF(COUNT(E80:L80)=0,"",MIN(E80:L80)) | N80: =IF(COUNT(E80:L80)=0,"",LOOKUP(2,1/(E80:L80<>""),E80:L80)) | O80: =IF(M80="","",ROUND(M80*RESUMEN!$B$4,0)) | P80: =COUNT(E80:L80) | Q80: =IF(COUNT(J80:L80)=0,"",MIN(J80:L80))
A81: 63e0bd2165d38 | B81: ARETES T-SMILE ROSE GOLD | C81: 1cm | D81: stainless steel | G81: 3.3 | H81: 3.88 | L81: 3.3 | M81: =IF(COUNT(E81:L81)=0,"",MIN(E81:L81)) | N81: =IF(COUNT(E81:L81)=0,"",LOOKUP(2,1/(E81:L81<>""),E81:L81)) | O81: =IF(M81="","",ROUND(M81*RESUMEN!$B$4,0)) | P81: =COUNT(E81:L81) | Q81: =IF(COUNT(J81:L81)=0,"",MIN(J81:L81))
A82: 641b376c85b37 | B82: ARETES T-SMILE ROSE GOLD CON ZIRCONIA | C82: rose gold | D82: copper | I82: 6.8 | L82: 6.8 | M82: =IF(COUNT(E82:L82)=0,"",MIN(E82:L82)) | N82: =IF(COUNT(E82:L82)=0,"",LOOKUP(2,1/(E82:L82<>""),E82:L82)) | O82: =IF(M82="","",ROUND(M82*RESUMEN!$B$4,0)) | P82: =COUNT(E82:L82) | Q82: =IF(COUNT(J82:L82)=0,"",MIN(J82:L82))
A83: 63e0bd216689b-1 | B83: ARETES T-SMILE SILVER | C83: 1.5cm | D83: stainless steel | G83: 3.3 | M83: =IF(COUNT(E83:L83)=0,"",MIN(E83:L83)) | N83: =IF(COUNT(E83:L83)=0,"",LOOKUP(2,1/(E83:L83<>""),E83:L83)) | O83: =IF(M83="","",ROUND(M83*RESUMEN!$B$4,0)) | P83: =COUNT(E83:L83) | Q83: =IF(COUNT(J83:L83)=0,"",MIN(J83:L83))
A84: 63e0bd216689b-2 | B84: ARETES T-SMILE SILVER | C84: 1cm | D84: stainless steel | E84: 3.88 | L84: 3.88 | M84: =IF(COUNT(E84:L84)=0,"",MIN(E84:L84)) | N84: =IF(COUNT(E84:L84)=0,"",LOOKUP(2,1/(E84:L84<>""),E84:L84)) | O84: =IF(M84="","",ROUND(M84*RESUMEN!$B$4,0)) | P84: =COUNT(E84:L84) | Q84: =IF(COUNT(J84:L84)=0,"",MIN(J84:L84))
A85: 63ebd921017f7 | B85: ARETES T-SMILE SILVER CON ZIRCONIA | C85: Default Title | D85: copper | E85: 6.8 | G85: 6.8 | I85: 6.8 | K85: 6.8 | M85: =IF(COUNT(E85:L85)=0,"",MIN(E85:L85)) | N85: =IF(COUNT(E85:L85)=0,"",LOOKUP(2,1/(E85:L85<>""),E85:L85)) | O85: =IF(M85="","",ROUND(M85*RESUMEN!$B$4,0)) | P85: =COUNT(E85:L85) | Q85: =IF(COUNT(J85:L85)=0,"",MIN(J85:L85))
A86: 94530225617804 | B86: ARETES TRIBALES CD | C86: Default Title | E86: 8.8 | M86: =IF(COUNT(E86:L86)=0,"",MIN(E86:L86)) | N86: =IF(COUNT(E86:L86)=0,"",LOOKUP(2,1/(E86:L86<>""),E86:L86)) | O86: =IF(M86="","",ROUND(M86*RESUMEN!$B$4,0)) | P86: =COUNT(E86:L86) | Q86: =IF(COUNT(J86:L86)=0,"",MIN(J86:L86))
A87: 677c26b82bccf | B87: ARETES TRÉBOL GOLD CON ZIRCONIA | D87: copper | E87: 8.8 | G87: 8.8 | M87: =IF(COUNT(E87:L87)=0,"",MIN(E87:L87)) | N87: =IF(COUNT(E87:L87)=0,"",LOOKUP(2,1/(E87:L87<>""),E87:L87)) | O87: =IF(M87="","",ROUND(M87*RESUMEN!$B$4,0)) | P87: =COUNT(E87:L87) | Q87: =IF(COUNT(J87:L87)=0,"",MIN(J87:L87))
A88: 678a9af11a3e6 | B88: ARETES TRÉBOL SILVER CON ZIRCONIA | C88: Default Title | D88: copper | E88: 8.8 | J88: 8.8 | M88: =IF(COUNT(E88:L88)=0,"",MIN(E88:L88)) | N88: =IF(COUNT(E88:L88)=0,"",LOOKUP(2,1/(E88:L88<>""),E88:L88)) | O88: =IF(M88="","",ROUND(M88*RESUMEN!$B$4,0)) | P88: =COUNT(E88:L88) | Q88: =IF(COUNT(J88:L88)=0,"",MIN(J88:L88))
A89: 43071749587084 | B89: ARETES V CON PERLA | C89: XGN5-026 | D89: copper | G89: 8.8 | I89: 8.8 | J89: 8.8 | L89: 8.8 | M89: =IF(COUNT(E89:L89)=0,"",MIN(E89:L89)) | N89: =IF(COUNT(E89:L89)=0,"",LOOKUP(2,1/(E89:L89<>""),E89:L89)) | O89: =IF(M89="","",ROUND(M89*RESUMEN!$B$4,0)) | P89: =COUNT(E89:L89) | Q89: =IF(COUNT(J89:L89)=0,"",MIN(J89:L89))
A90: 64e78ed3b6948 | B90: ARETES YSL | C90: Default Title | D90: copper | E90: 9.8 | F90: 9.8 | G90: 9.8 | K90: 9.8 | M90: =IF(COUNT(E90:L90)=0,"",MIN(E90:L90)) | N90: =IF(COUNT(E90:L90)=0,"",LOOKUP(2,1/(E90:L90<>""),E90:L90)) | O90: =IF(M90="","",ROUND(M90*RESUMEN!$B$4,0)) | P90: =COUNT(E90:L90) | Q90: =IF(COUNT(J90:L90)=0,"",MIN(J90:L90))
A91: 665bd4b033012 | B91: ARETES YSL SILVER | C91: XG | D91: copper | G91: 4.6 | I91: 4.6 | J91: 4.6 | L91: 4.6 | M91: =IF(COUNT(E91:L91)=0,"",MIN(E91:L91)) | N91: =IF(COUNT(E91:L91)=0,"",LOOKUP(2,1/(E91:L91<>""),E91:L91)) | O91: =IF(M91="","",ROUND(M91*RESUMEN!$B$4,0)) | P91: =COUNT(E91:L91) | Q91: =IF(COUNT(J91:L91)=0,"",MIN(J91:L91))
A92: 39252672178381 | B92: ARRACADAS BLOSSOM GOLD ZIRCONIAS | C92: Default Title | D92: copper,zircon | F92: 9.8 | I92: 9.8 | M92: =IF(COUNT(E92:L92)=0,"",MIN(E92:L92)) | N92: =IF(COUNT(E92:L92)=0,"",LOOKUP(2,1/(E92:L92<>""),E92:L92)) | O92: =IF(M92="","",ROUND(M92*RESUMEN!$B$4,0)) | P92: =COUNT(E92:L92) | Q92: =IF(COUNT(J92:L92)=0,"",MIN(J92:L92))
A93: 43728071088236 | B93: ARRACADAS BV SERPENTI | C93: Default Title | D93: copper | G93: 8.8 | I93: 8.8 | J93: 8.8 | M93: =IF(COUNT(E93:L93)=0,"",MIN(E93:L93)) | N93: =IF(COUNT(E93:L93)=0,"",LOOKUP(2,1/(E93:L93<>""),E93:L93)) | O93: =IF(M93="","",ROUND(M93*RESUMEN!$B$4,0)) | P93: =COUNT(E93:L93) | Q93: =IF(COUNT(J93:L93)=0,"",MIN(J93:L93))
A94: 41889241805933 | B94: ARRACADAS BV ZIRCONIAS ROSEGOLD | C94: Default Title | F94: 14 | M94: =IF(COUNT(E94:L94)=0,"",MIN(E94:L94)) | N94: =IF(COUNT(E94:L94)=0,"",LOOKUP(2,1/(E94:L94<>""),E94:L94)) | O94: =IF(M94="","",ROUND(M94*RESUMEN!$B$4,0)) | P94: =COUNT(E94:L94) | Q94: =IF(COUNT(J94:L94)=0,"",MIN(J94:L94))
A95: 29603521001805 | B95: ARRACADAS CD LOGO CON ZIRCONIAS | C95: XGYY210103 | D95: copper,zircon | F95: 8.8 | J95: 8.8 | L95: 8.8 | M95: =IF(COUNT(E95:L95)=0,"",MIN(E95:L95)) | N95: =IF(COUNT(E95:L95)=0,"",LOOKUP(2,1/(E95:L95<>""),E95:L95)) | O95: =IF(M95="","",ROUND(M95*RESUMEN!$B$4,0)) | P95: =COUNT(E95:L95) | Q95: =IF(COUNT(J95:L95)=0,"",MIN(J95:L95))
A96: 39252671787533 | B96: ARRACADAS F GOLD | C96: Default Title | D96: copper | F96: 9.8 | K96: 9.8 | M96: =IF(COUNT(E96:L96)=0,"",MIN(E96:L96)) | N96: =IF(COUNT(E96:L96)=0,"",LOOKUP(2,1/(E96:L96<>""),E96:L96)) | O96: =IF(M96="","",ROUND(M96*RESUMEN!$B$4,0)) | P96: =COUNT(E96:L96) | Q96: =IF(COUNT(J96:L96)=0,"",MIN(J96:L96))
A97: 43071764562060 | B97: ARRACADAS V GOLD | C97: Regular | J97: 8.8 | M97: =IF(COUNT(E97:L97)=0,"",MIN(E97:L97)) | N97: =IF(COUNT(E97:L97)=0,"",LOOKUP(2,1/(E97:L97<>""),E97:L97)) | O97: =IF(M97="","",ROUND(M97*RESUMEN!$B$4,0)) | P97: =COUNT(E97:L97) | Q97: =IF(COUNT(J97:L97)=0,"",MIN(J97:L97))
A98: 42101481043501 | B98: BOLSA CC Nº25 | C98: XGHD244869 26*19 | D98: microfiber leather | E98: 66 | F98: 66 | G98: 66 | H98: 66 | J98: 66 | L98: 66 | M98: =IF(COUNT(E98:L98)=0,"",MIN(E98:L98)) | N98: =IF(COUNT(E98:L98)=0,"",LOOKUP(2,1/(E98:L98<>""),E98:L98)) | O98: =IF(M98="","",ROUND(M98*RESUMEN!$B$4,0)) | P98: =COUNT(E98:L98) | Q98: =IF(COUNT(J98:L98)=0,"",MIN(J98:L98))
A99: 43897301164429 | B99: BOLSA CC Nº25 BABY BLUE | C99: XGH493116 26cm b | D99: Genuine leather mi | G99: 63 | I99: 65 | J99: 65 | L99: 63 | M99: =IF(COUNT(E99:L99)=0,"",MIN(E99:L99)) | N99: =IF(COUNT(E99:L99)=0,"",LOOKUP(2,1/(E99:L99<>""),E99:L99)) | O99: =IF(M99="","",ROUND(M99*RESUMEN!$B$4,0)) | P99: =COUNT(E99:L99) | Q99: =IF(COUNT(J99:L99)=0,"",MIN(J99:L99))
A100: 98269341115213 | B100: BOLSA CC Nº25 BURDEOS | C100: Default Title | D100: Genuine leather mi | F100: 66 | G100: 66 | H100: 66 | K100: 66 | M100: =IF(COUNT(E100:L100)=0,"",MIN(E100:L100)) | N100: =IF(COUNT(E100:L100)=0,"",LOOKUP(2,1/(E100:L100<>""),E100:L100)) | O100: =IF(M100="","",ROUND(M100*RESUMEN!$B$4,0)) | P100: =COUNT(E100:L100) | Q100: =IF(COUNT(J100:L100)=0,"",MIN(J100:L100))
A101: 438973010904 | B101: BOLSA CC Nº25 YELLOW | D101: Genuine leather mi | I101: 65 | M101: =IF(COUNT(E101:L101)=0,"",MIN(E101:L101)) | N101: =IF(COUNT(E101:L101)=0,"",LOOKUP(2,1/(E101:L101<>""),E101:L101)) | O101: =IF(M101="","",ROUND(M101*RESUMEN!$B$4,0)) | P101: =COUNT(E101:L101) | Q101: =IF(COUNT(J101:L101)=0,"",MIN(J101:L101))
...

Sheet NANCY VIP
A1: HISTORIAL DE PRECIOS — NANCY VIP
A2: 7 orden(es) · costo unitario en USD · MXN = MEJOR × RESUMEN!B4 · * = dato del historial previo
A4: SKU | B4: PRODUCTO | C4: VARIANTE | D4: MATERIAL | E4: Sep 2025 06/09 | F4: Dic 2025 03/12 | G4: Mar 2026 01/03 | H4: Abr 2026 01/04 | I4: May 2026 08/05 | J4: May 2026 31/05 | K4: Jul 2026 09/07 | L4: MEJOR (US) | M4: ÚLTIMA (US) | N4: MXN (mejor×TC) | O4: # ÓRD.
A5: 42981628018828 | B5: ANILLO BLOSSOM STAR ROSEGOLD | C5: Regular | E5: 4.99 | H5: 2.3 | I5: 5.59 | L5: =IF(COUNT(E5:K5)=0,"",MIN(E5:K5)) | M5: =IF(COUNT(E5:K5)=0,"",LOOKUP(2,1/(E5:K5<>""),E5:K5)) | N5: =IF(L5="","",ROUND(L5*RESUMEN!$B$4,0)) | O5: =COUNT(E5:K5)
A6: 71036863389452 | B6: ANILLO BV CON UNA ZIRCONIA GOLD | C6: 7 | D6: stainless steel | J6: 3.99 | L6: =IF(COUNT(E6:K6)=0,"",MIN(E6:K6)) | M6: =IF(COUNT(E6:K6)=0,"",LOOKUP(2,1/(E6:K6<>""),E6:K6)) | N6: =IF(L6="","",ROUND(L6*RESUMEN!$B$4,0)) | O6: =COUNT(E6:K6)
A7: 71036863422220 | B7: ANILLO BV CON UNA ZIRCONIA GOLD | C7: 8 | I7: 3.99 | L7: =IF(COUNT(E7:K7)=0,"",MIN(E7:K7)) | M7: =IF(COUNT(E7:K7)=0,"",LOOKUP(2,1/(E7:K7<>""),E7:K7)) | N7: =IF(L7="","",ROUND(L7*RESUMEN!$B$4,0)) | O7: =COUNT(E7:K7)
A8: 62745763277677 | B8: ANILLO C CLASH ONYX | C8: 6 | D8: brass | J8: 10.89 | L8: =IF(COUNT(E8:K8)=0,"",MIN(E8:K8)) | M8: =IF(COUNT(E8:K8)=0,"",LOOKUP(2,1/(E8:K8<>""),E8:K8)) | N8: =IF(L8="","",ROUND(L8*RESUMEN!$B$4,0)) | O8: =COUNT(E8:K8)
A9: 62745763310445 | B9: ANILLO C CLASH ONYX | C9: 7 | D9: brass | J9: 10.89 | L9: =IF(COUNT(E9:K9)=0,"",MIN(E9:K9)) | M9: =IF(COUNT(E9:K9)=0,"",LOOKUP(2,1/(E9:K9<>""),E9:K9)) | N9: =IF(L9="","",ROUND(L9*RESUMEN!$B$4,0)) | O9: =COUNT(E9:K9)
A10: 58980702033101 | B10: ANILLO CC CAMELIA ROSE GOLD | C10: 6 | D10: brass | J10: 10.59 | L10: =IF(COUNT(E10:K10)=0,"",MIN(E10:K10)) | M10: =IF(COUNT(E10:K10)=0,"",LOOKUP(2,1/(E10:K10<>""),E10:K10)) | N10: =IF(L10="","",ROUND(L10*RESUMEN!$B$4,0)) | O10: =COUNT(E10:K10)
A11: 58980702165869 | B11: ANILLO CC CAMELIA ROSE GOLD | C11: 7 | D11: brass | J11: 10.59 | L11: =IF(COUNT(E11:K11)=0,"",MIN(E11:K11)) | M11: =IF(COUNT(E11:K11)=0,"",LOOKUP(2,1/(E11:K11<>""),E11:K11)) | N11: =IF(L11="","",ROUND(L11*RESUMEN!$B$4,0)) | O11: =COUNT(E11:K11)
A12: 58980701834797 | B12: ANILLO CC COCO SLIM SILVER | C12: 6 | D12: brass | J12: 7.39 | L12: =IF(COUNT(E12:K12)=0,"",MIN(E12:K12)) | M12: =IF(COUNT(E12:K12)=0,"",LOOKUP(2,1/(E12:K12<>""),E12:K12)) | N12: =IF(L12="","",ROUND(L12*RESUMEN!$B$4,0)) | O12: =COUNT(E12:K12)
A13: 58980701967565 | B13: ANILLO CC COCO SLIM SILVER | C13: 7 | D13: brass | J13: 7.39 | L13: =IF(COUNT(E13:K13)=0,"",MIN(E13:K13)) | M13: =IF(COUNT(E13:K13)=0,"",LOOKUP(2,1/(E13:K13<>""),E13:K13)) | N13: =IF(L13="","",ROUND(L13*RESUMEN!$B$4,0)) | O13: =COUNT(E13:K13)
A14: 58980701641581 | B14: ANILLO CC COCO ZIRCONIA GOLD | C14: Default Title | D14: brass | J14: 6.69 | L14: =IF(COUNT(E14:K14)=0,"",MIN(E14:K14)) | M14: =IF(COUNT(E14:K14)=0,"",LOOKUP(2,1/(E14:K14<>""),E14:K14)) | N14: =IF(L14="","",ROUND(L14*RESUMEN!$B$4,0)) | O14: =COUNT(E14:K14)
A15: 58980701543277 | B15: ANILLO CC COCO ZIRCONIA ROSE GOLD | C15: Default Title | D15: brass | J15: 6.69 | L15: =IF(COUNT(E15:K15)=0,"",MIN(E15:K15)) | M15: =IF(COUNT(E15:K15)=0,"",LOOKUP(2,1/(E15:K15<>""),E15:K15)) | N15: =IF(L15="","",ROUND(L15*RESUMEN!$B$4,0)) | O15: =COUNT(E15:K15)
A16: 58980701738189 | B16: ANILLO CC COCO ZIRCONIA SILVER | C16: Default Title | D16: brass | J16: 6.69 | L16: =IF(COUNT(E16:K16)=0,"",MIN(E16:K16)) | M16: =IF(COUNT(E16:K16)=0,"",LOOKUP(2,1/(E16:K16<>""),E16:K16)) | N16: =IF(L16="","",ROUND(L16*RESUMEN!$B$4,0)) | O16: =COUNT(E16:K16)
A17: 58980702231405 | B17: ANILLO CC ETERNAL N5 | C17: 6 | D17: brass | J17: 6.69 | L17: =IF(COUNT(E17:K17)=0,"",MIN(E17:K17)) | M17: =IF(COUNT(E17:K17)=0,"",LOOKUP(2,1/(E17:K17<>""),E17:K17)) | N17: =IF(L17="","",ROUND(L17*RESUMEN!$B$4,0)) | O17: =COUNT(E17:K17)
A18: 58980702364173 | B18: ANILLO CC ETERNAL N5 | C18: 7 | D18: brass | J18: 6.69 | L18: =IF(COUNT(E18:K18)=0,"",MIN(E18:K18)) | M18: =IF(COUNT(E18:K18)=0,"",LOOKUP(2,1/(E18:K18<>""),E18:K18)) | N18: =IF(L18="","",ROUND(L18*RESUMEN!$B$4,0)) | O18: =COUNT(E18:K18)
A19: 80464311068525 | B19: ANILLO CD REVOLUTION | C19: 6 | D19: brass | H19: 2.8 | J19: 4.99 | L19: =IF(COUNT(E19:K19)=0,"",MIN(E19:K19)) | M19: =IF(COUNT(E19:K19)=0,"",LOOKUP(2,1/(E19:K19<>""),E19:K19)) | N19: =IF(L19="","",ROUND(L19*RESUMEN!$B$4,0)) | O19: =COUNT(E19:K19)
A20: 42951547486348 | B20: ANILLO CD REVOLUTION | C20: 8 | E20: 3.49 | I20: 5.59 | L20: =IF(COUNT(E20:K20)=0,"",MIN(E20:K20)) | M20: =IF(COUNT(E20:K20)=0,"",LOOKUP(2,1/(E20:K20<>""),E20:K20)) | N20: =IF(L20="","",ROUND(L20*RESUMEN!$B$4,0)) | O20: =COUNT(E20:K20)
A21: 56481462558348 | B21: ANILLO ECROU SILVER | C21: 6 | D21: brass | J21: 3.29 | L21: =IF(COUNT(E21:K21)=0,"",MIN(E21:K21)) | M21: =IF(COUNT(E21:K21)=0,"",LOOKUP(2,1/(E21:K21<>""),E21:K21)) | N21: =IF(L21="","",ROUND(L21*RESUMEN!$B$4,0)) | O21: =COUNT(E21:K21)
A22: 56481462591116 | B22: ANILLO ECROU SILVER | C22: 7 | D22: brass | G22: 3.29 | H22: 3.29 | L22: =IF(COUNT(E22:K22)=0,"",MIN(E22:K22)) | M22: =IF(COUNT(E22:K22)=0,"",LOOKUP(2,1/(E22:K22<>""),E22:K22)) | N22: =IF(L22="","",ROUND(L22*RESUMEN!$B$4,0)) | O22: =COUNT(E22:K22)
A23: 56481462623884 | B23: ANILLO ECROU SILVER | C23: 8 | D23: brass | F23: 3.29 | H23: 3.29 | L23: =IF(COUNT(E23:K23)=0,"",MIN(E23:K23)) | M23: =IF(COUNT(E23:K23)=0,"",LOOKUP(2,1/(E23:K23<>""),E23:K23)) | N23: =IF(L23="","",ROUND(L23*RESUMEN!$B$4,0)) | O23: =COUNT(E23:K23)
A24: 42981601575052 | B24: ANILLO ESSENTIAL V PERLE | C24: Default Title | E24: 4.99 | K24: 5.59 | L24: =IF(COUNT(E24:K24)=0,"",MIN(E24:K24)) | M24: =IF(COUNT(E24:K24)=0,"",LOOKUP(2,1/(E24:K24<>""),E24:K24)) | N24: =IF(L24="","",ROUND(L24*RESUMEN!$B$4,0)) | O24: =COUNT(E24:K24)
A25: 66593a9c168cf | B25: ANILLO KNOT GOLD | C25: 6 | D25: brass | F25: 5.99 | G25: 5.59 | H25: 5.59 | I25: 5.59 | K25: 4.99 | L25: =IF(COUNT(E25:K25)=0,"",MIN(E25:K25)) | M25: =IF(COUNT(E25:K25)=0,"",LOOKUP(2,1/(E25:K25<>""),E25:K25)) | N25: =IF(L25="","",ROUND(L25*RESUMEN!$B$4,0)) | O25: =COUNT(E25:K25)
A26: 66593a9cc1aaa | B26: ANILLO KNOT GOLD | C26: 7 | D26: brass | F26: 0 | G26: 5.59 | H26: 5.59 | I26: 5.59 | J26: 5.59 | L26: =IF(COUNT(E26:K26)=0,"",MIN(E26:K26)) | M26: =IF(COUNT(E26:K26)=0,"",LOOKUP(2,1/(E26:K26<>""),E26:K26)) | N26: =IF(L26="","",ROUND(L26*RESUMEN!$B$4,0)) | O26: =COUNT(E26:K26)
A27: 2653027325964 | B27: ANILLO KNOT GOLD | C27: 8 | G27: 5.59 | I27: 5.59 | K27: 4.99 | L27: =IF(COUNT(E27:K27)=0,"",MIN(E27:K27)) | M27: =IF(COUNT(E27:K27)=0,"",LOOKUP(2,1/(E27:K27<>""),E27:K27)) | N27: =IF(L27="","",ROUND(L27*RESUMEN!$B$4,0)) | O27: =COUNT(E27:K27)
A28: 62745761965261 | B28: ANILLO LOVE GOLD CON MICROZIRCONIAS Y ZIRCONIAS | C28: 6 | D28: stainless steel | J28: 5.99 | L28: =IF(COUNT(E28:K28)=0,"",MIN(E28:K28)) | M28: =IF(COUNT(E28:K28)=0,"",LOOKUP(2,1/(E28:K28<>""),E28:K28)) | N28: =IF(L28="","",ROUND(L28*RESUMEN!$B$4,0)) | O28: =COUNT(E28:K28)
A29: 62745762098029 | B29: ANILLO LOVE GOLD CON MICROZIRCONIAS Y ZIRCONIAS | C29: 7 | D29: stainless steel | J29: 5.99 | L29: =IF(COUNT(E29:K29)=0,"",MIN(E29:K29)) | M29: =IF(COUNT(E29:K29)=0,"",LOOKUP(2,1/(E29:K29<>""),E29:K29)) | N29: =IF(L29="","",ROUND(L29*RESUMEN!$B$4,0)) | O29: =COUNT(E29:K29)
A30: 62745762555085 | B30: ANILLO LOVE ROSE GOLD CON MICROZIRCONIAS | C30: 6 | D30: stainless steel | J30: 5.39 | L30: =IF(COUNT(E30:K30)=0,"",MIN(E30:K30)) | M30: =IF(COUNT(E30:K30)=0,"",LOOKUP(2,1/(E30:K30<>""),E30:K30)) | N30: =IF(L30="","",ROUND(L30*RESUMEN!$B$4,0)) | O30: =COUNT(E30:K30)
A31: 62745762687853 | B31: ANILLO LOVE ROSE GOLD CON MICROZIRCONIAS | C31: 7 | D31: stainless steel | J31: 5.39 | L31: =IF(COUNT(E31:K31)=0,"",MIN(E31:K31)) | M31: =IF(COUNT(E31:K31)=0,"",LOOKUP(2,1/(E31:K31<>""),E31:K31)) | N31: =IF(L31="","",ROUND(L31*RESUMEN!$B$4,0)) | O31: =COUNT(E31:K31)
A32: 62745762125709 | B32: ANILLO LOVE ROSE GOLD CON MICROZIRCONIAS Y ZIRCONIAS | C32: 6 | D32: stainless steel | J32: 5.99 | L32: =IF(COUNT(E32:K32)=0,"",MIN(E32:K32)) | M32: =IF(COUNT(E32:K32)=0,"",LOOKUP(2,1/(E32:K32<>""),E32:K32)) | N32: =IF(L32="","",ROUND(L32*RESUMEN!$B$4,0)) | O32: =COUNT(E32:K32)
A33: 62745762258477 | B33: ANILLO LOVE ROSE GOLD CON MICROZIRCONIAS Y ZIRCONIAS | C33: 7 | D33: stainless steel | J33: 5.99 | L33: =IF(COUNT(E33:K33)=0,"",MIN(E33:K33)) | M33: =IF(COUNT(E33:K33)=0,"",LOOKUP(2,1/(E33:K33<>""),E33:K33)) | N33: =IF(L33="","",ROUND(L33*RESUMEN!$B$4,0)) | O33: =COUNT(E33:K33)
A34: 62745762329101 | B34: ANILLO LOVE SILVER CON MICROZIRCONIAS Y ZIRCONIAS | C34: 6 | D34: stainless steel | J34: 5.99 | L34: =IF(COUNT(E34:K34)=0,"",MIN(E34:K34)) | M34: =IF(COUNT(E34:K34)=0,"",LOOKUP(2,1/(E34:K34<>""),E34:K34)) | N34: =IF(L34="","",ROUND(L34*RESUMEN!$B$4,0)) | O34: =COUNT(E34:K34)
A35: 62745762461869 | B35: ANILLO LOVE SILVER CON MICROZIRCONIAS Y ZIRCONIAS | C35: 7 | D35: stainless steel | J35: 5.99 | L35: =IF(COUNT(E35:K35)=0,"",MIN(E35:K35)) | M35: =IF(COUNT(E35:K35)=0,"",LOOKUP(2,1/(E35:K35<>""),E35:K35)) | N35: =IF(L35="","",ROUND(L35*RESUMEN!$B$4,0)) | O35: =COUNT(E35:K35)
A36: 42981580832908 | B36: ANILLO LV VOLT MULTI | C36: Default Title | G36: 5.59 | L36: =IF(COUNT(E36:K36)=0,"",MIN(E36:K36)) | M36: =IF(COUNT(E36:K36)=0,"",LOOKUP(2,1/(E36:K36<>""),E36:K36)) | N36: =IF(L36="","",ROUND(L36*RESUMEN!$B$4,0)) | O36: =COUNT(E36:K36)
A37: 42981773246604 | B37: ANILLO PANTHERE GOLD | C37: Regular | D37: brass | F37: 5.59 | G37: 5.59 | J37: 5.59 | K37: 7.29 | L37: =IF(COUNT(E37:K37)=0,"",MIN(E37:K37)) | M37: =IF(COUNT(E37:K37)=0,"",LOOKUP(2,1/(E37:K37<>""),E37:K37)) | N37: =IF(L37="","",ROUND(L37*RESUMEN!$B$4,0)) | O37: =COUNT(E37:K37)
A38: 42981806637196 | B38: ANILLO PANTHERE SILVER | C38: Default Title | D38: brass | H38: 5.59 | I38: 5.59 | L38: =IF(COUNT(E38:K38)=0,"",MIN(E38:K38)) | M38: =IF(COUNT(E38:K38)=0,"",LOOKUP(2,1/(E38:K38<>""),E38:K38)) | N38: =IF(L38="","",ROUND(L38*RESUMEN!$B$4,0)) | O38: =COUNT(E38:K38)
A39: 66593bd6d7885 | B39: ANILLO PERLEE GOLD | C39: 6 | I39: 5.59 | L39: =IF(COUNT(E39:K39)=0,"",MIN(E39:K39)) | M39: =IF(COUNT(E39:K39)=0,"",LOOKUP(2,1/(E39:K39<>""),E39:K39)) | N39: =IF(L39="","",ROUND(L39*RESUMEN!$B$4,0)) | O39: =COUNT(E39:K39)
A40: 66593bd77de70 | B40: ANILLO PERLEE GOLD | C40: 7 | D40: brass | G40: 5.59 | H40: 5.59 | L40: =IF(COUNT(E40:K40)=0,"",MIN(E40:K40)) | M40: =IF(COUNT(E40:K40)=0,"",LOOKUP(2,1/(E40:K40<>""),E40:K40)) | N40: =IF(L40="","",ROUND(L40*RESUMEN!$B$4,0)) | O40: =COUNT(E40:K40)
A41: 66593be00cc70 | B41: ANILLO PERLEE ROSEGOLD | C41: 7 | F41: 5.59 | I41: 5.59 | L41: =IF(COUNT(E41:K41)=0,"",MIN(E41:K41)) | M41: =IF(COUNT(E41:K41)=0,"",LOOKUP(2,1/(E41:K41<>""),E41:K41)) | N41: =IF(L41="","",ROUND(L41*RESUMEN!$B$4,0)) | O41: =COUNT(E41:K41)
A42: 66593be0a0b51 | B42: ANILLO PERLEE ROSEGOLD | C42: 8 | F42: 5.59 | G42: 5.59 | L42: =IF(COUNT(E42:K42)=0,"",MIN(E42:K42)) | M42: =IF(COUNT(E42:K42)=0,"",LOOKUP(2,1/(E42:K42<>""),E42:K42)) | N42: =IF(L42="","",ROUND(L42*RESUMEN!$B$4,0)) | O42: =COUNT(E42:K42)
A43: 66593be14e8c5 | B43: ANILLO PERLEE SILVER | C43: 6 | D43: brass | G43: 5.59 | H43: 5.59 | L43: =IF(COUNT(E43:K43)=0,"",MIN(E43:K43)) | M43: =IF(COUNT(E43:K43)=0,"",LOOKUP(2,1/(E43:K43<>""),E43:K43)) | N43: =IF(L43="","",ROUND(L43*RESUMEN!$B$4,0)) | O43: =COUNT(E43:K43)
A44: 66593be202d61 | B44: ANILLO PERLEE SILVER | C44: 7 | F44: 5.59 | K44: 5.59 | L44: =IF(COUNT(E44:K44)=0,"",MIN(E44:K44)) | M44: =IF(COUNT(E44:K44)=0,"",LOOKUP(2,1/(E44:K44<>""),E44:K44)) | N44: =IF(L44="","",ROUND(L44*RESUMEN!$B$4,0)) | O44: =COUNT(E44:K44)
A45: 66593be29b6a6 | B45: ANILLO PERLEE SILVER | C45: 8 | G45: 5.59 | L45: =IF(COUNT(E45:K45)=0,"",MIN(E45:K45)) | M45: =IF(COUNT(E45:K45)=0,"",LOOKUP(2,1/(E45:K45<>""),E45:K45)) | N45: =IF(L45="","",ROUND(L45*RESUMEN!$B$4,0)) | O45: =COUNT(E45:K45)
A46: 50328871088397 | B46: ANILLO PERLEE SILVER | C46: 9 | K46: 5.59 | L46: =IF(COUNT(E46:K46)=0,"",MIN(E46:K46)) | M46: =IF(COUNT(E46:K46)=0,"",LOOKUP(2,1/(E46:K46<>""),E46:K46)) | N46: =IF(L46="","",ROUND(L46*RESUMEN!$B$4,0)) | O46: =COUNT(E46:K46)
A47: 71288021336845 | B47: ANILLO T SIXTEEN STONE ROSE GOLD | C47: 6 | D47: brass | J47: 6.99 | L47: =IF(COUNT(E47:K47)=0,"",MIN(E47:K47)) | M47: =IF(COUNT(E47:K47)=0,"",LOOKUP(2,1/(E47:K47<>""),E47:K47)) | N47: =IF(L47="","",ROUND(L47*RESUMEN!$B$4,0)) | O47: =COUNT(E47:K47)
A48: 71288021469613 | B48: ANILLO T SIXTEEN STONE ROSE GOLD | C48: 7 | D48: brass | J48: 6.99 | L48: =IF(COUNT(E48:K48)=0,"",MIN(E48:K48)) | M48: =IF(COUNT(E48:K48)=0,"",LOOKUP(2,1/(E48:K48<>""),E48:K48)) | N48: =IF(L48="","",ROUND(L48*RESUMEN!$B$4,0)) | O48: =COUNT(E48:K48)
A49: 97902501045901 | B49: ANILLO TB GOLD | C49: 6 | E49: 2.99 | L49: =IF(COUNT(E49:K49)=0,"",MIN(E49:K49)) | M49: =IF(COUNT(E49:K49)=0,"",LOOKUP(2,1/(E49:K49<>""),E49:K49)) | N49: =IF(L49="","",ROUND(L49*RESUMEN!$B$4,0)) | O49: =COUNT(E49:K49)
A50: 42981951111308 | B50: ANILLO TB GOLD | C50: 7 | E50: 2.99 | K50: 2.99 | L50: =IF(COUNT(E50:K50)=0,"",MIN(E50:K50)) | M50: =IF(COUNT(E50:K50)=0,"",LOOKUP(2,1/(E50:K50<>""),E50:K50)) | N50: =IF(L50="","",ROUND(L50*RESUMEN!$B$4,0)) | O50: =COUNT(E50:K50)
A51: 42981951144076 | B51: ANILLO TB GOLD | C51: 8 | E51: 2.99 | L51: =IF(COUNT(E51:K51)=0,"",MIN(E51:K51)) | M51: =IF(COUNT(E51:K51)=0,"",LOOKUP(2,1/(E51:K51<>""),E51:K51)) | N51: =IF(L51="","",ROUND(L51*RESUMEN!$B$4,0)) | O51: =COUNT(E51:K51)
A52: 42981955862668 | B52: ANILLO TB SILVER | C52: 6 | D52: stainless steel | E52: 2.99 | I52: 2.99 | L52: =IF(COUNT(E52:K52)=0,"",MIN(E52:K52)) | M52: =IF(COUNT(E52:K52)=0,"",LOOKUP(2,1/(E52:K52<>""),E52:K52)) | N52: =IF(L52="","",ROUND(L52*RESUMEN!$B$4,0)) | O52: =COUNT(E52:K52)
A53: 42981955895436 | B53: ANILLO TB SILVER | C53: 7 | D53: stainless steel | E53: 2.99 | I53: 2.99 | L53: =IF(COUNT(E53:K53)=0,"",MIN(E53:K53)) | M53: =IF(COUNT(E53:K53)=0,"",LOOKUP(2,1/(E53:K53<>""),E53:K53)) | N53: =IF(L53="","",ROUND(L53*RESUMEN!$B$4,0)) | O53: =COUNT(E53:K53)
A54: 42981955928204 | B54: ANILLO TB SILVER | C54: 8 | D54: stainless steel | E54: 2.99 | I54: 2.99 | L54: =IF(COUNT(E54:K54)=0,"",MIN(E54:K54)) | M54: =IF(COUNT(E54:K54)=0,"",LOOKUP(2,1/(E54:K54<>""),E54:K54)) | N54: =IF(L54="","",ROUND(L54*RESUMEN!$B$4,0)) | O54: =COUNT(E54:K54)
A55: 2653028882316 | B55: ANILLO TREBOL GOLD BLACK | C55: 6 | G55: 5.59 | L55: =IF(COUNT(E55:K55)=0,"",MIN(E55:K55)) | M55: =IF(COUNT(E55:K55)=0,"",LOOKUP(2,1/(E55:K55<>""),E55:K55)) | N55: =IF(L55="","",ROUND(L55*RESUMEN!$B$4,0)) | O55: =COUNT(E55:K55)
A56: 665bb4bf5d480 | B56: ANILLO TREBOL GOLD BLACK | C56: 7 | F56: 5.59 | G56: 5.59 | L56: =IF(COUNT(E56:K56)=0,"",MIN(E56:K56)) | M56: =IF(COUNT(E56:K56)=0,"",LOOKUP(2,1/(E56:K56<>""),E56:K56)) | N56: =IF(L56="","",ROUND(L56*RESUMEN!$B$4,0)) | O56: =COUNT(E56:K56)
A57: 2653020127500 | B57: ANILLO TREBOL GOLD BLACK | C57: 8 | D57: brass | F57: 5.59 | I57: 5.59 | L57: =IF(COUNT(E57:K57)=0,"",MIN(E57:K57)) | M57: =IF(COUNT(E57:K57)=0,"",LOOKUP(2,1/(E57:K57<>""),E57:K57)) | N57: =IF(L57="","",ROUND(L57*RESUMEN!$B$4,0)) | O57: =COUNT(E57:K57)
A58: 665bb4c1438b1 | B58: ANILLO TREBOL GOLD GREEN | C58: 7 | D58: brass | F58: 5.59 | G58: 5.59 | H58: 5.59 | L58: =IF(COUNT(E58:K58)=0,"",MIN(E58:K58)) | M58: =IF(COUNT(E58:K58)=0,"",LOOKUP(2,1/(E58:K58<>""),E58:K58)) | N58: =IF(L58="","",ROUND(L58*RESUMEN!$B$4,0)) | O58: =COUNT(E58:K58)
A59: 02653025069708 | B59: ANILLO TREBOL GOLD WHITE | I59: 5.59 | L59: =IF(COUNT(E59:K59)=0,"",MIN(E59:K59)) | M59: =IF(COUNT(E59:K59)=0,"",LOOKUP(2,1/(E59:K59<>""),E59:K59)) | N59: =IF(L59="","",ROUND(L59*RESUMEN!$B$4,0)) | O59: =COUNT(E59:K59)
A60: 665bb4c25887b | B60: ANILLO TREBOL GOLD WHITE | C60: 7 | G60: 5.59 | L60: =IF(COUNT(E60:K60)=0,"",MIN(E60:K60)) | M60: =IF(COUNT(E60:K60)=0,"",LOOKUP(2,1/(E60:K60<>""),E60:K60)) | N60: =IF(L60="","",ROUND(L60*RESUMEN!$B$4,0)) | O60: =COUNT(E60:K60)
A61: 673cd5677aee7 | B61: ANILLO TRUE GOLD | C61: 6 | G61: 7.59 | L61: =IF(COUNT(E61:K61)=0,"",MIN(E61:K61)) | M61: =IF(COUNT(E61:K61)=0,"",LOOKUP(2,1/(E61:K61<>""),E61:K61)) | N61: =IF(L61="","",ROUND(L61*RESUMEN!$B$4,0)) | O61: =COUNT(E61:K61)
A62: 673cd568aea80 | B62: ANILLO TRUE GOLD | C62: 8 | D62: brass | I62: 5.59 | L62: =IF(COUNT(E62:K62)=0,"",MIN(E62:K62)) | M62: =IF(COUNT(E62:K62)=0,"",LOOKUP(2,1/(E62:K62<>""),E62:K62)) | N62: =IF(L62="","",ROUND(L62*RESUMEN!$B$4,0)) | O62: =COUNT(E62:K62)
A63: 71288022047565 | B63: ANILLO VF ALHAMBRA GOLD | C63: 6 | D63: brass | J63: 5.59 | L63: =IF(COUNT(E63:K63)=0,"",MIN(E63:K63)) | M63: =IF(COUNT(E63:K63)=0,"",LOOKUP(2,1/(E63:K63<>""),E63:K63)) | N63: =IF(L63="","",ROUND(L63*RESUMEN!$B$4,0)) | O63: =COUNT(E63:K63)
A64: 71288022180333 | B64: ANILLO VF ALHAMBRA GOLD | C64: 7 | D64: brass | J64: 5.59 | L64: =IF(COUNT(E64:K64)=0,"",MIN(E64:K64)) | M64: =IF(COUNT(E64:K64)=0,"",LOOKUP(2,1/(E64:K64<>""),E64:K64)) | N64: =IF(L64="","",ROUND(L64*RESUMEN!$B$4,0)) | O64: =COUNT(E64:K64)
A65: 71288022239085 | B65: ANILLO VF ALHAMBRA SILVER | C65: 6 | D65: brass | J65: 5.59 | L65: =IF(COUNT(E65:K65)=0,"",MIN(E65:K65)) | M65: =IF(COUNT(E65:K65)=0,"",LOOKUP(2,1/(E65:K65<>""),E65:K65)) | N65: =IF(L65="","",ROUND(L65*RESUMEN!$B$4,0)) | O65: =COUNT(E65:K65)
A66: 71288022371853 | B66: ANILLO VF ALHAMBRA SILVER | C66: 7 | D66: brass | J66: 5.59 | L66: =IF(COUNT(E66:K66)=0,"",MIN(E66:K66)) | M66: =IF(COUNT(E66:K66)=0,"",LOOKUP(2,1/(E66:K66<>""),E66:K66)) | N66: =IF(L66="","",ROUND(L66*RESUMEN!$B$4,0)) | O66: =COUNT(E66:K66)
A67: 71288022725517 | B67: ANILLO VF PERLÉE DUO GOLD | C67: 6 | D67: brass | J67: 7.99 | L67: =IF(COUNT(E67:K67)=0,"",MIN(E67:K67)) | M67: =IF(COUNT(E67:K67)=0,"",LOOKUP(2,1/(E67:K67<>""),E67:K67)) | N67: =IF(L67="","",ROUND(L67*RESUMEN!$B$4,0)) | O67: =COUNT(E67:K67)
A68: 71288022858285 | B68: ANILLO VF PERLÉE DUO GOLD | C68: 7 | D68: brass | J68: 7.99 | L68: =IF(COUNT(E68:K68)=0,"",MIN(E68:K68)) | M68: =IF(COUNT(E68:K68)=0,"",LOOKUP(2,1/(E68:K68<>""),E68:K68)) | N68: =IF(L68="","",ROUND(L68*RESUMEN!$B$4,0)) | O68: =COUNT(E68:K68)
A69: 71288022597837 | B69: ANILLO VF PERLÉE DUO ROSE GOLD | C69: 6 | D69: brass | J69: 7.99 | L69: =IF(COUNT(E69:K69)=0,"",MIN(E69:K69)) | M69: =IF(COUNT(E69:K69)=0,"",LOOKUP(2,1/(E69:K69<>""),E69:K69)) | N69: =IF(L69="","",ROUND(L69*RESUMEN!$B$4,0)) | O69: =COUNT(E69:K69)
A70: 71288022630605 | B70: ANILLO VF PERLÉE DUO ROSE GOLD | C70: 7 | D70: brass | J70: 7.99 | L70: =IF(COUNT(E70:K70)=0,"",MIN(E70:K70)) | M70: =IF(COUNT(E70:K70)=0,"",LOOKUP(2,1/(E70:K70<>""),E70:K70)) | N70: =IF(L70="","",ROUND(L70*RESUMEN!$B$4,0)) | O70: =COUNT(E70:K70)
A71: 71288022951501 | B71: ANILLO VF PERLÉE DUO SILVER | C71: 6 | D71: brass | J71: 7.99 | L71: =IF(COUNT(E71:K71)=0,"",MIN(E71:K71)) | M71: =IF(COUNT(E71:K71)=0,"",LOOKUP(2,1/(E71:K71<>""),E71:K71)) | N71: =IF(L71="","",ROUND(L71*RESUMEN!$B$4,0)) | O71: =COUNT(E71:K71)
A72: 71288023084269 | B72: ANILLO VF PERLÉE DUO SILVER | C72: 7 | D72: brass | J72: 7.99 | L72: =IF(COUNT(E72:K72)=0,"",MIN(E72:K72)) | M72: =IF(COUNT(E72:K72)=0,"",LOOKUP(2,1/(E72:K72<>""),E72:K72)) | N72: =IF(L72="","",ROUND(L72*RESUMEN!$B$4,0)) | O72: =COUNT(E72:K72)
A73: 71288022468461 | B73: ANILLO VF TWIN ALHAMBRA SILVER | C73: 7 | D73: brass | J73: 7.99 | L73: =IF(COUNT(E73:K73)=0,"",MIN(E73:K73)) | M73: =IF(COUNT(E73:K73)=0,"",LOOKUP(2,1/(E73:K73<>""),E73:K73)) | N73: =IF(L73="","",ROUND(L73*RESUMEN!$B$4,0)) | O73: =COUNT(E73:K73)
A74: 646f84c300fa5 | B74: ARETES BV GOLD-BLACK | C74: 0.7cm | D74: stainless steel | E74: 3.69 | G74: 3.69 | H74: 3.69 | I74: 3.69 | K74: 5.59 | L74: =IF(COUNT(E74:K74)=0,"",MIN(E74:K74)) | M74: =IF(COUNT(E74:K74)=0,"",LOOKUP(2,1/(E74:K74<>""),E74:K74)) | N74: =IF(L74="","",ROUND(L74*RESUMEN!$B$4,0)) | O74: =COUNT(E74:K74)
A75: 52064791097837 | B75: ARETES BV GOLD-WHITE | C75: Default Title | D75: stainless steel | E75: 3.69 | G75: 3.69 | I75: 3.69 | L75: =IF(COUNT(E75:K75)=0,"",MIN(E75:K75)) | M75: =IF(COUNT(E75:K75)=0,"",LOOKUP(2,1/(E75:K75<>""),E75:K75)) | N75: =IF(L75="","",ROUND(L75*RESUMEN!$B$4,0)) | O75: =COUNT(E75:K75)
A76: 63ebd619250f6 | B76: ARETES BV ROSE GOLD CON ZIRCONIA | C76: Default Title | D76: brass | F76: 5.59 | I76: 5.59 | J76: 5.59 | L76: =IF(COUNT(E76:K76)=0,"",MIN(E76:K76)) | M76: =IF(COUNT(E76:K76)=0,"",LOOKUP(2,1/(E76:K76<>""),E76:K76)) | N76: =IF(L76="","",ROUND(L76*RESUMEN!$B$4,0)) | O76: =COUNT(E76:K76)
A77: 63ebd61958890 | B77: ARETES BV ROSE GOLD-BLACK | C77: 1cm | D77: stainless steel | F77: 3.69 | G77: 3.69 | I77: 3.69 | L77: =IF(COUNT(E77:K77)=0,"",MIN(E77:K77)) | M77: =IF(COUNT(E77:K77)=0,"",LOOKUP(2,1/(E77:K77<>""),E77:K77)) | N77: =IF(L77="","",ROUND(L77*RESUMEN!$B$4,0)) | O77: =COUNT(E77:K77)
A78: 64e78ca71edc7 | B78: ARETES BV SILVER- WHITE | C78: Regular | D78: stainless steel | F78: 3.69 | G78: 3.69 | H78: 3.69 | J78: 3.69 | L78: =IF(COUNT(E78:K78)=0,"",MIN(E78:K78)) | M78: =IF(COUNT(E78:K78)=0,"",LOOKUP(2,1/(E78:K78<>""),E78:K78)) | N78: =IF(L78="","",ROUND(L78*RESUMEN!$B$4,0)) | O78: =COUNT(E78:K78)
A79: 64e78ca690d8e | B79: ARETES BV SILVER-BLACK | C79: 0.7 cm | D79: stainless steel | F79: 3.69 | K79: 5.59 | L79: =IF(COUNT(E79:K79)=0,"",MIN(E79:K79)) | M79: =IF(COUNT(E79:K79)=0,"",LOOKUP(2,1/(E79:K79<>""),E79:K79)) | N79: =IF(L79="","",ROUND(L79*RESUMEN!$B$4,0)) | O79: =COUNT(E79:K79)
A80: 62745763441517 | B80: ARETES C CLASH ONYX | C80: Default Title | D80: brass | J80: 14.39 | L80: =IF(COUNT(E80:K80)=0,"",MIN(E80:K80)) | M80: =IF(COUNT(E80:K80)=0,"",LOOKUP(2,1/(E80:K80<>""),E80:K80)) | N80: =IF(L80="","",ROUND(L80*RESUMEN!$B$4,0)) | O80: =COUNT(E80:K80)
A81: 62745763507053 | B81: ARETES C CLASH ROSEGOLD TRIPLE | C81: Default Title | D81: brass | J81: 14.39 | L81: =IF(COUNT(E81:K81)=0,"",MIN(E81:K81)) | M81: =IF(COUNT(E81:K81)=0,"",LOOKUP(2,1/(E81:K81<>""),E81:K81)) | N81: =IF(L81="","",ROUND(L81*RESUMEN!$B$4,0)) | O81: =COUNT(E81:K81)
A82: 58980703081677 | B82: ARETES CC BOUTON CAMELIA | C82: Default Title | D82: brass | J82: 7.99 | L82: =IF(COUNT(E82:K82)=0,"",MIN(E82:K82)) | M82: =IF(COUNT(E82:K82)=0,"",LOOKUP(2,1/(E82:K82<>""),E82:K82)) | N82: =IF(L82="","",ROUND(L82*RESUMEN!$B$4,0)) | O82: =COUNT(E82:K82)
A83: 58980702817837 | B83: ARETES CC ETOILE FILANTE SILVER | C83: Default Title | D83: brass | J83: 7.59 | L83: =IF(COUNT(E83:K83)=0,"",MIN(E83:K83)) | M83: =IF(COUNT(E83:K83)=0,"",LOOKUP(2,1/(E83:K83<>""),E83:K83)) | N83: =IF(L83="","",ROUND(L83*RESUMEN!$B$4,0)) | O83: =COUNT(E83:K83)
A84: 22974392232621 | B84: ARETES CC RESIN PEARL SILVER | C84: Default Title | D84: alloy | H84: 2.99 | L84: =IF(COUNT(E84:K84)=0,"",MIN(E84:K84)) | M84: =IF(COUNT(E84:K84)=0,"",LOOKUP(2,1/(E84:K84<>""),E84:K84)) | N84: =IF(L84="","",ROUND(L84*RESUMEN!$B$4,0)) | O84: =COUNT(E84:K84)
A85: 665bb4e91bcaf | B85: ARETES CD GOLD BLACK | C85: Default Title | D85: brass | G85: 5.59 | I85: 5.59 | J85: 5.59 | K85: 5.59 | L85: =IF(COUNT(E85:K85)=0,"",MIN(E85:K85)) | M85: =IF(COUNT(E85:K85)=0,"",LOOKUP(2,1/(E85:K85<>""),E85:K85)) | N85: =IF(L85="","",ROUND(L85*RESUMEN!$B$4,0)) | O85: =COUNT(E85:K85)
A86: 42981640208524 | B86: ARETES CD GOLD CON PERLA COLGANTE | C86: Default Title | D86: brass | E86: 4.49 | F86: 4.49 | G86: 5.59 | H86: 5.59 | I86: 4.49 | K86: 5.59 | L86: =IF(COUNT(E86:K86)=0,"",MIN(E86:K86)) | M86: =IF(COUNT(E86:K86)=0,"",LOOKUP(2,1/(E86:K86<>""),E86:K86)) | N86: =IF(L86="","",ROUND(L86*RESUMEN!$B$4,0)) | O86: =COUNT(E86:K86)
A87: 665bb4f54f46f | B87: ARETES CORAZÓN GC | C87: Default Title | G87: 5.59 | K87: 3.69 | L87: =IF(COUNT(E87:K87)=0,"",MIN(E87:K87)) | M87: =IF(COUNT(E87:K87)=0,"",LOOKUP(2,1/(E87:K87<>""),E87:K87)) | N87: =IF(L87="","",ROUND(L87*RESUMEN!$B$4,0)) | O87: =COUNT(E87:K87)
A88: 43047196360844 | B88: ARETES CORAZÓN GRABADO SILVER | C88: Default Title | E88: 2.39 | L88: =IF(COUNT(E88:K88)=0,"",MIN(E88:K88)) | M88: =IF(COUNT(E88:K88)=0,"",LOOKUP(2,1/(E88:K88<>""),E88:K88)) | N88: =IF(L88="","",ROUND(L88*RESUMEN!$B$4,0)) | O88: =COUNT(E88:K88)
A89: 68eee447fb3d | B89: ARETES DE ESLABONES GOLD MZ | F89: 6.99 | L89: =IF(COUNT(E89:K89)=0,"",MIN(E89:K89)) | M89: =IF(COUNT(E89:K89)=0,"",LOOKUP(2,1/(E89:K89<>""),E89:K89)) | N89: =IF(L89="","",ROUND(L89*RESUMEN!$B$4,0)) | O89: =COUNT(E89:K89)
A90: 668eee447fb3d | B90: ARETES DE ESLABONES GOLD MZ | C90: High Quality | D90: brass | H90: 5.79 | I90: 6.99 | J90: 6.99 | K90: 7.59 | L90: =IF(COUNT(E90:K90)=0,"",MIN(E90:K90)) | M90: =IF(COUNT(E90:K90)=0,"",LOOKUP(2,1/(E90:K90<>""),E90:K90)) | N90: =IF(L90="","",ROUND(L90*RESUMEN!$B$4,0)) | O90: =COUNT(E90:K90)
A91: 43047216775308 | B91: ARETES ESLABON LISO GOLD | C91: Default Title | D91: brass | F91: 5.79 | H91: 5.79 | I91: 5.79 | L91: =IF(COUNT(E91:K91)=0,"",MIN(E91:K91)) | M91: =IF(COUNT(E91:K91)=0,"",LOOKUP(2,1/(E91:K91<>""),E91:K91)) | N91: =IF(L91="","",ROUND(L91*RESUMEN!$B$4,0)) | O91: =COUNT(E91:K91)
A92: 43047216545932 | B92: ARETES ESLABON LISO ROSEGOLD | C92: Small 3cm | D92: brass | G92: 5.79 | J92: 5.79 | L92: =IF(COUNT(E92:K92)=0,"",MIN(E92:K92)) | M92: =IF(COUNT(E92:K92)=0,"",LOOKUP(2,1/(E92:K92<>""),E92:K92)) | N92: =IF(L92="","",ROUND(L92*RESUMEN!$B$4,0)) | O92: =COUNT(E92:K92)
A93: 42981553012876 | B93: ARETES ESSENTIAL LV GOLD | C93: Default Title | D93: brass | E93: 4.19 | F93: 5.59 | G93: 5.59 | H93: 5.59 | I93: 5.59 | J93: 5.59 | L93: =IF(COUNT(E93:K93)=0,"",MIN(E93:K93)) | M93: =IF(COUNT(E93:K93)=0,"",LOOKUP(2,1/(E93:K93<>""),E93:K93)) | N93: =IF(L93="","",ROUND(L93*RESUMEN!$B$4,0)) | O93: =COUNT(E93:K93)
A94: 42981569396876 | B94: ARETES ESSENTIAL LV SILVER | C94: Default Title | D94: brass | G94: 5.59 | H94: 5.59 | I94: 5.59 | L94: =IF(COUNT(E94:K94)=0,"",MIN(E94:K94)) | M94: =IF(COUNT(E94:K94)=0,"",LOOKUP(2,1/(E94:K94<>""),E94:K94)) | N94: =IF(L94="","",ROUND(L94*RESUMEN!$B$4,0)) | O94: =COUNT(E94:K94)
A95: 42981998657676 | B95: ARETES FR GOLD | C95: Regular | D95: brass | E95: 4.49 | F95: 4.49 | H95: 5.59 | J95: 4.99 | L95: =IF(COUNT(E95:K95)=0,"",MIN(E95:K95)) | M95: =IF(COUNT(E95:K95)=0,"",LOOKUP(2,1/(E95:K95<>""),E95:K95)) | N95: =IF(L95="","",ROUND(L95*RESUMEN!$B$4,0)) | O95: =COUNT(E95:K95)
A96: 42982006882444 | B96: ARETES FR GOLD CON PERLA | C96: Default Title | D96: brass | E96: 4.49 | F96: 4.49 | H96: 5.59 | I96: 4.49 | J96: 4.99 | K96: 4.99 | L96: =IF(COUNT(E96:K96)=0,"",MIN(E96:K96)) | M96: =IF(COUNT(E96:K96)=0,"",LOOKUP(2,1/(E96:K96<>""),E96:K96)) | N96: =IF(L96="","",ROUND(L96*RESUMEN!$B$4,0)) | O96: =COUNT(E96:K96)
A97: 665bd22d2f1c6 | B97: ARETES FR GOLD CON ZIRCONIA | C97: Regular | D97: brass | E97: 4.99 | H97: 5.59 | I97: 5.59 | K97: 4.99 | L97: =IF(COUNT(E97:K97)=0,"",MIN(E97:K97)) | M97: =IF(COUNT(E97:K97)=0,"",LOOKUP(2,1/(E97:K97<>""),E97:K97)) | N97: =IF(L97="","",ROUND(L97*RESUMEN!$B$4,0)) | O97: =COUNT(E97:K97)
A98: 678a9af396518 | B98: ARETES FR SILVER | C98: Regular | D98: brass | F98: 4.49 | J98: 4.99 | K98: 4.99 | L98: =IF(COUNT(E98:K98)=0,"",MIN(E98:K98)) | M98: =IF(COUNT(E98:K98)=0,"",LOOKUP(2,1/(E98:K98<>""),E98:K98)) | N98: =IF(L98="","",ROUND(L98*RESUMEN!$B$4,0)) | O98: =COUNT(E98:K98)
A99: 68431135029516 | B99: ARETES GC COLGANTES PERLA | C99: Default Title | E99: 4.49 | L99: =IF(COUNT(E99:K99)=0,"",MIN(E99:K99)) | M99: =IF(COUNT(E99:K99)=0,"",LOOKUP(2,1/(E99:K99<>""),E99:K99)) | N99: =IF(L99="","",ROUND(L99*RESUMEN!$B$4,0)) | O99: =COUNT(E99:K99)
A100: 64e78ca83b5da-1 | B100: ARETES GC GOLD | C100: Regular | D100: brass | G100: 5.59 | I100: 5.59 | K100: 2.99 | L100: =IF(COUNT(E100:K100)=0,"",MIN(E100:K100)) | M100: =IF(COUNT(E100:K100)=0,"",LOOKUP(2,1/(E100:K100<>""),E100:K100)) | N100: =IF(L100="","",ROUND(L100*RESUMEN!$B$4,0)) | O100: =COUNT(E100:K100)
A101: 654bdb23ce5c1 | B101: ARETES GC ICE CREAM | C101: Regular | D101: brass | J101: 6.29 | L101: =IF(COUNT(E101:K101)=0,"",MIN(E101:K101)) | M101: =IF(COUNT(E101:K101)=0,"",LOOKUP(2,1/(E101:K101<>""),E101:K101)) | N101: =IF(L101="","",ROUND(L101*RESUMEN!$B$4,0)) | O101: =COUNT(E101:K101)
...

Sheet DINA DU
A1: HISTORIAL DE PRECIOS — DINA DU
A2: 5 orden(es) · costo unitario en USD · MXN = MEJOR × RESUMEN!B4 · * = dato del historial previo
A4: SKU | B4: PRODUCTO | C4: VARIANTE | D4: MATERIAL | E4: Dic 2024 ord.1046* | F4: Ene 2025 ord.1046* | G4: Oct 2025 21/10 | H4: Feb 2026 06/02 | I4: Abr 2026 27/04 | J4: MEJOR (US) | K4: ÚLTIMA (US) | L4: MXN (mejor×TC) | M4: # ÓRD.
A5: ⚠️ 17 | B5: 2-M | F5: 16 | J5: =IF(COUNT(E5:I5)=0,"",MIN(E5:I5)) | K5: =IF(COUNT(E5:I5)=0,"",LOOKUP(2,1/(E5:I5<>""),E5:I5)) | L5: =IF(J5="","",ROUND(J5*RESUMEN!$B$4,0)) | M5: =COUNT(E5:I5)
A6: 66593bcfaca6f | B6: ANILLO MM | C6: AJUSTABLE | H6: 2.79 | I6: 2.79 | J6: =IF(COUNT(E6:I6)=0,"",MIN(E6:I6)) | K6: =IF(COUNT(E6:I6)=0,"",LOOKUP(2,1/(E6:I6<>""),E6:I6)) | L6: =IF(J6="","",ROUND(J6*RESUMEN!$B$4,0)) | M6: =COUNT(E6:I6)
A7: 648cc5b58feaa | B7: ARETES MM COLGANTE | C7: Default Title | D7: stianless steel | G7: 2.39 | I7: 2.39 | J7: =IF(COUNT(E7:I7)=0,"",MIN(E7:I7)) | K7: =IF(COUNT(E7:I7)=0,"",LOOKUP(2,1/(E7:I7<>""),E7:I7)) | L7: =IF(J7="","",ROUND(J7*RESUMEN!$B$4,0)) | M7: =COUNT(E7:I7)
A8: 654bdbdb26372 | B8: BOLSA CC WHITE | C8: 17cmx24cm | I8: 18 | J8: =IF(COUNT(E8:I8)=0,"",MIN(E8:I8)) | K8: =IF(COUNT(E8:I8)=0,"",LOOKUP(2,1/(E8:I8<>""),E8:I8)) | L8: =IF(J8="","",ROUND(J8*RESUMEN!$B$4,0)) | M8: =COUNT(E8:I8)
A9: 94956736687244 | B9: BOLSA MINI POCHETTE LV | C9: 9cm de alto x 15cm de largo x 3cm de ancho | H9: 22 | I9: 22 | J9: =IF(COUNT(E9:I9)=0,"",MIN(E9:I9)) | K9: =IF(COUNT(E9:I9)=0,"",LOOKUP(2,1/(E9:I9<>""),E9:I9)) | L9: =IF(J9="","",ROUND(J9*RESUMEN!$B$4,0)) | M9: =COUNT(E9:I9)
A10: 43124008910988 | B10: BOLSO C CLAUDE | C10: 13.5cm de alto x 22cm de largo x 5cm de ancho | D10: Lambskin leather | G10: 45 | H10: 45 | J10: =IF(COUNT(E10:I10)=0,"",MIN(E10:I10)) | K10: =IF(COUNT(E10:I10)=0,"",LOOKUP(2,1/(E10:I10<>""),E10:I10)) | L10: =IF(J10="","",ROUND(J10*RESUMEN!$B$4,0)) | M10: =COUNT(E10:I10)
A11: 85367152250157 | B11: BOLSO C NINO BLACK | C11: BLACK/GOLD | H11: 45 | J11: =IF(COUNT(E11:I11)=0,"",MIN(E11:I11)) | K11: =IF(COUNT(E11:I11)=0,"",LOOKUP(2,1/(E11:I11<>""),E11:I11)) | L11: =IF(J11="","",ROUND(J11*RESUMEN!$B$4,0)) | M11: =COUNT(E11:I11)
A12: 44504631084621 | B12: BOLSO C TILLY BROWN | C12: 15cm de alto x 19.5cm de largo x 7.5cm de ancho | G12: 42 | J12: =IF(COUNT(E12:I12)=0,"",MIN(E12:I12)) | K12: =IF(COUNT(E12:I12)=0,"",LOOKUP(2,1/(E12:I12<>""),E12:I12)) | L12: =IF(J12="","",ROUND(J12*RESUMEN!$B$4,0)) | M12: =COUNT(E12:I12)
A13: 85367152384621 | B13: BOLSO CC BOY BLACK | C13: BLACK/GOLD | H13: 15 | J13: =IF(COUNT(E13:I13)=0,"",MIN(E13:I13)) | K13: =IF(COUNT(E13:I13)=0,"",LOOKUP(2,1/(E13:I13<>""),E13:I13)) | L13: =IF(J13="","",ROUND(J13*RESUMEN!$B$4,0)) | M13: =COUNT(E13:I13)
A14: 654bdbd5ab77d | B14: BOLSO CC BOY MINI BLACK | C14: 24.8cm de largo x 16cm de alto x 7.5cm de ancho | D14: Lambskin leather | G14: 15 | H14: 15 | I14: 15 | J14: =IF(COUNT(E14:I14)=0,"",MIN(E14:I14)) | K14: =IF(COUNT(E14:I14)=0,"",LOOKUP(2,1/(E14:I14<>""),E14:I14)) | L14: =IF(J14="","",ROUND(J14*RESUMEN!$B$4,0)) | M14: =COUNT(E14:I14)
A15: 85367152182925 | B15: BOLSO CC SHINY STAR BLACK | C15: BLACK/GOLD | H15: 56 | J15: =IF(COUNT(E15:I15)=0,"",MIN(E15:I15)) | K15: =IF(COUNT(E15:I15)=0,"",LOOKUP(2,1/(E15:I15<>""),E15:I15)) | L15: =IF(J15="","",ROUND(J15*RESUMEN!$B$4,0)) | M15: =COUNT(E15:I15)
A16: 10132411318605 | B16: BOLSO CD BOW BLACK | C16: Default Title | I16: 71 | J16: =IF(COUNT(E16:I16)=0,"",MIN(E16:I16)) | K16: =IF(COUNT(E16:I16)=0,"",LOOKUP(2,1/(E16:I16<>""),E16:I16)) | L16: =IF(J16="","",ROUND(J16*RESUMEN!$B$4,0)) | M16: =COUNT(E16:I16)
A17: 10132411251373 | B17: BOLSO CD BOW BURGUNDY | C17: Default Title | I17: 71 | J17: =IF(COUNT(E17:I17)=0,"",MIN(E17:I17)) | K17: =IF(COUNT(E17:I17)=0,"",LOOKUP(2,1/(E17:I17<>""),E17:I17)) | L17: =IF(J17="","",ROUND(J17*RESUMEN!$B$4,0)) | M17: =COUNT(E17:I17)
A18: 85367151372749 | B18: BOLSO CD MESSENGER SOLAPA | C18: BLACK | H18: 43 | J18: =IF(COUNT(E18:I18)=0,"",MIN(E18:I18)) | K18: =IF(COUNT(E18:I18)=0,"",LOOKUP(2,1/(E18:I18<>""),E18:I18)) | L18: =IF(J18="","",ROUND(J18*RESUMEN!$B$4,0)) | M18: =COUNT(E18:I18)
A19: 10132411116909 | B19: BOLSO CD SADDLE ALL BLACK | C19: Default Title | I19: 63 | J19: =IF(COUNT(E19:I19)=0,"",MIN(E19:I19)) | K19: =IF(COUNT(E19:I19)=0,"",LOOKUP(2,1/(E19:I19<>""),E19:I19)) | L19: =IF(J19="","",ROUND(J19*RESUMEN!$B$4,0)) | M19: =COUNT(E19:I19)
A20: 85367151238285 | B20: BOLSO CD SAFARI OBLIQUE | C20: BLACK/BLUE | H20: 48 | J20: =IF(COUNT(E20:I20)=0,"",MIN(E20:I20)) | K20: =IF(COUNT(E20:I20)=0,"",LOOKUP(2,1/(E20:I20<>""),E20:I20)) | L20: =IF(J20="","",ROUND(J20*RESUMEN!$B$4,0)) | M20: =COUNT(E20:I20)
A21: 19693770314380 | B21: BOLSO DE VIAJE BROWN LV 55cm | C21: HIGH QUALITY | I21: 63 | J21: =IF(COUNT(E21:I21)=0,"",MIN(E21:I21)) | K21: =IF(COUNT(E21:I21)=0,"",LOOKUP(2,1/(E21:I21<>""),E21:I21)) | L21: =IF(J21="","",ROUND(J21*RESUMEN!$B$4,0)) | M21: =COUNT(E21:I21)
A22: 665bb9079b157 | B22: BOLSO DOUBLE V LV | C22: 17cm de alto x 23cm de largo x 9.5cm de ancho | D22: Lambskin leather | G22: 45 | J22: =IF(COUNT(E22:I22)=0,"",MIN(E22:I22)) | K22: =IF(COUNT(E22:I22)=0,"",LOOKUP(2,1/(E22:I22<>""),E22:I22)) | L22: =IF(J22="","",ROUND(J22*RESUMEN!$B$4,0)) | M22: =COUNT(E22:I22)
A23: 10132411776813 | B23: BOLSO F GRAPHY LOGOS | C23: Default Title | I23: 78 | J23: =IF(COUNT(E23:I23)=0,"",MIN(E23:I23)) | K23: =IF(COUNT(E23:I23)=0,"",LOOKUP(2,1/(E23:I23<>""),E23:I23)) | L23: =IF(J23="","",ROUND(J23*RESUMEN!$B$4,0)) | M23: =COUNT(E23:I23)
A24: 677c26af628d5 | B24: BOLSO GC DIONYSUS CHERRY RED | C24: 18cm de largo x 12cm de alto x 4cm de ancho | I24: 56 | J24: =IF(COUNT(E24:I24)=0,"",MIN(E24:I24)) | K24: =IF(COUNT(E24:I24)=0,"",LOOKUP(2,1/(E24:I24<>""),E24:I24)) | L24: =IF(J24="","",ROUND(J24*RESUMEN!$B$4,0)) | M24: =COUNT(E24:I24)
A25: 677c26ae9f248 | B25: BOLSO LV BAGATELLE | C25: 23cm de largo x 20cm de alto x 8.5cm | D25: Lambskin leather | G25: 43 | I25: 43 | J25: =IF(COUNT(E25:I25)=0,"",MIN(E25:I25)) | K25: =IF(COUNT(E25:I25)=0,"",LOOKUP(2,1/(E25:I25<>""),E25:I25)) | L25: =IF(J25="","",ROUND(J25*RESUMEN!$B$4,0)) | M25: =COUNT(E25:I25)
A26: 43728084218572 | B26: BOLSO LV DISTRICT BLACK | C26: 25cm de largo x 23cm de alto x 6.5cm de ancho (REMATE) | D26: Micro fiber leat | G26: 21 | J26: =IF(COUNT(E26:I26)=0,"",MIN(E26:I26)) | K26: =IF(COUNT(E26:I26)=0,"",LOOKUP(2,1/(E26:I26<>""),E26:I26)) | L26: =IF(J26="","",ROUND(J26*RESUMEN!$B$4,0)) | M26: =COUNT(E26:I26)
A27: 654bdc44be732 | B27: BOLSO LV PÉGASE BLACK | C27: 25.5cm de largo x 26cm de alto x 6.cm de ancho | D27: Micro fiber leat | G27: 21 | J27: =IF(COUNT(E27:I27)=0,"",MIN(E27:I27)) | K27: =IF(COUNT(E27:I27)=0,"",LOOKUP(2,1/(E27:I27<>""),E27:I27)) | L27: =IF(J27="","",ROUND(J27*RESUMEN!$B$4,0)) | M27: =COUNT(E27:I27)
A28: 64e78f9336406 | B28: BOLSO V BLACK | C28: 20.5cmx14cm | D28: Lambskin leather | G28: 46 | H28: 46 | J28: =IF(COUNT(E28:I28)=0,"",MIN(E28:I28)) | K28: =IF(COUNT(E28:I28)=0,"",LOOKUP(2,1/(E28:I28<>""),E28:I28)) | L28: =IF(J28="","",ROUND(J28*RESUMEN!$B$4,0)) | M28: =COUNT(E28:I28)
A29: 64e78f941b012 | B29: BOLSO V WHITE | C29: 20.5cmx14cm | D29: Lambskin leather | G29: 46 | J29: =IF(COUNT(E29:I29)=0,"",MIN(E29:I29)) | K29: =IF(COUNT(E29:I29)=0,"",LOOKUP(2,1/(E29:I29<>""),E29:I29)) | L29: =IF(J29="","",ROUND(J29*RESUMEN!$B$4,0)) | M29: =COUNT(E29:I29)
A30: 67572cbd4a7ca | B30: BOLSO YSL CON CADENA BLACK | C30: 19cm de alto x 24cm de largo x 7cm de ancho | D30: Lambskin leather | G30: 46 | H30: 46 | J30: =IF(COUNT(E30:I30)=0,"",MIN(E30:I30)) | K30: =IF(COUNT(E30:I30)=0,"",LOOKUP(2,1/(E30:I30<>""),E30:I30)) | L30: =IF(J30="","",ROUND(J30*RESUMEN!$B$4,0)) | M30: =COUNT(E30:I30)
A31: 58071991054829 | B31: BOLSO YSL CON CADENA BURDEOS | C31: 24cm de largo x 18cm de alto x 8cm de ancho. | I31: 46 | J31: =IF(COUNT(E31:I31)=0,"",MIN(E31:I31)) | K31: =IF(COUNT(E31:I31)=0,"",LOOKUP(2,1/(E31:I31<>""),E31:I31)) | L31: =IF(J31="","",ROUND(J31*RESUMEN!$B$4,0)) | M31: =COUNT(E31:I31)
A32: 43409491041677 | B32: BOLSO YSL CON CADENA NUDE | C32: REGULAR | I32: 46 | J32: =IF(COUNT(E32:I32)=0,"",MIN(E32:I32)) | K32: =IF(COUNT(E32:I32)=0,"",LOOKUP(2,1/(E32:I32<>""),E32:I32)) | L32: =IF(J32="","",ROUND(J32*RESUMEN!$B$4,0)) | M32: =COUNT(E32:I32)
A33: 94350532835596 | B33: BOLSO YSL CON CADENA NUDE | C33: REGULAR | D33: Lambskin leather | G33: 46 | J33: =IF(COUNT(E33:I33)=0,"",MIN(E33:I33)) | K33: =IF(COUNT(E33:I33)=0,"",LOOKUP(2,1/(E33:I33<>""),E33:I33)) | L33: =IF(J33="","",ROUND(J33*RESUMEN!$B$4,0)) | M33: =COUNT(E33:I33)
A34: 67572cbe60534 | B34: BOLSO YSL CON CADENA OFF WHITE | C34: Middle Quality | I34: 46 | J34: =IF(COUNT(E34:I34)=0,"",MIN(E34:I34)) | K34: =IF(COUNT(E34:I34)=0,"",LOOKUP(2,1/(E34:I34<>""),E34:I34)) | L34: =IF(J34="","",ROUND(J34*RESUMEN!$B$4,0)) | M34: =COUNT(E34:I34)
A35: 654bdc38b0ca9 | B35: BOLSO YSL CON CADENA RED | C35: 17.5cm de alto x 23.5cm de largo x 6cm de ancho | D35: Lambskin leather | G35: 46 | J35: =IF(COUNT(E35:I35)=0,"",MIN(E35:I35)) | K35: =IF(COUNT(E35:I35)=0,"",LOOKUP(2,1/(E35:I35<>""),E35:I35)) | L35: =IF(J35="","",ROUND(J35*RESUMEN!$B$4,0)) | M35: =COUNT(E35:I35)
A36: 85367151645069 | B36: CARTERA C SMALL BLACK | C36: BLACK/GOLD | H36: 28 | J36: =IF(COUNT(E36:I36)=0,"",MIN(E36:I36)) | K36: =IF(COUNT(E36:I36)=0,"",LOOKUP(2,1/(E36:I36<>""),E36:I36)) | L36: =IF(J36="","",ROUND(J36*RESUMEN!$B$4,0)) | M36: =COUNT(E36:I36)
A37: 43728091877228 | B37: CARTERA CC BLACK | C37: 13cmx13cm | D37: Micro fiber leat | G37: 24 | H37: 24 | I37: 24 | J37: =IF(COUNT(E37:I37)=0,"",MIN(E37:I37)) | K37: =IF(COUNT(E37:I37)=0,"",LOOKUP(2,1/(E37:I37<>""),E37:I37)) | L37: =IF(J37="","",ROUND(J37*RESUMEN!$B$4,0)) | M37: =COUNT(E37:I37)
A38: 85367152015693 | B38: CARTERA CC JOLIE BLACK | C38: BLACK/GOLD | H38: 23 | J38: =IF(COUNT(E38:I38)=0,"",MIN(E38:I38)) | K38: =IF(COUNT(E38:I38)=0,"",LOOKUP(2,1/(E38:I38<>""),E38:I38)) | L38: =IF(J38="","",ROUND(J38*RESUMEN!$B$4,0)) | M38: =COUNT(E38:I38)
A39: 10132411606189 | B39: CARTERA F BAGUETTE MINI | C39: Default Title | I39: 75 | J39: =IF(COUNT(E39:I39)=0,"",MIN(E39:I39)) | K39: =IF(COUNT(E39:I39)=0,"",LOOKUP(2,1/(E39:I39<>""),E39:I39)) | L39: =IF(J39="","",ROUND(J39*RESUMEN!$B$4,0)) | M39: =COUNT(E39:I39)
A40: 10132411501101 | B40: CARTERA F GRAPHY WHITE | C40: Default Title | I40: 52 | J40: =IF(COUNT(E40:I40)=0,"",MIN(E40:I40)) | K40: =IF(COUNT(E40:I40)=0,"",LOOKUP(2,1/(E40:I40<>""),E40:I40)) | L40: =IF(J40="","",ROUND(J40*RESUMEN!$B$4,0)) | M40: =COUNT(E40:I40)
A41: 43728091639180 | B41: CARTERA LV BLUE | C41: 12cmx9cm | D41: Micro fiber leat | G41: 13 | I41: 13 | J41: =IF(COUNT(E41:I41)=0,"",MIN(E41:I41)) | K41: =IF(COUNT(E41:I41)=0,"",LOOKUP(2,1/(E41:I41<>""),E41:I41)) | L41: =IF(J41="","",ROUND(J41*RESUMEN!$B$4,0)) | M41: =COUNT(E41:I41)
A42: 648cc60ce32b1 | B42: CARTERA LV BROWN | C42: 12cmx9cm | D42: Micro fiber leat | G42: 13 | I42: 13 | J42: =IF(COUNT(E42:I42)=0,"",MIN(E42:I42)) | K42: =IF(COUNT(E42:I42)=0,"",LOOKUP(2,1/(E42:I42<>""),E42:I42)) | L42: =IF(J42="","",ROUND(J42*RESUMEN!$B$4,0)) | M42: =COUNT(E42:I42)
A43: 85367151407213 | B43: CARTERA LV SARAH MONOGRAM | C43: BROWN | H43: 18 | J43: =IF(COUNT(E43:I43)=0,"",MIN(E43:I43)) | K43: =IF(COUNT(E43:I43)=0,"",LOOKUP(2,1/(E43:I43<>""),E43:I43)) | L43: =IF(J43="","",ROUND(J43*RESUMEN!$B$4,0)) | M43: =COUNT(E43:I43)
A44: 85367151779533 | B44: CARTERA PR LOGO | C44: BLACK/GOLD | H44: 29 | J44: =IF(COUNT(E44:I44)=0,"",MIN(E44:I44)) | K44: =IF(COUNT(E44:I44)=0,"",LOOKUP(2,1/(E44:I44<>""),E44:I44)) | L44: =IF(J44="","",ROUND(J44*RESUMEN!$B$4,0)) | M44: =COUNT(E44:I44)
A45: 85367151846765 | B45: CARTERA YSL SILVER LOGO | C45: BLACK/SILVER | H45: 25 | J45: =IF(COUNT(E45:I45)=0,"",MIN(E45:I45)) | K45: =IF(COUNT(E45:I45)=0,"",LOOKUP(2,1/(E45:I45<>""),E45:I45)) | L45: =IF(J45="","",ROUND(J45*RESUMEN!$B$4,0)) | M45: =COUNT(E45:I45)
A46: 648cc5c03c2b5 | B46: CHOKER MM ZIRCONIAS | C46: 41cm | I46: 4.09 | J46: =IF(COUNT(E46:I46)=0,"",MIN(E46:I46)) | K46: =IF(COUNT(E46:I46)=0,"",LOOKUP(2,1/(E46:I46<>""),E46:I46)) | L46: =IF(J46="","",ROUND(J46*RESUMEN!$B$4,0)) | M46: =COUNT(E46:I46)
A47: 654bdbcfcfee3 | B47: CINTO C GOLD BLACK | C47: 100cm | H47: 15 | J47: =IF(COUNT(E47:I47)=0,"",MIN(E47:I47)) | K47: =IF(COUNT(E47:I47)=0,"",LOOKUP(2,1/(E47:I47<>""),E47:I47)) | L47: =IF(J47="","",ROUND(J47*RESUMEN!$B$4,0)) | M47: =COUNT(E47:I47)
A48: 42265109266572 | B48: CINTO CD | C48: 100cm | H48: 10 | J48: =IF(COUNT(E48:I48)=0,"",MIN(E48:I48)) | K48: =IF(COUNT(E48:I48)=0,"",LOOKUP(2,1/(E48:I48<>""),E48:I48)) | L48: =IF(J48="","",ROUND(J48*RESUMEN!$B$4,0)) | M48: =COUNT(E48:I48)
A49: 654bdbcf948ed | B49: CINTO FR GOLD BLACK | C49: 115cm | H49: 12 | J49: =IF(COUNT(E49:I49)=0,"",MIN(E49:I49)) | K49: =IF(COUNT(E49:I49)=0,"",LOOKUP(2,1/(E49:I49<>""),E49:I49)) | L49: =IF(J49="","",ROUND(J49*RESUMEN!$B$4,0)) | M49: =COUNT(E49:I49)
A50: 42556045426828 | B50: CINTO FR ROSEGOLD | C50: 100cm | D50: Split leather | G50: 12 | H50: 12 | I50: 12 | J50: =IF(COUNT(E50:I50)=0,"",MIN(E50:I50)) | K50: =IF(COUNT(E50:I50)=0,"",LOOKUP(2,1/(E50:I50<>""),E50:I50)) | L50: =IF(J50="","",ROUND(J50*RESUMEN!$B$4,0)) | M50: =COUNT(E50:I50)
A51: 85367152486317 | B51: CINTO FR SILVER BROWN | C51: 100cm | H51: 12 | J51: =IF(COUNT(E51:I51)=0,"",MIN(E51:I51)) | K51: =IF(COUNT(E51:I51)=0,"",LOOKUP(2,1/(E51:I51<>""),E51:I51)) | L51: =IF(J51="","",ROUND(J51*RESUMEN!$B$4,0)) | M51: =COUNT(E51:I51)
A52: 648cc60e5d7a4 | B52: CINTO GC BLACK | C52: 100cm | D52: Split leather | G52: 12 | J52: =IF(COUNT(E52:I52)=0,"",MIN(E52:I52)) | K52: =IF(COUNT(E52:I52)=0,"",LOOKUP(2,1/(E52:I52<>""),E52:I52)) | L52: =IF(J52="","",ROUND(J52*RESUMEN!$B$4,0)) | M52: =COUNT(E52:I52)
A53: 654bdbcfd9269 | B53: CINTO H BLACK | C53: 100cm con extension | D53: Split leather | G53: 15 | H53: 15 | J53: =IF(COUNT(E53:I53)=0,"",MIN(E53:I53)) | K53: =IF(COUNT(E53:I53)=0,"",LOOKUP(2,1/(E53:I53<>""),E53:I53)) | L53: =IF(J53="","",ROUND(J53*RESUMEN!$B$4,0)) | M53: =COUNT(E53:I53)
A54: 654bdbd026f64 | B54: CINTO H GOLD BLACK | C54: 100cm con extension | I54: 15 | J54: =IF(COUNT(E54:I54)=0,"",MIN(E54:I54)) | K54: =IF(COUNT(E54:I54)=0,"",LOOKUP(2,1/(E54:I54<>""),E54:I54)) | L54: =IF(J54="","",ROUND(J54*RESUMEN!$B$4,0)) | M54: =COUNT(E54:I54)
A55: 654bdbcfbb016 | B55: CINTO H SILVER BLACK | C55: 115cm con extension | H55: 15 | I55: 15 | J55: =IF(COUNT(E55:I55)=0,"",MIN(E55:I55)) | K55: =IF(COUNT(E55:I55)=0,"",LOOKUP(2,1/(E55:I55<>""),E55:I55)) | L55: =IF(J55="","",ROUND(J55*RESUMEN!$B$4,0)) | M55: =COUNT(E55:I55)
A56: 654bdbcfde867 | B56: CINTO YSL GOLD BLACK | C56: 100cm | D56: Split leather | G56: 12 | H56: 12 | J56: =IF(COUNT(E56:I56)=0,"",MIN(E56:I56)) | K56: =IF(COUNT(E56:I56)=0,"",LOOKUP(2,1/(E56:I56<>""),E56:I56)) | L56: =IF(J56="","",ROUND(J56*RESUMEN!$B$4,0)) | M56: =COUNT(E56:I56)
A57: 10132411463245 | B57: GORRO F LOGOS | C57: Default Title | I57: 10 | J57: =IF(COUNT(E57:I57)=0,"",MIN(E57:I57)) | K57: =IF(COUNT(E57:I57)=0,"",LOOKUP(2,1/(E57:I57<>""),E57:I57)) | L57: =IF(J57="","",ROUND(J57*RESUMEN!$B$4,0)) | M57: =COUNT(E57:I57)
A58: 648cc600a2ec5 | B58: GORRO PR BLACK | C58: M | I58: 11 | J58: =IF(COUNT(E58:I58)=0,"",MIN(E58:I58)) | K58: =IF(COUNT(E58:I58)=0,"",LOOKUP(2,1/(E58:I58<>""),E58:I58)) | L58: =IF(J58="","",ROUND(J58*RESUMEN!$B$4,0)) | M58: =COUNT(E58:I58)
A59: 64e78f9c9c153 | B59: GORRO PR MEZCLILLA BLACK | C59: S | I59: 11 | J59: =IF(COUNT(E59:I59)=0,"",MIN(E59:I59)) | K59: =IF(COUNT(E59:I59)=0,"",LOOKUP(2,1/(E59:I59<>""),E59:I59)) | L59: =IF(J59="","",ROUND(J59*RESUMEN!$B$4,0)) | M59: =COUNT(E59:I59)
A60: 95383471436684 | B60: HOODIE C BLACK | C60: L | D60: Cotton | G60: 27 | J60: =IF(COUNT(E60:I60)=0,"",MIN(E60:I60)) | K60: =IF(COUNT(E60:I60)=0,"",LOOKUP(2,1/(E60:I60<>""),E60:I60)) | L60: =IF(J60="","",ROUND(J60*RESUMEN!$B$4,0)) | M60: =COUNT(E60:I60)
A61: 42265107366028 | B61: HOODIE C BLACK | C61: M | D61: Cotton | G61: 27 | J61: =IF(COUNT(E61:I61)=0,"",MIN(E61:I61)) | K61: =IF(COUNT(E61:I61)=0,"",LOOKUP(2,1/(E61:I61<>""),E61:I61)) | L61: =IF(J61="","",ROUND(J61*RESUMEN!$B$4,0)) | M61: =COUNT(E61:I61)
A62: 679be962d942d | B62: HOODIE C WHITE | C62: L | I62: 27 | J62: =IF(COUNT(E62:I62)=0,"",MIN(E62:I62)) | K62: =IF(COUNT(E62:I62)=0,"",LOOKUP(2,1/(E62:I62<>""),E62:I62)) | L62: =IF(J62="","",ROUND(J62*RESUMEN!$B$4,0)) | M62: =COUNT(E62:I62)
A63: 42556129345676 | B63: HOODIE C WHITE | C63: M | D63: Cotton | G63: 27 | J63: =IF(COUNT(E63:I63)=0,"",MIN(E63:I63)) | K63: =IF(COUNT(E63:I63)=0,"",LOOKUP(2,1/(E63:I63<>""),E63:I63)) | L63: =IF(J63="","",ROUND(J63*RESUMEN!$B$4,0)) | M63: =COUNT(E63:I63)
A64: ⚠️ 25 | B64: KX331782 white-3 nude-2 black-5 | E64: 46 | J64: =IF(COUNT(E64:I64)=0,"",MIN(E64:I64)) | K64: =IF(COUNT(E64:I64)=0,"",LOOKUP(2,1/(E64:I64<>""),E64:I64)) | L64: =IF(J64="","",ROUND(J64*RESUMEN!$B$4,0)) | M64: =COUNT(E64:I64)
A65: ⚠️ 24 | B65: M62650 | F65: 13 | J65: =IF(COUNT(E65:I65)=0,"",MIN(E65:I65)) | K65: =IF(COUNT(E65:I65)=0,"",LOOKUP(2,1/(E65:I65<>""),E65:I65)) | L65: =IF(J65="","",ROUND(J65*RESUMEN!$B$4,0)) | M65: =COUNT(E65:I65)
A66: 94956734303628 | B66: MONEDERO LV | C66: 15.5cm de largo x 11cm de alto | H66: 13 | I66: 13 | J66: =IF(COUNT(E66:I66)=0,"",MIN(E66:I66)) | K66: =IF(COUNT(E66:I66)=0,"",LOOKUP(2,1/(E66:I66<>""),E66:I66)) | L66: =IF(J66="","",ROUND(J66*RESUMEN!$B$4,0)) | M66: =COUNT(E66:I66)
A67: 654bdadbcb222 | B67: PULSERA CD DE TELA BABY PINK | C67: 15cm con extensión de 5cm | H67: 4 | I67: 4 | J67: =IF(COUNT(E67:I67)=0,"",MIN(E67:I67)) | K67: =IF(COUNT(E67:I67)=0,"",LOOKUP(2,1/(E67:I67<>""),E67:I67)) | L67: =IF(J67="","",ROUND(J67*RESUMEN!$B$4,0)) | M67: =COUNT(E67:I67)
A68: 648cc5c47664a | B68: PULSERA CD DE TELA BEIGE | C68: 15cm con extensión de 5cm | H68: 4 | I68: 4 | J68: =IF(COUNT(E68:I68)=0,"",MIN(E68:I68)) | K68: =IF(COUNT(E68:I68)=0,"",LOOKUP(2,1/(E68:I68<>""),E68:I68)) | L68: =IF(J68="","",ROUND(J68*RESUMEN!$B$4,0)) | M68: =COUNT(E68:I68)
A69: 648cc5c57f64d | B69: PULSERA CD DE TELA DARK BLUE | C69: 15cm con extensión de 5cm | H69: 4 | J69: =IF(COUNT(E69:I69)=0,"",MIN(E69:I69)) | K69: =IF(COUNT(E69:I69)=0,"",LOOKUP(2,1/(E69:I69<>""),E69:I69)) | L69: =IF(J69="","",ROUND(J69*RESUMEN!$B$4,0)) | M69: =COUNT(E69:I69)
A70: 648cc5f7495e2 | B70: PULSERA CD DE TELA PINK | C70: 15cm con extensión de 5cm | I70: 4 | J70: =IF(COUNT(E70:I70)=0,"",MIN(E70:I70)) | K70: =IF(COUNT(E70:I70)=0,"",LOOKUP(2,1/(E70:I70<>""),E70:I70)) | L70: =IF(J70="","",ROUND(J70*RESUMEN!$B$4,0)) | M70: =COUNT(E70:I70)
A71: 10132411046285 | B71: SANDALIAS CD DIORACT BLACK | C71: 38/25mx | I71: 35 | J71: =IF(COUNT(E71:I71)=0,"",MIN(E71:I71)) | K71: =IF(COUNT(E71:I71)=0,"",LOOKUP(2,1/(E71:I71<>""),E71:I71)) | L71: =IF(J71="","",ROUND(J71*RESUMEN!$B$4,0)) | M71: =COUNT(E71:I71)
A72: 85367151541677 | B72: TARJETERO C LOGO | C72: BLACK/GOLD | H72: 12 | J72: =IF(COUNT(E72:I72)=0,"",MIN(E72:I72)) | K72: =IF(COUNT(E72:I72)=0,"",LOOKUP(2,1/(E72:I72<>""),E72:I72)) | L72: =IF(J72="","",ROUND(J72*RESUMEN!$B$4,0)) | M72: =COUNT(E72:I72)
A73: 85367151913997 | B73: TARJETERO CC JOLIE BLACK | C73: BLACK/GOLD | H73: 15 | J73: =IF(COUNT(E73:I73)=0,"",MIN(E73:I73)) | K73: =IF(COUNT(E73:I73)=0,"",LOOKUP(2,1/(E73:I73<>""),E73:I73)) | L73: =IF(J73="","",ROUND(J73*RESUMEN!$B$4,0)) | M73: =COUNT(E73:I73)
A74: 665bd49b4a58a | B74: TARJETERO LV BLUE | C74: 8cm x 11cm | D74: Micro fiber leat | G74: 17 | J74: =IF(COUNT(E74:I74)=0,"",MIN(E74:I74)) | K74: =IF(COUNT(E74:I74)=0,"",LOOKUP(2,1/(E74:I74<>""),E74:I74)) | L74: =IF(J74="","",ROUND(J74*RESUMEN!$B$4,0)) | M74: =COUNT(E74:I74)
A75: 665bd4a0c3b63 | B75: TARJETERO LV BROWN | C75: 8cm x 11cm | D75: Micro fiber leat | G75: 17 | J75: =IF(COUNT(E75:I75)=0,"",MIN(E75:I75)) | K75: =IF(COUNT(E75:I75)=0,"",LOOKUP(2,1/(E75:I75<>""),E75:I75)) | L75: =IF(J75="","",ROUND(J75*RESUMEN!$B$4,0)) | M75: =COUNT(E75:I75)
A76: 71326661043149 | B76: TRAJE DE BAÑO COMPLETO F LOGOS | C76: BROWN-M | H76: 22 | J76: =IF(COUNT(E76:I76)=0,"",MIN(E76:I76)) | K76: =IF(COUNT(E76:I76)=0,"",LOOKUP(2,1/(E76:I76<>""),E76:I76)) | L76: =IF(J76="","",ROUND(J76*RESUMEN!$B$4,0)) | M76: =COUNT(E76:I76)
A77: 70937181082701 | B77: TRAJE DE BAÑO GC ASIMETRICO | C77: BROWN-M | H77: 17.5 | J77: =IF(COUNT(E77:I77)=0,"",MIN(E77:I77)) | K77: =IF(COUNT(E77:I77)=0,"",LOOKUP(2,1/(E77:I77<>""),E77:I77)) | L77: =IF(J77="","",ROUND(J77*RESUMEN!$B$4,0)) | M77: =COUNT(E77:I77)
A78: ⚠️ 26 | B78: WL超纤657228 black-3 white-3 khaki-2 | E78: 46 | J78: =IF(COUNT(E78:I78)=0,"",MIN(E78:I78)) | K78: =IF(COUNT(E78:I78)=0,"",LOOKUP(2,1/(E78:I78<>""),E78:I78)) | L78: =IF(J78="","",ROUND(J78*RESUMEN!$B$4,0)) | M78: =COUNT(E78:I78)
A79: ⚠️ 13 | B79: black | E79: 43 | J79: =IF(COUNT(E79:I79)=0,"",MIN(E79:I79)) | K79: =IF(COUNT(E79:I79)=0,"",LOOKUP(2,1/(E79:I79<>""),E79:I79)) | L79: =IF(J79="","",ROUND(J79*RESUMEN!$B$4,0)) | M79: =COUNT(E79:I79)
A80: ⚠️ 16 | B80: black | E80: 21 | J80: =IF(COUNT(E80:I80)=0,"",MIN(E80:I80)) | K80: =IF(COUNT(E80:I80)=0,"",LOOKUP(2,1/(E80:I80<>""),E80:I80)) | L80: =IF(J80="","",ROUND(J80*RESUMEN!$B$4,0)) | M80: =COUNT(E80:I80)
A81: ⚠️ 20 | B81: black- 10 beige-6 | E81: 9 | J81: =IF(COUNT(E81:I81)=0,"",MIN(E81:I81)) | K81: =IF(COUNT(E81:I81)=0,"",LOOKUP(2,1/(E81:I81<>""),E81:I81)) | L81: =IF(J81="","",ROUND(J81*RESUMEN!$B$4,0)) | M81: =COUNT(E81:I81)
A82: ⚠️ 19 | B82: black-10 white-5 | E82: 11 | J82: =IF(COUNT(E82:I82)=0,"",MIN(E82:I82)) | K82: =IF(COUNT(E82:I82)=0,"",LOOKUP(2,1/(E82:I82<>""),E82:I82)) | L82: =IF(J82="","",ROUND(J82*RESUMEN!$B$4,0)) | M82: =COUNT(E82:I82)
A83: ⚠️ 11 | B83: brown | F83: 22 | J83: =IF(COUNT(E83:I83)=0,"",MIN(E83:I83)) | K83: =IF(COUNT(E83:I83)=0,"",LOOKUP(2,1/(E83:I83<>""),E83:I83)) | L83: =IF(J83="","",ROUND(J83*RESUMEN!$B$4,0)) | M83: =COUNT(E83:I83)
A84: ⚠️ 12 | B84: brown | F84: 39 | J84: =IF(COUNT(E84:I84)=0,"",MIN(E84:I84)) | K84: =IF(COUNT(E84:I84)=0,"",LOOKUP(2,1/(E84:I84<>""),E84:I84)) | L84: =IF(J84="","",ROUND(J84*RESUMEN!$B$4,0)) | M84: =COUNT(E84:I84)
A85: ⚠️ 15 | B85: pink-3 black-5 | F85: 20 | J85: =IF(COUNT(E85:I85)=0,"",MIN(E85:I85)) | K85: =IF(COUNT(E85:I85)=0,"",LOOKUP(2,1/(E85:I85<>""),E85:I85)) | L85: =IF(J85="","",ROUND(J85*RESUMEN!$B$4,0)) | M85: =COUNT(E85:I85)
A86: ⚠️ 10 | B86: silver | F86: 2.79 | J86: =IF(COUNT(E86:I86)=0,"",MIN(E86:I86)) | K86: =IF(COUNT(E86:I86)=0,"",LOOKUP(2,1/(E86:I86<>""),E86:I86)) | L86: =IF(J86="","",ROUND(J86*RESUMEN!$B$4,0)) | M86: =COUNT(E86:I86)
A87: ⚠️ 18 | B87: silver-10 gold-5 | F87: 12 | J87: =IF(COUNT(E87:I87)=0,"",MIN(E87:I87)) | K87: =IF(COUNT(E87:I87)=0,"",LOOKUP(2,1/(E87:I87<>""),E87:I87)) | L87: =IF(J87="","",ROUND(J87*RESUMEN!$B$4,0)) | M87: =COUNT(E87:I87)
A88: ⚠️ 22 | B88: white M-6 L-3 black M-8 L-5 | E88: 27 | J88: =IF(COUNT(E88:I88)=0,"",MIN(E88:I88)) | K88: =IF(COUNT(E88:I88)=0,"",LOOKUP(2,1/(E88:I88<>""),E88:I88)) | L88: =IF(J88="","",ROUND(J88*RESUMEN!$B$4,0)) | M88: =COUNT(E88:I88)
A89: ⚠️ 14 | B89: wine red | E89: 20 | J89: =IF(COUNT(E89:I89)=0,"",MIN(E89:I89)) | K89: =IF(COUNT(E89:I89)=0,"",LOOKUP(2,1/(E89:I89<>""),E89:I89)) | L89: =IF(J89="","",ROUND(J89*RESUMEN!$B$4,0)) | M89: =COUNT(E89:I89)

Sheet COCOMA
A1: HISTORIAL DE PRECIOS — COCOMA
A2: 2 orden(es) · costo unitario en USD · MXN = MEJOR × RESUMEN!B4 · * = dato del historial previo
A4: SKU | B4: PRODUCTO | C4: VARIANTE | D4: MATERIAL | E4: May 2025 01/05 | F4: Ene 2026 20/01 | G4: MEJOR (US) | H4: ÚLTIMA (US) | I4: MXN (mejor×TC) | J4: # ÓRD.
A5: 654bd7ac2dee3 | B5: ANILLO BV 3 OROS | C5: 5 | E5: 4.08 | F5: 4.08 | G5: =IF(COUNT(E5:F5)=0,"",MIN(E5:F5)) | H5: =IF(COUNT(E5:F5)=0,"",LOOKUP(2,1/(E5:F5<>""),E5:F5)) | I5: =IF(G5="","",ROUND(G5*RESUMEN!$B$4,0)) | J5: =COUNT(E5:F5)
A6: 64e78e797f140 | B6: ANILLO BV 3 OROS | C6: 6 | E6: 4.08 | F6: 4.08 | G6: =IF(COUNT(E6:F6)=0,"",MIN(E6:F6)) | H6: =IF(COUNT(E6:F6)=0,"",LOOKUP(2,1/(E6:F6<>""),E6:F6)) | I6: =IF(G6="","",ROUND(G6*RESUMEN!$B$4,0)) | J6: =COUNT(E6:F6)
A7: 64e78e7a486d9 | B7: ANILLO BV 3 OROS | C7: 7 | E7: 4.08 | F7: 4.08 | G7: =IF(COUNT(E7:F7)=0,"",MIN(E7:F7)) | H7: =IF(COUNT(E7:F7)=0,"",LOOKUP(2,1/(E7:F7<>""),E7:F7)) | I7: =IF(G7="","",ROUND(G7*RESUMEN!$B$4,0)) | J7: =COUNT(E7:F7)
A8: 64e78e7b03ab1 | B8: ANILLO BV 3 OROS | C8: 8 | E8: 4.08 | F8: 4.08 | G8: =IF(COUNT(E8:F8)=0,"",MIN(E8:F8)) | H8: =IF(COUNT(E8:F8)=0,"",LOOKUP(2,1/(E8:F8<>""),E8:F8)) | I8: =IF(G8="","",ROUND(G8*RESUMEN!$B$4,0)) | J8: =COUNT(E8:F8)
A9: 64e78e7bb52a6 | B9: ANILLO BV 3 OROS | C9: 9 | E9: 4.08 | F9: 4.08 | G9: =IF(COUNT(E9:F9)=0,"",MIN(E9:F9)) | H9: =IF(COUNT(E9:F9)=0,"",LOOKUP(2,1/(E9:F9<>""),E9:F9)) | I9: =IF(G9="","",ROUND(G9*RESUMEN!$B$4,0)) | J9: =COUNT(E9:F9)
A10: 2653039501964 | B10: ANILLO BV GOLD | C10: 10 | E10: 4.06 | F10: 4.3 | G10: =IF(COUNT(E10:F10)=0,"",MIN(E10:F10)) | H10: =IF(COUNT(E10:F10)=0,"",LOOKUP(2,1/(E10:F10<>""),E10:F10)) | I10: =IF(G10="","",ROUND(G10*RESUMEN!$B$4,0)) | J10: =COUNT(E10:F10)
A11: 2653039534732 | B11: ANILLO BV GOLD | C11: 11 | F11: 4.3 | G11: =IF(COUNT(E11:F11)=0,"",MIN(E11:F11)) | H11: =IF(COUNT(E11:F11)=0,"",LOOKUP(2,1/(E11:F11<>""),E11:F11)) | I11: =IF(G11="","",ROUND(G11*RESUMEN!$B$4,0)) | J11: =COUNT(E11:F11)
A12: 2653039567500 | B12: ANILLO BV GOLD | C12: 12 | F12: 4.3 | G12: =IF(COUNT(E12:F12)=0,"",MIN(E12:F12)) | H12: =IF(COUNT(E12:F12)=0,"",LOOKUP(2,1/(E12:F12<>""),E12:F12)) | I12: =IF(G12="","",ROUND(G12*RESUMEN!$B$4,0)) | J12: =COUNT(E12:F12)
A13: 2653039338124 | B13: ANILLO BV GOLD | C13: 5 | F13: 4.3 | G13: =IF(COUNT(E13:F13)=0,"",MIN(E13:F13)) | H13: =IF(COUNT(E13:F13)=0,"",LOOKUP(2,1/(E13:F13<>""),E13:F13)) | I13: =IF(G13="","",ROUND(G13*RESUMEN!$B$4,0)) | J13: =COUNT(E13:F13)
A14: 2653039370892 | B14: ANILLO BV GOLD | C14: 6 | E14: 4.06 | F14: 4.3 | G14: =IF(COUNT(E14:F14)=0,"",MIN(E14:F14)) | H14: =IF(COUNT(E14:F14)=0,"",LOOKUP(2,1/(E14:F14<>""),E14:F14)) | I14: =IF(G14="","",ROUND(G14*RESUMEN!$B$4,0)) | J14: =COUNT(E14:F14)
A15: 2653039403660 | B15: ANILLO BV GOLD | C15: 7 | E15: 4.06 | F15: 4.3 | G15: =IF(COUNT(E15:F15)=0,"",MIN(E15:F15)) | H15: =IF(COUNT(E15:F15)=0,"",LOOKUP(2,1/(E15:F15<>""),E15:F15)) | I15: =IF(G15="","",ROUND(G15*RESUMEN!$B$4,0)) | J15: =COUNT(E15:F15)
A16: 2653039436428 | B16: ANILLO BV GOLD | C16: 8 | E16: 4.06 | F16: 4.3 | G16: =IF(COUNT(E16:F16)=0,"",MIN(E16:F16)) | H16: =IF(COUNT(E16:F16)=0,"",LOOKUP(2,1/(E16:F16<>""),E16:F16)) | I16: =IF(G16="","",ROUND(G16*RESUMEN!$B$4,0)) | J16: =COUNT(E16:F16)
A17: 2653039469196 | B17: ANILLO BV GOLD | C17: 9 | F17: 4.3 | G17: =IF(COUNT(E17:F17)=0,"",MIN(E17:F17)) | H17: =IF(COUNT(E17:F17)=0,"",LOOKUP(2,1/(E17:F17<>""),E17:F17)) | I17: =IF(G17="","",ROUND(G17*RESUMEN!$B$4,0)) | J17: =COUNT(E17:F17)
A18: 63e0b1e6f022f | B18: ANILLO BV GOLD DELGADO | C18: 10 | F18: 7.89 | G18: =IF(COUNT(E18:F18)=0,"",MIN(E18:F18)) | H18: =IF(COUNT(E18:F18)=0,"",LOOKUP(2,1/(E18:F18<>""),E18:F18)) | I18: =IF(G18="","",ROUND(G18*RESUMEN!$B$4,0)) | J18: =COUNT(E18:F18)
A19: 63e0b1e3636a9 | B19: ANILLO BV GOLD DELGADO | C19: 6 | E19: 7.89 | G19: =IF(COUNT(E19:F19)=0,"",MIN(E19:F19)) | H19: =IF(COUNT(E19:F19)=0,"",LOOKUP(2,1/(E19:F19<>""),E19:F19)) | I19: =IF(G19="","",ROUND(G19*RESUMEN!$B$4,0)) | J19: =COUNT(E19:F19)
A20: 63e0b1e45372f | B20: ANILLO BV GOLD DELGADO | C20: 7 HIGH QUALITY | E20: 7.89 | F20: 7.89 | G20: =IF(COUNT(E20:F20)=0,"",MIN(E20:F20)) | H20: =IF(COUNT(E20:F20)=0,"",LOOKUP(2,1/(E20:F20<>""),E20:F20)) | I20: =IF(G20="","",ROUND(G20*RESUMEN!$B$4,0)) | J20: =COUNT(E20:F20)
A21: 63e0b1e52d057 | B21: ANILLO BV GOLD DELGADO | C21: 8 HIGH QUALITY | F21: 7.89 | G21: =IF(COUNT(E21:F21)=0,"",MIN(E21:F21)) | H21: =IF(COUNT(E21:F21)=0,"",LOOKUP(2,1/(E21:F21<>""),E21:F21)) | I21: =IF(G21="","",ROUND(G21*RESUMEN!$B$4,0)) | J21: =COUNT(E21:F21)
A22: 63e0b1e70453e | B22: ANILLO BV ROSE GOLD | C22: 10 | F22: 4.3 | G22: =IF(COUNT(E22:F22)=0,"",MIN(E22:F22)) | H22: =IF(COUNT(E22:F22)=0,"",LOOKUP(2,1/(E22:F22<>""),E22:F22)) | I22: =IF(G22="","",ROUND(G22*RESUMEN!$B$4,0)) | J22: =COUNT(E22:F22)
A23: 63e0b1e29450b | B23: ANILLO BV ROSE GOLD | C23: 5 | F23: 4.3 | G23: =IF(COUNT(E23:F23)=0,"",MIN(E23:F23)) | H23: =IF(COUNT(E23:F23)=0,"",LOOKUP(2,1/(E23:F23<>""),E23:F23)) | I23: =IF(G23="","",ROUND(G23*RESUMEN!$B$4,0)) | J23: =COUNT(E23:F23)
A24: 63e0b1e36f7c6 | B24: ANILLO BV ROSE GOLD | C24: 6 | F24: 4.3 | G24: =IF(COUNT(E24:F24)=0,"",MIN(E24:F24)) | H24: =IF(COUNT(E24:F24)=0,"",LOOKUP(2,1/(E24:F24<>""),E24:F24)) | I24: =IF(G24="","",ROUND(G24*RESUMEN!$B$4,0)) | J24: =COUNT(E24:F24)
A25: 63e0b1e44c6d7 | B25: ANILLO BV ROSE GOLD | C25: 7 | F25: 4.3 | G25: =IF(COUNT(E25:F25)=0,"",MIN(E25:F25)) | H25: =IF(COUNT(E25:F25)=0,"",LOOKUP(2,1/(E25:F25<>""),E25:F25)) | I25: =IF(G25="","",ROUND(G25*RESUMEN!$B$4,0)) | J25: =COUNT(E25:F25)
A26: 63e0b1e537df8 | B26: ANILLO BV ROSE GOLD | C26: 8 | F26: 4.3 | G26: =IF(COUNT(E26:F26)=0,"",MIN(E26:F26)) | H26: =IF(COUNT(E26:F26)=0,"",LOOKUP(2,1/(E26:F26<>""),E26:F26)) | I26: =IF(G26="","",ROUND(G26*RESUMEN!$B$4,0)) | J26: =COUNT(E26:F26)
A27: 63e0b1e628eb5 | B27: ANILLO BV ROSE GOLD | C27: 9 | F27: 4.3 | G27: =IF(COUNT(E27:F27)=0,"",MIN(E27:F27)) | H27: =IF(COUNT(E27:F27)=0,"",LOOKUP(2,1/(E27:F27<>""),E27:F27)) | I27: =IF(G27="","",ROUND(G27*RESUMEN!$B$4,0)) | J27: =COUNT(E27:F27)
A28: 63e0b1e2d5f1e | B28: ANILLO BV ROSE GOLD DELGADO | C28: 5 | F28: 7.89 | G28: =IF(COUNT(E28:F28)=0,"",MIN(E28:F28)) | H28: =IF(COUNT(E28:F28)=0,"",LOOKUP(2,1/(E28:F28<>""),E28:F28)) | I28: =IF(G28="","",ROUND(G28*RESUMEN!$B$4,0)) | J28: =COUNT(E28:F28)
A29: 63e0b1e3b4fa0 | B29: ANILLO BV ROSE GOLD DELGADO | C29: 6 | F29: 7.89 | G29: =IF(COUNT(E29:F29)=0,"",MIN(E29:F29)) | H29: =IF(COUNT(E29:F29)=0,"",LOOKUP(2,1/(E29:F29<>""),E29:F29)) | I29: =IF(G29="","",ROUND(G29*RESUMEN!$B$4,0)) | J29: =COUNT(E29:F29)
A30: 63e0b1e49258e | B30: ANILLO BV ROSE GOLD DELGADO | C30: 7 | F30: 7.89 | G30: =IF(COUNT(E30:F30)=0,"",MIN(E30:F30)) | H30: =IF(COUNT(E30:F30)=0,"",LOOKUP(2,1/(E30:F30<>""),E30:F30)) | I30: =IF(G30="","",ROUND(G30*RESUMEN!$B$4,0)) | J30: =COUNT(E30:F30)
A31: 63e0b1e577108 | B31: ANILLO BV ROSE GOLD DELGADO | C31: 8 | F31: 7.89 | G31: =IF(COUNT(E31:F31)=0,"",MIN(E31:F31)) | H31: =IF(COUNT(E31:F31)=0,"",LOOKUP(2,1/(E31:F31<>""),E31:F31)) | I31: =IF(G31="","",ROUND(G31*RESUMEN!$B$4,0)) | J31: =COUNT(E31:F31)
A32: 63e0b1e659918 | B32: ANILLO BV ROSE GOLD DELGADO | C32: 9 | F32: 7.89 | G32: =IF(COUNT(E32:F32)=0,"",MIN(E32:F32)) | H32: =IF(COUNT(E32:F32)=0,"",LOOKUP(2,1/(E32:F32<>""),E32:F32)) | I32: =IF(G32="","",ROUND(G32*RESUMEN!$B$4,0)) | J32: =COUNT(E32:F32)
A33: 63e0b1fbdf1a6 | B33: ANILLO BV SILVER | C33: 10 | E33: 4.06 | F33: 4.06 | G33: =IF(COUNT(E33:F33)=0,"",MIN(E33:F33)) | H33: =IF(COUNT(E33:F33)=0,"",LOOKUP(2,1/(E33:F33<>""),E33:F33)) | I33: =IF(G33="","",ROUND(G33*RESUMEN!$B$4,0)) | J33: =COUNT(E33:F33)
A34: 63e0b1fcc7359 | B34: ANILLO BV SILVER | C34: 11 | E34: 4.06 | F34: 4.06 | G34: =IF(COUNT(E34:F34)=0,"",MIN(E34:F34)) | H34: =IF(COUNT(E34:F34)=0,"",LOOKUP(2,1/(E34:F34<>""),E34:F34)) | I34: =IF(G34="","",ROUND(G34*RESUMEN!$B$4,0)) | J34: =COUNT(E34:F34)
A35: 63e0b1fde9905 | B35: ANILLO BV SILVER | C35: 12 | E35: 4.06 | F35: 4.06 | G35: =IF(COUNT(E35:F35)=0,"",MIN(E35:F35)) | H35: =IF(COUNT(E35:F35)=0,"",LOOKUP(2,1/(E35:F35<>""),E35:F35)) | I35: =IF(G35="","",ROUND(G35*RESUMEN!$B$4,0)) | J35: =COUNT(E35:F35)
A36: 63e0b1f7d50b1 | B36: ANILLO BV SILVER | C36: 6 | F36: 4.06 | G36: =IF(COUNT(E36:F36)=0,"",MIN(E36:F36)) | H36: =IF(COUNT(E36:F36)=0,"",LOOKUP(2,1/(E36:F36<>""),E36:F36)) | I36: =IF(G36="","",ROUND(G36*RESUMEN!$B$4,0)) | J36: =COUNT(E36:F36)
A37: 63e0b1f8bb7d5 | B37: ANILLO BV SILVER | C37: 7 | E37: 4.06 | F37: 4.06 | G37: =IF(COUNT(E37:F37)=0,"",MIN(E37:F37)) | H37: =IF(COUNT(E37:F37)=0,"",LOOKUP(2,1/(E37:F37<>""),E37:F37)) | I37: =IF(G37="","",ROUND(G37*RESUMEN!$B$4,0)) | J37: =COUNT(E37:F37)
A38: 63e0b1f9a5ac2 | B38: ANILLO BV SILVER | C38: 8 | E38: 4.06 | F38: 4.06 | G38: =IF(COUNT(E38:F38)=0,"",MIN(E38:F38)) | H38: =IF(COUNT(E38:F38)=0,"",LOOKUP(2,1/(E38:F38<>""),E38:F38)) | I38: =IF(G38="","",ROUND(G38*RESUMEN!$B$4,0)) | J38: =COUNT(E38:F38)
A39: 63e0b1fa92d45 | B39: ANILLO BV SILVER | C39: 9 | F39: 4.06 | G39: =IF(COUNT(E39:F39)=0,"",MIN(E39:F39)) | H39: =IF(COUNT(E39:F39)=0,"",LOOKUP(2,1/(E39:F39<>""),E39:F39)) | I39: =IF(G39="","",ROUND(G39*RESUMEN!$B$4,0)) | J39: =COUNT(E39:F39)
A40: 63e0b1fd046c4 | B40: ANILLO BV SILVER DELGADO | C40: 10 | F40: 7.89 | G40: =IF(COUNT(E40:F40)=0,"",MIN(E40:F40)) | H40: =IF(COUNT(E40:F40)=0,"",LOOKUP(2,1/(E40:F40<>""),E40:F40)) | I40: =IF(G40="","",ROUND(G40*RESUMEN!$B$4,0)) | J40: =COUNT(E40:F40)
A41: 63e0b1f91d20d | B41: ANILLO BV SILVER DELGADO | C41: 6 | F41: 7.89 | G41: =IF(COUNT(E41:F41)=0,"",MIN(E41:F41)) | H41: =IF(COUNT(E41:F41)=0,"",LOOKUP(2,1/(E41:F41<>""),E41:F41)) | I41: =IF(G41="","",ROUND(G41*RESUMEN!$B$4,0)) | J41: =COUNT(E41:F41)
A42: 63e0b1fa23537 | B42: ANILLO BV SILVER DELGADO | C42: 7 | F42: 7.89 | G42: =IF(COUNT(E42:F42)=0,"",MIN(E42:F42)) | H42: =IF(COUNT(E42:F42)=0,"",LOOKUP(2,1/(E42:F42<>""),E42:F42)) | I42: =IF(G42="","",ROUND(G42*RESUMEN!$B$4,0)) | J42: =COUNT(E42:F42)
A43: 63e0b1fb11aa3 | B43: ANILLO BV SILVER DELGADO | C43: 8 | F43: 7.89 | G43: =IF(COUNT(E43:F43)=0,"",MIN(E43:F43)) | H43: =IF(COUNT(E43:F43)=0,"",LOOKUP(2,1/(E43:F43<>""),E43:F43)) | I43: =IF(G43="","",ROUND(G43*RESUMEN!$B$4,0)) | J43: =COUNT(E43:F43)
A44: 63e0b1fc15c01 | B44: ANILLO BV SILVER DELGADO | C44: 9 | F44: 7.89 | G44: =IF(COUNT(E44:F44)=0,"",MIN(E44:F44)) | H44: =IF(COUNT(E44:F44)=0,"",LOOKUP(2,1/(E44:F44<>""),E44:F44)) | I44: =IF(G44="","",ROUND(G44*RESUMEN!$B$4,0)) | J44: =COUNT(E44:F44)
A45: 63ebd81634b8a | B45: ARETES CC GOLD CON ZIRCONIA | C45: Default Title | F45: 4.18 | G45: =IF(COUNT(E45:F45)=0,"",MIN(E45:F45)) | H45: =IF(COUNT(E45:F45)=0,"",LOOKUP(2,1/(E45:F45<>""),E45:F45)) | I45: =IF(G45="","",ROUND(G45*RESUMEN!$B$4,0)) | J45: =COUNT(E45:F45)
A46: 63e0bb0b18c6d | B46: ARETES GC ZIRCONIA | C46: Default Title | F46: 3.46 | G46: =IF(COUNT(E46:F46)=0,"",MIN(E46:F46)) | H46: =IF(COUNT(E46:F46)=0,"",LOOKUP(2,1/(E46:F46<>""),E46:F46)) | I46: =IF(G46="","",ROUND(G46*RESUMEN!$B$4,0)) | J46: =COUNT(E46:F46)
A47: 646f84c070459 | B47: ARETES LV COLGANTE | C47: Regular | F47: 3.7 | G47: =IF(COUNT(E47:F47)=0,"",MIN(E47:F47)) | H47: =IF(COUNT(E47:F47)=0,"",LOOKUP(2,1/(E47:F47<>""),E47:F47)) | I47: =IF(G47="","",ROUND(G47*RESUMEN!$B$4,0)) | J47: =COUNT(E47:F47)
A48: 646f84bcb068f | B48: ARETES T GOLD | C48: Default Title | E48: 3.7 | F48: 3.7 | G48: =IF(COUNT(E48:F48)=0,"",MIN(E48:F48)) | H48: =IF(COUNT(E48:F48)=0,"",LOOKUP(2,1/(E48:F48<>""),E48:F48)) | I48: =IF(G48="","",ROUND(G48*RESUMEN!$B$4,0)) | J48: =COUNT(E48:F48)
A49: 646f84b9b65ea | B49: ARETES T ROSE GOLD | C49: Default Title | F49: 3.7 | G49: =IF(COUNT(E49:F49)=0,"",MIN(E49:F49)) | H49: =IF(COUNT(E49:F49)=0,"",LOOKUP(2,1/(E49:F49<>""),E49:F49)) | I49: =IF(G49="","",ROUND(G49*RESUMEN!$B$4,0)) | J49: =COUNT(E49:F49)
A50: 646f84b99a256 | B50: ARETES T SILVER | C50: Default Title | E50: 3.7 | F50: 3.7 | G50: =IF(COUNT(E50:F50)=0,"",MIN(E50:F50)) | H50: =IF(COUNT(E50:F50)=0,"",LOOKUP(2,1/(E50:F50<>""),E50:F50)) | I50: =IF(G50="","",ROUND(G50*RESUMEN!$B$4,0)) | J50: =COUNT(E50:F50)
A51: 668eee4709a5f | B51: PULSERA DE CUENTAS CON INSIGNIA DE CORAZÓN ROSE GOLD | C51: 17 cm | E51: 4.42 | F51: 4.42 | G51: =IF(COUNT(E51:F51)=0,"",MIN(E51:F51)) | H51: =IF(COUNT(E51:F51)=0,"",LOOKUP(2,1/(E51:F51<>""),E51:F51)) | I51: =IF(G51="","",ROUND(G51*RESUMEN!$B$4,0)) | J51: =COUNT(E51:F51)
A52: 43047221198988 | B52: PULSERA DE CUENTAS GOLD | C52: 16cm | E52: 4.42 | F52: 4.42 | G52: =IF(COUNT(E52:F52)=0,"",MIN(E52:F52)) | H52: =IF(COUNT(E52:F52)=0,"",LOOKUP(2,1/(E52:F52<>""),E52:F52)) | I52: =IF(G52="","",ROUND(G52*RESUMEN!$B$4,0)) | J52: =COUNT(E52:F52)
A53: 43047209828492 | B53: PULSERA DE CUENTAS GOLD CON INSIGNIA DE CORAZÓN BLUE | C53: 16cm | E53: 4.66 | F53: 4.66 | G53: =IF(COUNT(E53:F53)=0,"",MIN(E53:F53)) | H53: =IF(COUNT(E53:F53)=0,"",LOOKUP(2,1/(E53:F53<>""),E53:F53)) | I53: =IF(G53="","",ROUND(G53*RESUMEN!$B$4,0)) | J53: =COUNT(E53:F53)
A54: 43047210680460 | B54: PULSERA DE CUENTAS GOLD CON INSIGNIA DE CORAZÓN RED | C54: 16cm | E54: 4.66 | F54: 4.66 | G54: =IF(COUNT(E54:F54)=0,"",MIN(E54:F54)) | H54: =IF(COUNT(E54:F54)=0,"",LOOKUP(2,1/(E54:F54<>""),E54:F54)) | I54: =IF(G54="","",ROUND(G54*RESUMEN!$B$4,0)) | J54: =COUNT(E54:F54)
A55: 43728095967788 | B55: PULSERA DOBLE STAR CD | C55: 16cm con extensión de 5cm | E55: 3.98 | F55: 3.98 | G55: =IF(COUNT(E55:F55)=0,"",MIN(E55:F55)) | H55: =IF(COUNT(E55:F55)=0,"",LOOKUP(2,1/(E55:F55<>""),E55:F55)) | I55: =IF(G55="","",ROUND(G55*RESUMEN!$B$4,0)) | J55: =COUNT(E55:F55)

Sheet MOLLY
A1: HISTORIAL DE PRECIOS — MOLLY
A2: 1 orden(es) · costo unitario en USD · MXN = MEJOR × RESUMEN!B4 · * = dato del historial previo
A4: SKU | B4: PRODUCTO | C4: VARIANTE | D4: MATERIAL | E4: Oct 2025 10/10 | F4: MEJOR (US) | G4: ÚLTIMA (US) | H4: MXN (mejor×TC) | I4: # ÓRD.
A5: 85887251053901 | B5: ABRIGO CAQUI JW | C5: M | E5: 7.9 | F5: =IF(COUNT(E5:E5)=0,"",MIN(E5:E5)) | G5: =IF(COUNT(E5:E5)=0,"",LOOKUP(2,1/(E5:E5<>""),E5:E5)) | H5: =IF(F5="","",ROUND(F5*RESUMEN!$B$4,0)) | I5: =COUNT(E5:E5)
A6: 85887251172013 | B6: ABRIGO WHITE JW | C6: M | E6: 14.8 | F6: =IF(COUNT(E6:E6)=0,"",MIN(E6:E6)) | G6: =IF(COUNT(E6:E6)=0,"",LOOKUP(2,1/(E6:E6<>""),E6:E6)) | H6: =IF(F6="","",ROUND(F6*RESUMEN!$B$4,0)) | I6: =COUNT(E6:E6)
A7: 85887251265229 | B7: ABRIGO WHITE-BLACK JW | C7: S | E7: 5.12 | F7: =IF(COUNT(E7:E7)=0,"",MIN(E7:E7)) | G7: =IF(COUNT(E7:E7)=0,"",LOOKUP(2,1/(E7:E7<>""),E7:E7)) | H7: =IF(F7="","",ROUND(F7*RESUMEN!$B$4,0)) | I7: =COUNT(E7:E7)
A8: 85887252613805 | B8: BLAZER BLACK FEATHERS JW | C8: M | E8: 20 | F8: =IF(COUNT(E8:E8)=0,"",MIN(E8:E8)) | G8: =IF(COUNT(E8:E8)=0,"",LOOKUP(2,1/(E8:E8<>""),E8:E8)) | H8: =IF(F8="","",ROUND(F8*RESUMEN!$B$4,0)) | I8: =COUNT(E8:E8)
A9: 85887252823437 | B9: BLUSA WHITE-BLACK JW | C9: M | E9: 10.9 | F9: =IF(COUNT(E9:E9)=0,"",MIN(E9:E9)) | G9: =IF(COUNT(E9:E9)=0,"",LOOKUP(2,1/(E9:E9<>""),E9:E9)) | H9: =IF(F9="","",ROUND(F9*RESUMEN!$B$4,0)) | I9: =COUNT(E9:E9)
A10: 85887251827853 | B10: CAMISETA BLUE JW | C10: L | E10: 14.2 | F10: =IF(COUNT(E10:E10)=0,"",MIN(E10:E10)) | G10: =IF(COUNT(E10:E10)=0,"",LOOKUP(2,1/(E10:E10<>""),E10:E10)) | H10: =IF(F10="","",ROUND(F10*RESUMEN!$B$4,0)) | I10: =COUNT(E10:E10)
A11: 85887251787565 | B11: CAMISETA GREEN JW | C11: M | E11: 14.2 | F11: =IF(COUNT(E11:E11)=0,"",MIN(E11:E11)) | G11: =IF(COUNT(E11:E11)=0,"",LOOKUP(2,1/(E11:E11<>""),E11:E11)) | H11: =IF(F11="","",ROUND(F11*RESUMEN!$B$4,0)) | I11: =COUNT(E11:E11)
A12: 85887251964013 | B12: CAMISETA WHITE JW | C12: M | E12: 14.2 | F12: =IF(COUNT(E12:E12)=0,"",MIN(E12:E12)) | G12: =IF(COUNT(E12:E12)=0,"",LOOKUP(2,1/(E12:E12<>""),E12:E12)) | H12: =IF(F12="","",ROUND(F12*RESUMEN!$B$4,0)) | I12: =COUNT(E12:E12)
A13: 85887252483277 | B13: CHAMARRA BLACK JW | C13: L | E13: 20.8 | F13: =IF(COUNT(E13:E13)=0,"",MIN(E13:E13)) | G13: =IF(COUNT(E13:E13)=0,"",LOOKUP(2,1/(E13:E13<>""),E13:E13)) | H13: =IF(F13="","",ROUND(F13*RESUMEN!$B$4,0)) | I13: =COUNT(E13:E13)
A14: 85887252725133 | B14: CONJUNTO WHITE CASHMERE | C14: M | E14: 16.9 | F14: =IF(COUNT(E14:E14)=0,"",MIN(E14:E14)) | G14: =IF(COUNT(E14:E14)=0,"",LOOKUP(2,1/(E14:E14<>""),E14:E14)) | H14: =IF(F14="","",ROUND(F14*RESUMEN!$B$4,0)) | I14: =COUNT(E14:E14)
A15: 85887251331053 | B15: SUDADERA ZIPPER BEIGE JW | C15: M | E15: 18.9 | F15: =IF(COUNT(E15:E15)=0,"",MIN(E15:E15)) | G15: =IF(COUNT(E15:E15)=0,"",LOOKUP(2,1/(E15:E15<>""),E15:E15)) | H15: =IF(F15="","",ROUND(F15*RESUMEN!$B$4,0)) | I15: =COUNT(E15:E15)
A16: 85887252087757 | B16: SUETER BONE JW | C16: L | E16: 17.5 | F16: =IF(COUNT(E16:E16)=0,"",MIN(E16:E16)) | G16: =IF(COUNT(E16:E16)=0,"",LOOKUP(2,1/(E16:E16<>""),E16:E16)) | H16: =IF(F16="","",ROUND(F16*RESUMEN!$B$4,0)) | I16: =COUNT(E16:E16)
... A23: 85887252345421 | B23: SUETER ZIPPER WHITE JW | C23: M | E23: 8.8 | F23: =IF(COUNT(E23:E23)=0,"",MIN(E23:E23)) | G23: =IF(COUNT(E23:E23)=0,"",LOOKUP(2,1/(E23:E23<>""),E23:E23)) | H23: =IF(F23="","",ROUND(F23*RESUMEN!$B$4,0)) | I23: =COUNT(E23:E23)

Sheet COCO ZHANG
A1: HISTORIAL DE PRECIOS — COCO ZHANG
A2: 1 orden(es) · costo unitario en USD · MXN = MEJOR × RESUMEN!B4 · * = dato del historial previo
A4: SKU | B4: PRODUCTO | C4: VARIANTE | D4: MATERIAL | E4: Feb 2026 16/02 | F4: MEJOR (US) | G4: ÚLTIMA (US) | H4: MXN (mejor×TC) | I4: # ÓRD.
A5: 26853592178861 | B5: GORRA 31 FOREVER BLACK | C5: Default Title | E5: 15 | F5: =IF(COUNT(E5:E5)=0,"",MIN(E5:E5)) | G5: =IF(COUNT(E5:E5)=0,"",LOOKUP(2,1/(E5:E5<>""),E5:E5)) | H5: =IF(F5="","",ROUND(F5*RESUMEN!$B$4,0)) | I5: =COUNT(E5:E5)
A6: 26853591980557 | B6: GORRA BARBAS B CHROME | C6: Default Title | E6: 15 | F6: =IF(COUNT(E6:E6)=0,"",MIN(E6:E6)) | G6: =IF(COUNT(E6:E6)=0,"",LOOKUP(2,1/(E6:E6<>""),E6:E6)) | H6: =IF(F6="","",ROUND(F6*RESUMEN!$B$4,0)) | I6: =COUNT(E6:E6)
A7: 26853591099213 | B7: GORRA BARBAS EL MAGO | C7: Default Title | E7: 15 | F7: =IF(COUNT(E7:E7)=0,"",MIN(E7:E7)) | G7: =IF(COUNT(E7:E7)=0,"",LOOKUP(2,1/(E7:E7<>""),E7:E7)) | H7: =IF(F7="","",ROUND(F7*RESUMEN!$B$4,0)) | I7: =COUNT(E7:E7)
A8: 26853591497517 | B8: GORRA DANDY ONYX | C8: Default Title | E8: 15 | F8: =IF(COUNT(E8:E8)=0,"",MIN(E8:E8)) | G8: =IF(COUNT(E8:E8)=0,"",LOOKUP(2,1/(E8:E8<>""),E8:E8)) | H8: =IF(F8="","",ROUND(F8*RESUMEN!$B$4,0)) | I8: =COUNT(E8:E8)
A9: 26853591721805 | B9: GORRA DANDY X JUNIOR CLAVE ALI | C9: Default Title | E9: 15 | F9: =IF(COUNT(E9:E9)=0,"",MIN(E9:E9)) | G9: =IF(COUNT(E9:E9)=0,"",LOOKUP(2,1/(E9:E9<>""),E9:E9)) | H9: =IF(F9="","",ROUND(F9*RESUMEN!$B$4,0)) | I9: =COUNT(E9:E9)
A10: 26853591657965 | B10: GORRA DANDY X JUNIOR EL AZUL | C10: Default Title | E10: 15 | F10: =IF(COUNT(E10:E10)=0,"",MIN(E10:E10)) | G10: =IF(COUNT(E10:E10)=0,"",LOOKUP(2,1/(E10:E10<>""),E10:E10)) | H10: =IF(F10="","",ROUND(F10*RESUMEN!$B$4,0)) | I10: =COUNT(E10:E10)
A11: 26853592046093 | B11: GORRA DANDY X LOST HILLS LH CHROME | C11: Default Title | E11: 15 | F11: =IF(COUNT(E11:E11)=0,"",MIN(E11:E11)) | G11: =IF(COUNT(E11:E11)=0,"",LOOKUP(2,1/(E11:E11<>""),E11:E11)) | H11: =IF(F11="","",ROUND(F11*RESUMEN!$B$4,0)) | I11: =COUNT(E11:E11)
A12: 26853592244397 | B12: GORRA EL BARBAS 77 | C12: Default Title | E12: 15 | F12: =IF(COUNT(E12:E12)=0,"",MIN(E12:E12)) | G12: =IF(COUNT(E12:E12)=0,"",LOOKUP(2,1/(E12:E12<>""),E12:E12)) | H12: =IF(F12="","",ROUND(F12*RESUMEN!$B$4,0)) | I12: =COUNT(E12:E12)
A13: 26853591330285 | B13: GORRA EL BARBAS CHROME | C13: Default Title | E13: 15 | F13: =IF(COUNT(E13:E13)=0,"",MIN(E13:E13)) | G13: =IF(COUNT(E13:E13)=0,"",LOOKUP(2,1/(E13:E13<>""),E13:E13)) | H13: =IF(F13="","",ROUND(F13*RESUMEN!$B$4,0)) | I13: =COUNT(E13:E13)
A14: 26853591295821 | B14: GORRA EL BARBAS CHROME X CT | C14: Default Title | E14: 15 | F14: =IF(COUNT(E14:E14)=0,"",MIN(E14:E14)) | G14: =IF(COUNT(E14:E14)=0,"",LOOKUP(2,1/(E14:E14<>""),E14:E14)) | H14: =IF(F14="","",ROUND(F14*RESUMEN!$B$4,0)) | I14: =COUNT(E14:E14)
A15: 26853591847789 | B15: GORRA EL BARBAS GALAXY | C15: Default Title | E15: 15 | F15: =IF(COUNT(E15:E15)=0,"",MIN(E15:E15)) | G15: =IF(COUNT(E15:E15)=0,"",LOOKUP(2,1/(E15:E15<>""),E15:E15)) | H15: =IF(F15="","",ROUND(F15*RESUMEN!$B$4,0)) | I15: =COUNT(E15:E15)
A16: 26853591559661 | B16: GORRA EL BARBAS X RICH THE KID STATE | C16: Default Title | E16: 15 | F16: =IF(COUNT(E16:E16)=0,"",MIN(E16:E16)) | G16: =IF(COUNT(E16:E16)=0,"",LOOKUP(2,1/(E16:E16<>""),E16:E16)) | H16: =IF(F16="","",ROUND(F16*RESUMEN!$B$4,0)) | I16: =COUNT(E16:E16)
A17: 26853591164749 | B17: GORRA THIRTY ONE FOREVER | C17: Default Title | E17: 15 | F17: =IF(COUNT(E17:E17)=0,"",MIN(E17:E17)) | G17: =IF(COUNT(E17:E17)=0,"",LOOKUP(2,1/(E17:E17<>""),E17:E17)) | H17: =IF(F17="","",ROUND(F17*RESUMEN!$B$4,0)) | I17: =COUNT(E17:E17)

Sheet TODAS LAS ORDENES
A1: PROVEEDOR | B1: ORDEN | C1: FECHA | D1: SKU | E1: PRODUCTO | F1: VARIANTE | G1: CANT. | H1: COSTO UNIT (US) | I1: COSTO UNIT TOTAL (MXN) | J1: ROAS 3 | K1: ROAS 3.5 | L1: ROAS 4 | M1: PRECIO VENTA (al ordenar)
A2: DINA DU | B2: ord.1046* | C2: 2024-12-01 | D2: ⚠️ 25 | E2: KX331782 white-3 nude-2 black-5 | H2: 46
A3: DINA DU | B3: ord.1046* | C3: 2024-12-01 | D3: ⚠️ 26 | E3: WL超纤657228 black-3 white-3 khaki-2 | H3: 46
A4: DINA DU | B4: ord.1046* | C4: 2024-12-01 | D4: ⚠️ 13 | E4: black | H4: 43
A5: DINA DU | B5: ord.1046* | C5: 2024-12-01 | D5: ⚠️ 16 | E5: black | H5: 21
A6: DINA DU | B6: ord.1046* | C6: 2024-12-01 | D6: ⚠️ 20 | E6: black- 10 beige-6 | H6: 9
A7: DINA DU | B7: ord.1046* | C7: 2024-12-01 | D7: ⚠️ 19 | E7: black-10 white-5 | H7: 11
A8: DINA DU | B8: ord.1046* | C8: 2024-12-01 | D8: ⚠️ 22 | E8: white M-6 L-3 black M-8 L-5 | H8: 27
A9: DINA DU | B9: ord.1046* | C9: 2024-12-01 | D9: ⚠️ 14 | E9: wine red | H9: 20
A10: DINA DU | B10: ord.1046* | C10: 2025-01-01 | D10: ⚠️ 17 | E10: 2-M | H10: 16
A11: DINA DU | B11: ord.1046* | C11: 2025-01-01 | D11: ⚠️ 24 | E11: M62650 | H11: 13
A12: DINA DU | B12: ord.1046* | C12: 2025-01-01 | D12: ⚠️ 11 | E12: brown | H12: 22
A13: DINA DU | B13: ord.1046* | C13: 2025-01-01 | D13: ⚠️ 12 | E13: brown | H13: 39
... A16: DINA DU | B16: ord.1046* | C16: 2025-01-01 | D16: ⚠️ 18 | E16: silver-10 gold-5 | H16: 12
A17: COCOMA | B17: COCOMA MAYO 2025 | C17: 2025-05-01 | D17: 654bd7ac2dee3 | E17: ANILLO BV 3 OROS | F17: 5 | G17: 2 | H17: 4.08 | I17: 99.94 | J17: 299.82 | K17: 349.79 | L17: 399.76 | M17: 520
A18: COCOMA | B18: COCOMA MAYO 2025 | C18: 2025-05-01 | D18: 64e78e797f140 | E18: ANILLO BV 3 OROS | F18: 6 | G18: 8 | H18: 4.08 | I18: 99.94 | J18: 299.82 | K18: 349.79 | L18: 399.76 | M18: 520
A19: COCOMA | B19: COCOMA MAYO 2025 | C19: 2025-05-01 | D19: 64e78e7a486d9 | E19: ANILLO BV 3 OROS | F19: 7 | G19: 10 | H19: 4.08 | I19: 99.94 | J19: 299.82 | K19: 349.79 | L19: 399.76 | M19: 520
A20: COCOMA | B20: COCOMA MAYO 2025 | C20: 2025-05-01 | D20: 64e78e7b03ab1 | E20: ANILLO BV 3 OROS | F20: 8 | G20: 3 | H20: 4.08 | I20: 99.94 | J20: 299.82 | K20: 349.79 | L20: 399.76 | M20: 520
A21: COCOMA | B21: COCOMA MAYO 2025 | C21: 2025-05-01 | D21: 64e78e7bb52a6 | E21: ANILLO BV 3 OROS | F21: 9 | G21: 2 | H21: 4.08 | I21: 99.94 | J21: 299.82 | K21: 349.79 | L21: 399.76 | M21: 364
A22: COCOMA | B22: COCOMA MAYO 2025 | C22: 2025-05-01 | D22: 2653039370892 | E22: ANILLO BV GOLD | F22: 6 | G22: 7 | H22: 4.06 | I22: 99.45 | J22: 298.35 | K22: 348.08 | L22: 397.8 | M22: 550
A23: COCOMA | B23: COCOMA MAYO 2025 | C23: 2025-05-01 | D23: 2653039403660 | E23: ANILLO BV GOLD | F23: 7 | G23: 3 | H23: 4.06 | I23: 99.45 | J23: 298.35 | K23: 348.08 | L23: 397.8 | M23: 550
A24: COCOMA | B24: COCOMA MAYO 2025 | C24: 2025-05-01 | D24: 2653039436428 | E24: ANILLO BV GOLD | F24: 8 | G24: 2 | H24: 4.06 | I24: 99.45 | J24: 298.35 | K24: 348.08 | L24: 397.8 | M24: 550
A25: COCOMA | B25: COCOMA MAYO 2025 | C25: 2025-05-01 | D25: 2653039501964 | E25: ANILLO BV GOLD | F25: 10 | G25: 3 | H25: 4.06 | I25: 99.45 | J25: 298.35 | K25: 348.08 | L25: 397.8 | M25: 550
A26: COCOMA | B26: COCOMA MAYO 2025 | C26: 2025-05-01 | D26: 63e0b1e3636a9 | E26: ANILLO BV GOLD DELGADO | F26: 6 | G26: 3 | H26: 7.89 | I26: 193.27 | J26: 579.8 | K26: 676.44 | L26: 773.07 | M26: 678
A27: COCOMA | B27: COCOMA MAYO 2025 | C27: 2025-05-01 | D27: 63e0b1e45372f | E27: ANILLO BV GOLD DELGADO | F27: 7 | G27: 2 | H27: 7.89 | I27: 193.27 | J27: 579.8 | K27: 676.44 | L27: 773.07 | M27: 678
A28: COCOMA | B28: COCOMA MAYO 2025 | C28: 2025-05-01 | D28: 63e0b1f8bb7d5 | E28: ANILLO BV SILVER | F28: 7 | G28: 2 | H28: 4.06 | I28: 99.45 | J28: 298.35 | K28: 348.08 | L28: 397.8 | M28: 520
... A46: HAIFENG | B46: HAIFENG 01/09/2025 | C46: 2025-09-01 | D46: 66176e62285d1 | E46: ANILLO CLASH ROSEGOLD | F46: 10 | G46: 1 | H46: 10 | I46: 212.56 | J46: 637.67 | K46: 743.95 | L46: 850.23 | M46: 850
A47: HAIFENG | B47: HAIFENG 01/09/2025 | C47: 2025-09-01 | D47: 66176e5f8fac7 | E47: ANILLO CLASH ROSEGOLD | F47: 6 | G47: 0 | H47: 10 | M47: 850
A48: HAIFENG | B48: HAIFENG 01/09/2025 | C48: 2025-09-01 | D48: 63ebd3f42d4db | E48: ANILLO CLASH SILVER | F48: 8 | G48: 3 | H48: 10 | I48: 212.56 | J48: 637.67 | K48: 743.95 | L48: 850.23 | M48: 850
A49: HAIFENG | B49: HAIFENG 01/09/2025 | C49: 2025-09-01 | D49: 63ebd3f32bfc9 | E49: ANILLO CLASH SILVER | F49: 7 | G49: 2 | H49: 10 | I49: 212.56 | J49: 637.67 | K49: 743.95 | L49: 850.23 | M49: 850
A50: HAIFENG | B50: HAIFENG 01/09/2025 | C50: 2025-09-01 | D50: 63ebd3f136b3c | E50: ANILLO CLASH SILVER | F50: 5 | G50: 2 | H50: 10 | I50: 212.56 | J50: 637.67 | K50: 743.95 | L50: 850.23 | M50: 850
A51: HAIFENG | B51: HAIFENG 01/09/2025 | C51: 2025-09-01 | D51: 66176cdb9f129 | E51: ANILLO CLAVO GOLD | F51: 6 HIGH QUALITY | G51: 2 | H51: 2.5 | I51: 53.14 | J51: 159.42 | K51: 185.99 | L51: 212.56 | M51: 400
A52: HAIFENG | B52: HAIFENG 01/09/2025 | C52: 2025-09-01 | D52: 66176cdc59c57 | E52: ANILLO CLAVO GOLD | F52: 7 HIGH QUALITY | G52: 2 | H52: 2.5 | I52: 53.14 | J52: 159.42 | K52: 185.99 | L52: 212.56 | M52: 400
A53: HAIFENG | B53: HAIFENG 01/09/2025 | C53: 2025-09-01 | D53: 66176cdce18ea | E53: ANILLO CLAVO GOLD | F53: 8 HIGH QUALITY | G53: 2 | H53: 2.5 | I53: 53.14 | J53: 159.42 | K53: 185.99 | L53: 212.56 | M53: 400
A54: HAIFENG | B54: HAIFENG 01/09/2025 | C54: 2025-09-01 | D54: 66176cdd7cc61 | E54: ANILLO CLAVO GOLD | F54: 9 HIGH QUALITY | G54: 3 | H54: 2.5 | I54: 53.14 | J54: 159.42 | K54: 185.99 | L54: 212.56 | M54: 400
A55: HAIFENG | B55: HAIFENG 01/09/2025 | C55: 2025-09-01 | D55: 66176ce0abf98 | E55: ANILLO CLAVO ROSE GOLD | F55: 5 HIGH QUALITY | G55: 2 | H55: 2.5 | I55: 53.14 | J55: 159.42 | K55: 185.99 | L55: 212.56 | M55: 400
A56: HAIFENG | B56: HAIFENG 01/09/2025 | C56: 2025-09-01 | D56: 66176ce151d29 | E56: ANILLO CLAVO ROSE GOLD | F56: 6 HIGH QUALITY | G56: 3 | H56: 2.5 | I56: 53.14 | J56: 159.42 | K56: 185.99 | L56: 212.56 | M56: 400
A57: HAIFENG | B57: HAIFENG 01/09/2025 | C57: 2025-09-01 | D57: 66176ce1d817d | E57: ANILLO CLAVO ROSE GOLD | F57: 7 HIGH QUALITY | G57: 2 | H57: 2.5 | I57: 53.14 | J57: 159.42 | K57: 185.99 | L57: 212.56 | M57: 400
A58: HAIFENG | B58: HAIFENG 01/09/2025 | C58: 2025-09-01 | D58: 66176cdc142e2 | E58: ANILLO CLAVO SILVER | F58: 7 HIGH QUALITY | G58: 4 | H58: 2.5 | I58: 53.14 | J58: 159.42 | K58: 185.99 | L58: 212.56 | M58: 400
A59: HAIFENG | B59: HAIFENG 01/09/2025 | C59: 2025-09-01 | D59: 63e0b72b646a2 | E59: ANILLO COCO GOLD | F59: 6 | G59: 2 | H59: 1.8 | I59: 38.26 | J59: 114.78 | K59: 133.91 | L59: 153.04 | M59: 400
... A107: HAIFENG | B107: HAIFENG 01/09/2025 | C107: 2025-09-01 | D107: 56481488586892 | E107: ANILLO TRES AROS CON ZIRCONIA | F107: 7 | G107: 4 | H107: 5 | I107: 106.28 | J107: 318.84 | K107: 371.97 | L107: 425.11 | M107: 850
A108: HAIFENG | B108: HAIFENG 01/09/2025 | C108: 2025-09-01 | D108: 56481488554124 | E108: ANILLO TRES AROS CON ZIRCONIA | F108: 6 | G108: 0 | H108: 5 | M108: 1405
A109: HAIFENG | B109: HAIFENG 01/09/2025 | C109: 2025-09-01 | D109: 56481485030668 | E109: ANILLO TRES AROS SILVER/BLACK | F109: 8 | G109: 3 | H109: 5 | I109: 106.28 | J109: 318.84 | K109: 371.97 | L109: 425.11 | M109: 500
A110: HAIFENG | B110: HAIFENG 01/09/2025 | C110: 2025-09-01 | D110: 56481485063436 | E110: ANILLO TRES AROS SILVER/BLACK | F110: 9 | G110: 3 | H110: 5 | I110: 106.28 | J110: 318.84 | K110: 371.97 | L110: 425.11 | M110: 500
A111: HAIFENG | B111: HAIFENG 01/09/2025 | C111: 2025-09-01 | D111: 38334521139841 | E111: ANILLO TRÉBOL GOLD | F111: 6 | G111: 4 | H111: 5.99 | I111: 127.32 | J111: 381.96 | K111: 445.63 | L111: 509.29 | M111: 599
A112: HAIFENG | B112: HAIFENG 01/09/2025 | C112: 2025-09-01 | D112: 64085741294285 | E112: ARETES CLASH GOLD C | F112: Default Title | G112: 2 | H112: 9 | I112: 191.3 | J112: 573.9 | K112: 669.55 | L112: 765.2 | M112: 750
A113: HAIFENG | B113: HAIFENG 01/09/2025 | C113: 2025-09-01 | D113: 64085741359693 | E113: ARETES CLASH ROSE GOLD C | F113: Default Title | G113: 2 | H113: 9 | I113: 191.3 | J113: 573.9 | K113: 669.55 | L113: 765.2 | M113: 742
A114: HAIFENG | B114: HAIFENG 01/09/2025 | C114: 2025-09-01 | D114: 67201534868749 | E114: ARETES CON DOBLE CIERRE T GOLD | F114: Default Title | G114: 4 | H114: 5 | I114: 106.28 | J114: 318.84 | K114: 371.97 | L114: 425.11 | M114: 670
A115: HAIFENG | B115: HAIFENG 01/09/2025 | C115: 2025-09-01 | D115: 56481477937932 | E115: ARETES FULL HEART SILVER | F115: Default Title | G115: 5 | H115: 5 | I115: 106.28 | J115: 318.84 | K115: 371.97 | L115: 425.11 | M115: 450
A116: HAIFENG | B116: HAIFENG 01/09/2025 | C116: 2025-09-01 | D116: 67201531170029 | E116: ARETES LOGO CD CON ZIRCONIA | F116: Default Title | G116: 3 | H116: 5.9 | I116: 125.41 | J116: 376.23 | K116: 438.93 | L116: 501.63 | M116: 487
A117: HAIFENG | B117: HAIFENG 01/09/2025 | C117: 2025-09-01 | D117: 67201531685421 | E117: ARETES LOGO H GOLD | F117: Default Title | G117: 2 | H117: 5 | I117: 106.28 | J117: 318.84 | K117: 371.97 | L117: 425.11 | M117: 480
A118: HAIFENG | B118: HAIFENG 01/09/2025 | C118: 2025-09-01 | D118: 67201531759373 | E118: ARETES LOGO H ROSE GOLD | F118: Default Title | G118: 2 | H118: 5 | I118: 106.28 | J118: 318.84 | K118: 371.97 | L118: 425.11 | M118: 480
A119: HAIFENG | B119: HAIFENG 01/09/2025 | C119: 2025-09-01 | D119: 67201531515469 | E119: ARETES LOGO H SILVER | F119: Default Title | G119: 2 | H119: 5 | I119: 106.28 | J119: 318.84 | K119: 371.97 | L119: 425.11 | M119: 480
A120: HAIFENG | B120: HAIFENG 01/09/2025 | C120: 2025-09-01 | D120: 67201534966797 | E120: ARETES LOVING HEART | F120: Default Title | G120: 5 | H120: 4 | I120: 85.02 | J120: 255.07 | K120: 297.58 | L120: 340.09 | M120: 499
... A161: HAIFENG | B161: HAIFENG 01/09/2025 | C161: 2025-09-01 | D161: 668eee34bc314 | E161: PULSERA DE CUENTAS CON INSIGNIA DE CORAZ√ìN BLUE | F161: 16 cm | G161: 5 | H161: 5 | I161: 106.28 | J161: 318.84 | K161: 371.97 | L161: 425.11 | M161: 550
A162: HAIFENG | B162: HAIFENG 01/09/2025 | C162: 2025-09-01 | D162: 27412601072353 | E162: PULSERA DE TELA TRES AROS ROYAL BLUE | F162: Default Title | G162: 0 | H162: 4.5 | M162: 399
A163: HAIFENG | B163: HAIFENG 01/09/2025 | C163: 2025-09-01 | D163: 66975821021217 | E163: PULSERA DE TELA TRES AROS WINE | F163: Default Title | G163: 0 | H163: 4.5 | M163: 280
A164: HAIFENG | B164: HAIFENG 01/09/2025 | C164: 2025-09-01 | D164: 79274691076205 | E164: PULSERA LOVE DELGADA GOLD | F164: 16cm | G164: 10 | H164: 5 | I164: 106.28 | J164: 318.84 | K164: 371.97 | L164: 425.11 | M164: 499
A165: HAIFENG | B165: HAIFENG 01/09/2025 | C165: 2025-09-01 | D165: 79274691108973 | E165: PULSERA LOVE DELGADA GOLD | F165: 17cm | G165: 10 | H165: 5 | I165: 106.28 | J165: 318.84 | K165: 371.97 | L165: 425.11 | M165: 499
A166: HAIFENG | B166: HAIFENG 01/09/2025 | C166: 2025-09-01 | D166: 63e0c58ca26ac | E166: PULSERA LOVE DELGADA ROSE GOLD | F166: 16 cm | G166: 5 | H166: 5 | I166: 106.28 | J166: 318.84 | K166: 371.97 | L166: 425.11 | M166: 499
A167: HAIFENG | B167: HAIFENG 01/09/2025 | C167: 2025-09-01 | D167: 77724991007277 | E167: PULSERA LOVE DELGADA SILVER | F167: 16cm | G167: 10 | H167: 5 | I167: 106.28 | J167: 318.84 | K167: 371.97 | L167: 425.11 | M167: 499
A168: HAIFENG | B168: HAIFENG 01/09/2025 | C168: 2025-09-01 | D168: 47179791074049 | E168: PULSERA LOVE LOVE GOLD | F168: 16cm con 5cm de extensión | G168: 10 | H168: 5 | I168: 106.28 | J168: 318.84 | K168: 371.97 | L168: 425.11 | M168: 499
A169: HAIFENG | B169: HAIFENG 01/09/2025 | C169: 2025-09-01 | D169: 66360701088653 | E169: PULSERA LUCKY SILVER CD | F169: Default Title | G169: 4 | H169: 6 | I169: 127.53 | J169: 382.6 | K169: 446.37 | L169: 510.14 | M169: 500
A170: HAIFENG | B170: HAIFENG 01/09/2025 | C170: 2025-09-01 | D170: 67201535214413 | E170: PULSERA LUCKY SPRING ROSE GOLD VF | F170: Default Title | G170: 8 | H170: 7 | I170: 148.79 | J170: 446.37 | K170: 520.76 | L170: 595.16 | M170: 599
A171: HAIFENG | B171: HAIFENG 01/09/2025 | C171: 2025-09-01 | D171: 37491253271052 | E171: PULSERA MARIQUITA VF | F171: 17cm con 2cm de extensión | G171: 8 | H171: 6 | I171: 127.53 | J171: 382.6 | K171: 446.37 | L171: 510.14 | M171: 520
A172: HAIFENG | B172: HAIFENG 01/09/2025 | C172: 2025-09-01 | D172: 66075802259373 | E172: PULSERA MONTAIGNE GOLD CD | F172: Default Title | G172: 4 | H172: 7 | I172: 148.79 | J172: 446.37 | K172: 520.76 | L172: 595.16 | M172: 599
A173: HAIFENG | B173: HAIFENG 01/09/2025 | C173: 2025-09-01 | D173: 67201532161837 | E173: PULSERA MSS GOLD | F173: Default Title | G173: 1 | H173: 7 | I173: 148.79 | J173: 446.37 | K173: 520.76 | L173: 595.16 | M173: 599
A174: HAIFENG | B174: HAIFENG 01/09/2025 | C174: 2025-09-01 | D174: 67201532004237 | E174: PULSERA MSS SILVER | F174: Default Title | G174: 1 | H174: 7 | I174: 148.79 | J174: 446.37 | K174: 520.76 | L174: 595.16 | M174: 599
A175: HAIFENG | B175: HAIFENG 01/09/2025 | C175: 2025-09-01 | D175: 82014673388812 | E175: PULSERA SMILE GOLD | F175: 16cm con extensión de 3cm | G175: 8 | H175: 7.5 | I175: 159.42 | J175: 478.25 | K175: 557.96 | L175: 637.67 | M175: 649
... A182: HAIFENG | B182: HAIFENG 01/09/2025 | C182: 2025-09-01 | D182: 66075802307341 | E182: PULSERAS CLAIR D LUNE SILVER CD | F182: Default Title | G182: 3 | H182: 4 | I182: 85.02 | J182: 255.07 | K182: 297.58 | L182: 340.09 | M182: 412
A183: HAIFENG | B183: HAIFENG 01/09/2025 | C183: 2025-09-01 | D183: 67201535214413 | E183: PULSERAS LUCKY SPRING ROSE GOLD VF | F183: Default Title | G183: 0 | H183: 7 | M183: 599
A184: ZOEY | B184: ZOEY 01/09/2025 | C184: 2025-09-01 | D184: BOX | G184: 5 | H184: 10 | I184: 251.18 | J184: 753.54 | K184: 879.12 | L184: 1004.71
A185: ZOEY | B185: ZOEY 01/09/2025 | C185: 2025-09-01 | D185: 94350549840780 | E185: BOLSO A TIEDIE | F185: 31cm de alto x 45.5cm de largo x 18cm de ancho | G185: 6 | H185: 10 | I185: 251.18 | J185: 753.54 | K185: 879.12 | L185: 1004.71 | M185: 1069
A186: ZOEY | B186: ZOEY 01/09/2025 | C186: 2025-09-01 | D186: 94350549840780 | E186: BOLSO A TIEDIE | F186: 31cm de alto x 45.5cm de largo x 18cm de ancho | G186: 3 | H186: 0 | I186: 0 | J186: 0 | K186: 0 | L186: 0 | M186: 1069
A187: ZOEY | B187: ZOEY 01/09/2025 | C187: 2025-09-01 | D187: 66581df1de94d | E187: BOLSO B BLACK | F187: 17cm de largo x 11cm de alto x 8.3cm de ancho | G187: 2 | H187: 45 | I187: 1130.3 | J187: 3390.91 | K187: 3956.06 | L187: 4521.21 | M187: 3800
A188: ZOEY | B188: ZOEY 01/09/2025 | C188: 2025-09-01 | D188: 66ec817ce19fe | E188: BOLSO B BLACK LISA | F188: HIGH QUALITY 23cm de largo x 14.5cm de alto x 10cm de ancho | G188: 1 | H188: 45 | I188: 1130.3 | J188: 3390.91 | K188: 3956.06 | L188: 4521.21 | M188: 3799
A189: ZOEY | B189: ZOEY 01/09/2025 | C189: 2025-09-01 | D189: 654bdbd00f373 | E189: BOLSO B WHITE | F189: 17cm de largo x 11cm de alto x 8.3cm de ancho | G189: 2 | H189: 45 | I189: 1130.3 | J189: 3390.91 | K189: 3956.06 | L189: 4521.21 | M189: 3775
A190: ZOEY | B190: ZOEY 01/09/2025 | C190: 2025-09-01 | D190: 68374516907020 | E190: BOLSO C CLAUDE BLACK | F190: 21.5cm de largo x 11.5cm de alto x 4.5cm de ancho | G190: 4 | H190: 52 | I190: 1306.13 | J190: 3918.38 | K190: 4571.45 | L190: 5224.51 | M190: 5095
A191: ZOEY | B191: ZOEY 01/09/2025 | C191: 2025-09-01 | D191: 63666799441676 | E191: BOLSO C TOTE | F191: 20cm de largo x 21 cm de alto x 11cm de ancho | G191: 2 | H191: 72 | I191: 1808.48 | J191: 5425.45 | K191: 6329.7 | L191: 7233.94 | M191: 6050
A192: ZOEY | B192: ZOEY 01/09/2025 | C192: 2025-09-01 | D192: 43728083210732 | E192: BOLSO CC 22 | F192: 19cm de alto x 23.5cm de ancho | G192: 6 | H192: 50 | I192: 1255.89 | J192: 3767.68 | K192: 4395.62 | L192: 5023.57 | M192: 4190
A193: ZOEY | B193: ZOEY 01/09/2025 | C193: 2025-09-01 | D193: 64571791072897 | E193: BOLSO CC BLACK | F193: 25cm de largo x 17cm de alto x 6cm de ancho | G193: 7 | H193: 48 | I193: 1205.66 | J193: 3616.97 | K193: 4219.8 | L193: 4822.63 | M193: 5089
A194: ZOEY | B194: ZOEY 01/09/2025 | C194: 2025-09-01 | D194: 43728087914796 | E194: BOLSO CD 30 MONTAIGNE BLACK | F194: 12cm de alto x 20cm de largo x 4cm de ancho | G194: 2 | H194: 52 | I194: 1306.13 | J194: 3918.38 | K194: 4571.45 | L194: 5224.51 | M194: 5520
